Workbook

Sheet village-reports
B1: =_xludf.textjoin("",TRUE,"Panchayat Report: ",J4,", ",G4, " Mandal") -> #NAME? | S1: Assembly | T1: Mandal | U1: Panchayat | W1: Year | X1: TDP | Y1: YSRCP | Z1: JSP
S2: Tuni | T2: =IFERROR(__xludf.DUMMYFUNCTION("unique(filter('Back End'!B:B,'Back End'!A:A=D4))"),"Prathipadu") -> Prathipadu | U2: =IFERROR(__xludf.DUMMYFUNCTION("unique(filter('Back End'!C:C,'Back End'!A:A=D4,'Back End'!B:B=G4))"),"Bavuruvaka") -> Bavuruvaka | W2: 2024 | X2: =C24 -> #N/A | Y2: =D24 -> 0 | Z2: =E24 -> 0
S3: Prathipadu | T3: =IFERROR(__xludf.DUMMYFUNCTION("""COMPUTED_VALUE"""),"Rowthulapudi") -> Rowthulapudi | U3: =IFERROR(__xludf.DUMMYFUNCTION("""COMPUTED_VALUE"""),"Buradakota") -> Buradakota | W3: 2019 | X3: =C26 -> 0.54149378 | Y3: =D26 -> 0.34439834 | Z3: =E26 -> 0.010373444
C4: Assembly | D4: Prathipadu | F4: Mandal | G4: Prathipadu | I4: Panchayat | J4: Buradakota | S4: Pithapuram | T4: =IFERROR(__xludf.DUMMYFUNCTION("""COMPUTED_VALUE"""),"Sankhavaram") -> Sankhavaram | U4: =IFERROR(__xludf.DUMMYFUNCTION("""COMPUTED_VALUE"""),"Chinasankarlapudi") -> Chinasankarlapudi | W4: 2014 | X4: =C28 -> 0.44239631 | Y4: =D28 -> 0.099078341 | Z4: =E28 -> 0
S5: Kakinada Rural | T5: =IFERROR(__xludf.DUMMYFUNCTION("""COMPUTED_VALUE"""),"Yeleswaram") -> Yeleswaram | U5: =IFERROR(__xludf.DUMMYFUNCTION("""COMPUTED_VALUE"""),"Chintaluru") -> Chintaluru
B6: Current Sarpanch | D6: =IFERROR(__xludf.DUMMYFUNCTION("filter(Data!F:F,Data!C:C=G4,Data!D:D=J4)"),"Chinthala Chinnalamma - 9493461257") -> Chinthala Chinnalamma - 9493461257 | F6: Party | H6: =IFERROR(__xludf.DUMMYFUNCTION("filter(Data!G:G,Data!C:C=G4,Data!D:D=J4)"),"") | J6: TDP - Current Position | L6: =IFERROR(__xludf.DUMMYFUNCTION("filter(Data!H:H,Data!C:C=G4,Data!D:D=J4)"),"") | S6: Peddapuram | T6: =IFERROR(__xludf.DUMMYFUNCTION("""COMPUTED_VALUE"""),"Yeleswaram Town") -> Yeleswaram Town | U6: =IFERROR(__xludf.DUMMYFUNCTION("""COMPUTED_VALUE"""),"Dharmavaram") -> Dharmavaram
S7: Kakinada Urban | U7: =IFERROR(__xludf.DUMMYFUNCTION("""COMPUTED_VALUE"""),"Gajjanapudi") -> Gajjanapudi
B8: Demographics | H8: Prominent Castes | S8: Jaggampeta | U8: =IFERROR(__xludf.DUMMYFUNCTION("""COMPUTED_VALUE"""),"Gokavaram") -> Gokavaram
U9: =IFERROR(__xludf.DUMMYFUNCTION("""COMPUTED_VALUE"""),"Lampakalova") -> Lampakalova
B10: =_xludf.textjoin("",TRUE,"Age Wise Electors",CHAR(10),"Total: ",D16+F16) -> #NAME? | H10: S No. | I10: Caste | K10: Voters | L10: Inclination | U10: =IFERROR(__xludf.DUMMYFUNCTION("""COMPUTED_VALUE"""),"Pandavulapalem") -> Pandavulapalem
B11: Age | D11: Male | F11: Female | H11: 1 | I11: =IFERROR(__xludf.DUMMYFUNCTION("filter('Caste Data'!D:D,'Caste Data'!A:A=D$4,'Caste Data'!B:B=G$4,'Caste Data'!C:C=J$4,'Caste Data'!G:G=H11)"),"Valmiki") -> Valmiki | K11: =IFERROR(__xludf.DUMMYFUNCTION("filter('Caste Data'!F:F,'Caste Data'!A:A=D$4,'Caste Data'!B:B=G$4,'Caste Data'!C:C=J$4,'Caste Data'!G:G=H11)"),259) -> 259 | U11: =IFERROR(__xludf.DUMMYFUNCTION("""COMPUTED_VALUE"""),"Peda Sankarlapudi") -> Peda Sankarlapudi
B12: 18-24 | D12: =IFERROR(__xludf.DUMMYFUNCTION("transpose(filter({Demography!S2:V1014,Demography!L2:L1014},Demography!A2:A1014=D4,Demography!B2:B1014=G4,Demography!D2:D1014=J4))"),33) -> 33 | F12: =IFERROR(__xludf.DUMMYFUNCTION("transpose(filter({Demography!O2:R1014, Demography!M2:M1014},Demography!A2:A1014=D4,Demography!B2:B1014=G4,Demography!D2:D1014=J4))"),20) -> 20 | H12: 2 | I12: =IFERROR(__xludf.DUMMYFUNCTION("filter('Caste Data'!D:D,'Caste Data'!A:A=D$4,'Caste Data'!B:B=G$4,'Caste Data'!C:C=J$4,'Caste Data'!G:G=H12)"),"K.Kapu") -> K.Kapu | K12: =IFERROR(__xludf.DUMMYFUNCTION("filter('Caste Data'!F:F,'Caste Data'!A:A=D$4,'Caste Data'!B:B=G$4,'Caste Data'!C:C=J$4,'Caste Data'!G:G=H12)"),257) -> 257 | U12: =IFERROR(__xludf.DUMMYFUNCTION("""COMPUTED_VALUE"""),"Peddipalem") -> Peddipalem
B13: 25-44 | D13: =IFERROR(__xludf.DUMMYFUNCTION("""COMPUTED_VALUE"""),155) -> 155 | F13: =IFERROR(__xludf.DUMMYFUNCTION("""COMPUTED_VALUE"""),165) -> 165 | H13: 3 | I13: =IFERROR(__xludf.DUMMYFUNCTION("filter('Caste Data'!D:D,'Caste Data'!A:A=D$4,'Caste Data'!B:B=G$4,'Caste Data'!C:C=J$4,'Caste Data'!G:G=H13)"),"K.Dora") -> K.Dora | K13: =IFERROR(__xludf.DUMMYFUNCTION("filter('Caste Data'!F:F,'Caste Data'!A:A=D$4,'Caste Data'!B:B=G$4,'Caste Data'!C:C=J$4,'Caste Data'!G:G=H13)"),200) -> 200 | U13: =IFERROR(__xludf.DUMMYFUNCTION("""COMPUTED_VALUE"""),"Pothuluru") -> Pothuluru
B14: 45-59 | D14: =IFERROR(__xludf.DUMMYFUNCTION("""COMPUTED_VALUE"""),55) -> 55 | F14: =IFERROR(__xludf.DUMMYFUNCTION("""COMPUTED_VALUE"""),75) -> 75 | H14: 4 | I14: =IFERROR(__xludf.DUMMYFUNCTION("filter('Caste Data'!D:D,'Caste Data'!A:A=D$4,'Caste Data'!B:B=G$4,'Caste Data'!C:C=J$4,'Caste Data'!G:G=H14)"),"Kapu") -> Kapu | K14: =IFERROR(__xludf.DUMMYFUNCTION("filter('Caste Data'!F:F,'Caste Data'!A:A=D$4,'Caste Data'!B:B=G$4,'Caste Data'!C:C=J$4,'Caste Data'!G:G=H14)"),10) -> 10 | U14: =IFERROR(__xludf.DUMMYFUNCTION("""COMPUTED_VALUE"""),"Prathipadu") -> Prathipadu
B15: 60+ | D15: =IFERROR(__xludf.DUMMYFUNCTION("""COMPUTED_VALUE"""),25) -> 25 | F15: =IFERROR(__xludf.DUMMYFUNCTION("""COMPUTED_VALUE"""),29) -> 29 | H15: 5 | I15: =IFERROR(__xludf.DUMMYFUNCTION("filter('Caste Data'!D:D,'Caste Data'!A:A=D$4,'Caste Data'!B:B=G$4,'Caste Data'!C:C=J$4,'Caste Data'!G:G=H15)"),"Yadava") -> Yadava | K15: =IFERROR(__xludf.DUMMYFUNCTION("filter('Caste Data'!F:F,'Caste Data'!A:A=D$4,'Caste Data'!B:B=G$4,'Caste Data'!C:C=J$4,'Caste Data'!G:G=H15)"),6) -> 6 | U15: =IFERROR(__xludf.DUMMYFUNCTION("""COMPUTED_VALUE"""),"Rachapalle") -> Rachapalle
B16: Total | D16: =IFERROR(__xludf.DUMMYFUNCTION("""COMPUTED_VALUE"""),268) -> 268 | F16: =IFERROR(__xludf.DUMMYFUNCTION("""COMPUTED_VALUE"""),289) -> 289 | H16: 6 | I16: =IFERROR(__xludf.DUMMYFUNCTION("filter('Caste Data'!D:D,'Caste Data'!A:A=D$4,'Caste Data'!B:B=G$4,'Caste Data'!C:C=J$4,'Caste Data'!G:G=H16)"),"Others BCs") -> Others BCs | K16: =IFERROR(__xludf.DUMMYFUNCTION("filter('Caste Data'!F:F,'Caste Data'!A:A=D$4,'Caste Data'!B:B=G$4,'Caste Data'!C:C=J$4,'Caste Data'!G:G=H16)"),4) -> 4 | U16: =IFERROR(__xludf.DUMMYFUNCTION("""COMPUTED_VALUE"""),"Rowthulapalem") -> Rowthulapalem
B17: Cohort Groups | D17: =IFERROR(__xludf.DUMMYFUNCTION("filter('Raw Data - Field Input'!H2:H1014,'Raw Data - Field Input'!A2:A1014=D4,'Raw Data - Field Input'!B2:B1014=G4,'Raw Data - Field Input'!D2:D1014=J4)"),"1.paddy farming 2.cashew farming") -> 1.paddy farming 2.cashew farming | H17: 7 | I17: =IFERROR(__xludf.DUMMYFUNCTION("filter('Caste Data'!D:D,'Caste Data'!A:A=D$4,'Caste Data'!B:B=G$4,'Caste Data'!C:C=J$4,'Caste Data'!G:G=H17)"),"Others OCs") -> Others OCs | K17: =IFERROR(__xludf.DUMMYFUNCTION("filter('Caste Data'!F:F,'Caste Data'!A:A=D$4,'Caste Data'!B:B=G$4,'Caste Data'!C:C=J$4,'Caste Data'!G:G=H17)"),4) -> 4 | U17: =IFERROR(__xludf.DUMMYFUNCTION("""COMPUTED_VALUE"""),"Sarabhavaram") -> Sarabhavaram
H18: 8 | I18: =IFERROR(__xludf.DUMMYFUNCTION("filter('Caste Data'!D:D,'Caste Data'!A:A=D$4,'Caste Data'!B:B=G$4,'Caste Data'!C:C=J$4,'Caste Data'!G:G=H18)"),"#N/A") -> #N/A | K18: =IFERROR(__xludf.DUMMYFUNCTION("filter('Caste Data'!F:F,'Caste Data'!A:A=D$4,'Caste Data'!B:B=G$4,'Caste Data'!C:C=J$4,'Caste Data'!G:G=H18)"),"#N/A") -> #N/A | U18: =IFERROR(__xludf.DUMMYFUNCTION("""COMPUTED_VALUE"""),"T Rayavaram") -> T Rayavaram
H19: 9 | I19: =IFERROR(__xludf.DUMMYFUNCTION("filter('Caste Data'!D:D,'Caste Data'!A:A=D$4,'Caste Data'!B:B=G$4,'Caste Data'!C:C=J$4,'Caste Data'!G:G=H19)"),"#N/A") -> #N/A | K19: =IFERROR(__xludf.DUMMYFUNCTION("filter('Caste Data'!F:F,'Caste Data'!A:A=D$4,'Caste Data'!B:B=G$4,'Caste Data'!C:C=J$4,'Caste Data'!G:G=H19)"),"#N/A") -> #N/A | U19: =IFERROR(__xludf.DUMMYFUNCTION("""COMPUTED_VALUE"""),"U.Jagannadhapuram") -> U.Jagannadhapuram
H20: 10 | I20: =IFERROR(__xludf.DUMMYFUNCTION("filter('Caste Data'!D:D,'Caste Data'!A:A=D$4,'Caste Data'!B:B=G$4,'Caste Data'!C:C=J$4,'Caste Data'!G:G=H20)"),"#N/A") -> #N/A | K20: =IFERROR(__xludf.DUMMYFUNCTION("filter('Caste Data'!F:F,'Caste Data'!A:A=D$4,'Caste Data'!B:B=G$4,'Caste Data'!C:C=J$4,'Caste Data'!G:G=H20)"),"#N/A") -> #N/A | U20: =IFERROR(__xludf.DUMMYFUNCTION("""COMPUTED_VALUE"""),"Uttarakanchi") -> Uttarakanchi
B21: Retro | U21: =IFERROR(__xludf.DUMMYFUNCTION("""COMPUTED_VALUE"""),"Vakapalle") -> Vakapalle
U22: =IFERROR(__xludf.DUMMYFUNCTION("""COMPUTED_VALUE"""),"Venkatanagaram") -> Venkatanagaram
B23: Election | C23: TDP | D23: YSRCP | E23: JSP | F23: BJP | G23: INC | H23: PRP | I23: Others | J23: AE Results | U23: =IFERROR(__xludf.DUMMYFUNCTION("""COMPUTED_VALUE"""),"Vommangi") -> Vommangi
B24: 2024 AE | C24: =IFERROR(__xludf.DUMMYFUNCTION("filter('Village-F20-2024'!W:AC,'Village-F20-2024'!D:D=D$4,'Village-F20-2024'!E:E=G$4,'Village-F20-2024'!F:F=J$4)"),"#N/A") -> #N/A | U24: =IFERROR(__xludf.DUMMYFUNCTION("""COMPUTED_VALUE"""),"Yeluru") -> Yeluru
B25: 2024 PE
B26: 2019 AE | C26: =IFERROR(__xludf.DUMMYFUNCTION("filter('Retro Villagewise'!L2:R1014,'Retro Villagewise'!A2:A1014=D4,'Retro Villagewise'!B2:B1014=G4,'Retro Villagewise'!D2:D1014=J4)"),0.5414937759) -> 0.54149378 | D26: =IFERROR(__xludf.DUMMYFUNCTION("""COMPUTED_VALUE"""),0.3443983402) -> 0.34439834 | E26: =IFERROR(__xludf.DUMMYFUNCTION("""COMPUTED_VALUE"""),0.01037344398) -> 0.010373444 | F26: =IFERROR(__xludf.DUMMYFUNCTION("""COMPUTED_VALUE"""),0) -> 0 | G26: =IFERROR(__xludf.DUMMYFUNCTION("""COMPUTED_VALUE"""),0) -> 0 | H26: =IFERROR(__xludf.DUMMYFUNCTION("""COMPUTED_VALUE"""),0) -> 0 | I26: =IFERROR(__xludf.DUMMYFUNCTION("""COMPUTED_VALUE"""),0.1037344398) -> 0.10373444
B27: 2019 PE | C27: =IFERROR(__xludf.DUMMYFUNCTION("filter('Retro Villagewise'!E2:K1014,'Retro Villagewise'!A2:A1014=D4,'Retro Villagewise'!B2:B1014=G4,'Retro Villagewise'!D2:D1014=J4)"),0.7697095436) -> 0.76970954 | D27: =IFERROR(__xludf.DUMMYFUNCTION("""COMPUTED_VALUE"""),0.1095435685) -> 0.10954357 | E27: =IFERROR(__xludf.DUMMYFUNCTION("""COMPUTED_VALUE"""),0.01244813278) -> 0.012448133 | F27: =IFERROR(__xludf.DUMMYFUNCTION("""COMPUTED_VALUE"""),0.01659751037) -> 0.01659751 | G27: =IFERROR(__xludf.DUMMYFUNCTION("""COMPUTED_VALUE"""),0) -> 0 | H27: =IFERROR(__xludf.DUMMYFUNCTION("""COMPUTED_VALUE"""),0) -> 0 | I27: =IFERROR(__xludf.DUMMYFUNCTION("""COMPUTED_VALUE"""),0.8941908714) -> 0.89419087
B28: 2014 AE | C28: =IFERROR(__xludf.DUMMYFUNCTION("filter('Retro Villagewise'!Z2:AF1014,'Retro Villagewise'!A2:A1014=D4,'Retro Villagewise'!B2:B1014=G4,'Retro Villagewise'!D2:D1014=J4)"),0.4423963134) -> 0.44239631 | D28: =IFERROR(__xludf.DUMMYFUNCTION("""COMPUTED_VALUE"""),0.09907834101) -> 0.099078341 | E28: =IFERROR(__xludf.DUMMYFUNCTION("""COMPUTED_VALUE"""),0) -> 0 | F28: =IFERROR(__xludf.DUMMYFUNCTION("""COMPUTED_VALUE"""),0) -> 0 | G28: =IFERROR(__xludf.DUMMYFUNCTION("""COMPUTED_VALUE"""),0.05529953917) -> 0.055299539 | H28: =IFERROR(__xludf.DUMMYFUNCTION("""COMPUTED_VALUE"""),0) -> 0 | I28: =IFERROR(__xludf.DUMMYFUNCTION("""COMPUTED_VALUE"""),0.4032258065) -> 0.40322581
B29: 2014 PE | C29: =IFERROR(__xludf.DUMMYFUNCTION("filter('Retro Villagewise'!S2:Y1014,'Retro Villagewise'!A2:A1014=D4,'Retro Villagewise'!B2:B1014=G4,'Retro Villagewise'!D2:D1014=J4)"),0.4907834101) -> 0.49078341 | D29: =IFERROR(__xludf.DUMMYFUNCTION("""COMPUTED_VALUE"""),0.09447004608) -> 0.094470046 | E29: =IFERROR(__xludf.DUMMYFUNCTION("""COMPUTED_VALUE"""),0) -> 0 | F29: =IFERROR(__xludf.DUMMYFUNCTION("""COMPUTED_VALUE"""),0) -> 0 | G29: =IFERROR(__xludf.DUMMYFUNCTION("""COMPUTED_VALUE"""),0.01382488479) -> 0.013824885 | H29: =IFERROR(__xludf.DUMMYFUNCTION("""COMPUTED_VALUE"""),0) -> 0 | I29: =IFERROR(__xludf.DUMMYFUNCTION("""COMPUTED_VALUE"""),0.400921659) -> 0.40092166
B30: 2009 AE | C30: =IFERROR(__xludf.DUMMYFUNCTION("filter('Retro Villagewise'!AN2:AT1014,'Retro Villagewise'!A2:A1014=D4,'Retro Villagewise'!B2:B1014=G4,'Retro Villagewise'!D2:D1014=J4)"),0.4293478261) -> 0.42934783 | D30: =IFERROR(__xludf.DUMMYFUNCTION("""COMPUTED_VALUE"""),0) -> 0 | E30: =IFERROR(__xludf.DUMMYFUNCTION("""COMPUTED_VALUE"""),0) -> 0 | F30: =IFERROR(__xludf.DUMMYFUNCTION("""COMPUTED_VALUE"""),0) -> 0 | G30: =IFERROR(__xludf.DUMMYFUNCTION("""COMPUTED_VALUE"""),0.1086956522) -> 0.10869565 | H30: =IFERROR(__xludf.DUMMYFUNCTION("""COMPUTED_VALUE"""),0.2092391304) -> 0.20923913 | I30: =IFERROR(__xludf.DUMMYFUNCTION("""COMPUTED_VALUE"""),0.2527173913) -> 0.25271739
B31: 2009 PE | C31: =IFERROR(__xludf.DUMMYFUNCTION("filter('Retro Villagewise'!AG2:AM1014,'Retro Villagewise'!A2:A1014=D4,'Retro Villagewise'!B2:B1014=G4,'Retro Villagewise'!D2:D1014=J4)"),0.4048913043) -> 0.4048913 | D31: =IFERROR(__xludf.DUMMYFUNCTION("""COMPUTED_VALUE"""),0) -> 0 | E31: =IFERROR(__xludf.DUMMYFUNCTION("""COMPUTED_VALUE"""),0) -> 0 | F31: =IFERROR(__xludf.DUMMYFUNCTION("""COMPUTED_VALUE"""),0.01630434783) -> 0.016304348 | G31: =IFERROR(__xludf.DUMMYFUNCTION("""COMPUTED_VALUE"""),0.08967391304) -> 0.089673913 | H31: =IFERROR(__xludf.DUMMYFUNCTION("""COMPUTED_VALUE"""),0.2255434783) -> 0.22554348 | I31: =IFERROR(__xludf.DUMMYFUNCTION("""COMPUTED_VALUE"""),0.2635869565) -> 0.26358696
B32: 2024 AE Story | H32: 2019 AE Story
B33: =IFERROR(__xludf.DUMMYFUNCTION("filter(Data!I:I,Data!C:C=G4,Data!D:D=J4)"),"") | H33: =IFERROR(__xludf.DUMMYFUNCTION("filter('Raw Data - Field Input'!J2:J1014,'Raw Data - Field Input'!A2:A1014=D4,'Raw Data - Field Input'!B2:B1014=G4,'Raw Data - Field Input'!D2:D1014=J4)"),"1. This is ST Konda dora dominant village which is majorly inclined towards YCP party . 2.TDP banked on Kapu along with Bc community of settibalija. 3.TDP failed to fulfil the promises of laying roads and hence there is a shift of vote bank towards YCP pa"&"rty to give it a one chance.") -> 1. This is ST Konda dora dominant village which is majorly inclined towards YCP party . 2.TDP banked on Kapu along with Bc community of settibalija. 3.TDP failed to fulfil the promises of laying roads and hence there is a shift of vote bank towards YCP party to give it a one chance.
B40: Sarpanch Election Scenario
B42: 2020 Election Scenario | H42: Expected Contestants for 2026 Elections
B43: =IFERROR(__xludf.DUMMYFUNCTION("filter(Data!J:J,Data!C:C=G4,Data!D:D=J4)"),"") | H43: Possible Reservation | K43: =IFERROR(__xludf.DUMMYFUNCTION("filter(Data!K:K,Data!C:C=G4,Data!D:D=J4)"),"")
H44: =IFERROR(__xludf.DUMMYFUNCTION("filter(Data!L:L,Data!C:C=G4,Data!D:D=J4)"),"")
B48: Key Leaders
B50: S No | C50: Name | F50: Caste | H50: Category | I50: Party | J50: Designation | L50: Mobile | M50: Influence
B51: 1 | C51: =IFERROR(__xludf.DUMMYFUNCTION("filter('Key Leaders'!E:E,'Key Leaders'!D:D=B51,'Key Leaders'!A:A=D$4,'Key Leaders'!B:B=G$4,'Key Leaders'!C:C=J$4)"),"#N/A") -> #N/A | F51: =IFERROR(__xludf.DUMMYFUNCTION("filter('Key Leaders'!F:F,'Key Leaders'!D:D=B51,'Key Leaders'!A:A=D$4,'Key Leaders'!B:B=G$4,'Key Leaders'!C:C=J$4)"),"#N/A") -> #N/A | H51: =IFERROR(__xludf.DUMMYFUNCTION("filter('Key Leaders'!G:H,'Key Leaders'!D:D=B51,'Key Leaders'!A:A=D$4,'Key Leaders'!B:B=G$4,'Key Leaders'!C:C=J$4)"),"#N/A") -> #N/A | J51: =IFERROR(__xludf.DUMMYFUNCTION("filter('Key Leaders'!I:I,'Key Leaders'!D:D=B51,'Key Leaders'!A:A=D$4,'Key Leaders'!B:B=G$4,'Key Leaders'!C:C=J$4)"),"#N/A") -> #N/A | L51: =IFERROR(__xludf.DUMMYFUNCTION("filter('Key Leaders'!J:K,'Key Leaders'!D:D=B51,'Key Leaders'!A:A=D$4,'Key Leaders'!B:B=G$4,'Key Leaders'!C:C=J$4)"),"#N/A") -> #N/A
B52: 2 | C52: =IFERROR(__xludf.DUMMYFUNCTION("filter('Key Leaders'!E:E,'Key Leaders'!D:D=B52,'Key Leaders'!A:A=D$4,'Key Leaders'!B:B=G$4,'Key Leaders'!C:C=J$4)"),"#N/A") -> #N/A | F52: =IFERROR(__xludf.DUMMYFUNCTION("filter('Key Leaders'!F:F,'Key Leaders'!D:D=B52,'Key Leaders'!A:A=D$4,'Key Leaders'!B:B=G$4,'Key Leaders'!C:C=J$4)"),"#N/A") -> #N/A | H52: =IFERROR(__xludf.DUMMYFUNCTION("filter('Key Leaders'!G:H,'Key Leaders'!D:D=B52,'Key Leaders'!A:A=D$4,'Key Leaders'!B:B=G$4,'Key Leaders'!C:C=J$4)"),"#N/A") -> #N/A | J52: =IFERROR(__xludf.DUMMYFUNCTION("filter('Key Leaders'!I:I,'Key Leaders'!D:D=B52,'Key Leaders'!A:A=D$4,'Key Leaders'!B:B=G$4,'Key Leaders'!C:C=J$4)"),"#N/A") -> #N/A | L52: =IFERROR(__xludf.DUMMYFUNCTION("filter('Key Leaders'!J:K,'Key Leaders'!D:D=B52,'Key Leaders'!A:A=D$4,'Key Leaders'!B:B=G$4,'Key Leaders'!C:C=J$4)"),"#N/A") -> #N/A
B53: 3 | C53: =IFERROR(__xludf.DUMMYFUNCTION("filter('Key Leaders'!E:E,'Key Leaders'!D:D=B53,'Key Leaders'!A:A=D$4,'Key Leaders'!B:B=G$4,'Key Leaders'!C:C=J$4)"),"#N/A") -> #N/A | F53: =IFERROR(__xludf.DUMMYFUNCTION("filter('Key Leaders'!F:F,'Key Leaders'!D:D=B53,'Key Leaders'!A:A=D$4,'Key Leaders'!B:B=G$4,'Key Leaders'!C:C=J$4)"),"#N/A") -> #N/A | H53: =IFERROR(__xludf.DUMMYFUNCTION("filter('Key Leaders'!G:H,'Key Leaders'!D:D=B53,'Key Leaders'!A:A=D$4,'Key Leaders'!B:B=G$4,'Key Leaders'!C:C=J$4)"),"#N/A") -> #N/A | J53: =IFERROR(__xludf.DUMMYFUNCTION("filter('Key Leaders'!I:I,'Key Leaders'!D:D=B53,'Key Leaders'!A:A=D$4,'Key Leaders'!B:B=G$4,'Key Leaders'!C:C=J$4)"),"#N/A") -> #N/A | L53: =IFERROR(__xludf.DUMMYFUNCTION("filter('Key Leaders'!J:K,'Key Leaders'!D:D=B53,'Key Leaders'!A:A=D$4,'Key Leaders'!B:B=G$4,'Key Leaders'!C:C=J$4)"),"#N/A") -> #N/A
B54: 4 | C54: =IFERROR(__xludf.DUMMYFUNCTION("filter('Key Leaders'!E:E,'Key Leaders'!D:D=B54,'Key Leaders'!A:A=D$4,'Key Leaders'!B:B=G$4,'Key Leaders'!C:C=J$4)"),"#N/A") -> #N/A | F54: =IFERROR(__xludf.DUMMYFUNCTION("filter('Key Leaders'!F:F,'Key Leaders'!D:D=B54,'Key Leaders'!A:A=D$4,'Key Leaders'!B:B=G$4,'Key Leaders'!C:C=J$4)"),"#N/A") -> #N/A | H54: =IFERROR(__xludf.DUMMYFUNCTION("filter('Key Leaders'!G:H,'Key Leaders'!D:D=B54,'Key Leaders'!A:A=D$4,'Key Leaders'!B:B=G$4,'Key Leaders'!C:C=J$4)"),"#N/A") -> #N/A | J54: =IFERROR(__xludf.DUMMYFUNCTION("filter('Key Leaders'!I:I,'Key Leaders'!D:D=B54,'Key Leaders'!A:A=D$4,'Key Leaders'!B:B=G$4,'Key Leaders'!C:C=J$4)"),"#N/A") -> #N/A | L54: =IFERROR(__xludf.DUMMYFUNCTION("filter('Key Leaders'!J:K,'Key Leaders'!D:D=B54,'Key Leaders'!A:A=D$4,'Key Leaders'!B:B=G$4,'Key Leaders'!C:C=J$4)"),"#N/A") -> #N/A
B55: 5 | C55: =IFERROR(__xludf.DUMMYFUNCTION("filter('Key Leaders'!E:E,'Key Leaders'!D:D=B55,'Key Leaders'!A:A=D$4,'Key Leaders'!B:B=G$4,'Key Leaders'!C:C=J$4)"),"#N/A") -> #N/A | F55: =IFERROR(__xludf.DUMMYFUNCTION("filter('Key Leaders'!F:F,'Key Leaders'!D:D=B55,'Key Leaders'!A:A=D$4,'Key Leaders'!B:B=G$4,'Key Leaders'!C:C=J$4)"),"#N/A") -> #N/A | H55: =IFERROR(__xludf.DUMMYFUNCTION("filter('Key Leaders'!G:H,'Key Leaders'!D:D=B55,'Key Leaders'!A:A=D$4,'Key Leaders'!B:B=G$4,'Key Leaders'!C:C=J$4)"),"#N/A") -> #N/A | J55: =IFERROR(__xludf.DUMMYFUNCTION("filter('Key Leaders'!I:I,'Key Leaders'!D:D=B55,'Key Leaders'!A:A=D$4,'Key Leaders'!B:B=G$4,'Key Leaders'!C:C=J$4)"),"#N/A") -> #N/A | L55: =IFERROR(__xludf.DUMMYFUNCTION("filter('Key Leaders'!J:K,'Key Leaders'!D:D=B55,'Key Leaders'!A:A=D$4,'Key Leaders'!B:B=G$4,'Key Leaders'!C:C=J$4)"),"#N/A") -> #N/A
B56: 6 | C56: =IFERROR(__xludf.DUMMYFUNCTION("filter('Key Leaders'!E:E,'Key Leaders'!D:D=B56,'Key Leaders'!A:A=D$4,'Key Leaders'!B:B=G$4,'Key Leaders'!C:C=J$4)"),"#N/A") -> #N/A | F56: =IFERROR(__xludf.DUMMYFUNCTION("filter('Key Leaders'!F:F,'Key Leaders'!D:D=B56,'Key Leaders'!A:A=D$4,'Key Leaders'!B:B=G$4,'Key Leaders'!C:C=J$4)"),"#N/A") -> #N/A | H56: =IFERROR(__xludf.DUMMYFUNCTION("filter('Key Leaders'!G:H,'Key Leaders'!D:D=B56,'Key Leaders'!A:A=D$4,'Key Leaders'!B:B=G$4,'Key Leaders'!C:C=J$4)"),"#N/A") -> #N/A | J56: =IFERROR(__xludf.DUMMYFUNCTION("filter('Key Leaders'!I:I,'Key Leaders'!D:D=B56,'Key Leaders'!A:A=D$4,'Key Leaders'!B:B=G$4,'Key Leaders'!C:C=J$4)"),"#N/A") -> #N/A | L56: =IFERROR(__xludf.DUMMYFUNCTION("filter('Key Leaders'!J:K,'Key Leaders'!D:D=B56,'Key Leaders'!A:A=D$4,'Key Leaders'!B:B=G$4,'Key Leaders'!C:C=J$4)"),"#N/A") -> #N/A
B57: 7 | C57: =IFERROR(__xludf.DUMMYFUNCTION("filter('Key Leaders'!E:E,'Key Leaders'!D:D=B57,'Key Leaders'!A:A=D$4,'Key Leaders'!B:B=G$4,'Key Leaders'!C:C=J$4)"),"#N/A") -> #N/A | F57: =IFERROR(__xludf.DUMMYFUNCTION("filter('Key Leaders'!F:F,'Key Leaders'!D:D=B57,'Key Leaders'!A:A=D$4,'Key Leaders'!B:B=G$4,'Key Leaders'!C:C=J$4)"),"#N/A") -> #N/A | H57: =IFERROR(__xludf.DUMMYFUNCTION("filter('Key Leaders'!G:H,'Key Leaders'!D:D=B57,'Key Leaders'!A:A=D$4,'Key Leaders'!B:B=G$4,'Key Leaders'!C:C=J$4)"),"#N/A") -> #N/A | J57: =IFERROR(__xludf.DUMMYFUNCTION("filter('Key Leaders'!I:I,'Key Leaders'!D:D=B57,'Key Leaders'!A:A=D$4,'Key Leaders'!B:B=G$4,'Key Leaders'!C:C=J$4)"),"#N/A") -> #N/A | L57: =IFERROR(__xludf.DUMMYFUNCTION("filter('Key Leaders'!J:K,'Key Leaders'!D:D=B57,'Key Leaders'!A:A=D$4,'Key Leaders'!B:B=G$4,'Key Leaders'!C:C=J$4)"),"#N/A") -> #N/A
B58: Internal Factions | H58: Chargesheet Points
B59: =IFERROR(__xludf.DUMMYFUNCTION("filter(Data!N:N,Data!C:C=G4,Data!D:D=J4)"),"") | H59: =IFERROR(__xludf.DUMMYFUNCTION("filter(Data!Q:Q,Data!C:C=G4,Data!D:D=J4)"),"")
B69: Key Development Activities | F69: Major Issues | J69: Additional Information
B70: =IFERROR(__xludf.DUMMYFUNCTION("filter(Data!O:O,Data!C:C=G4,Data!D:D=J4)"),"") | F70: =IFERROR(__xludf.DUMMYFUNCTION("filter(Data!P:P,Data!C:C=G4,Data!D:D=J4)"),"") | J70: =IFERROR(__xludf.DUMMYFUNCTION("filter(Data!R:R,Data!C:C=G4,Data!D:D=J4)"),"")

Sheet Demography
A1: Assembly | B1: Mandal | D1: Village | E1: Categorisation PE | F1: Total PSs | G1: Sarpanch Name | H1: Sarpanch Party | I1: Reservation | J1: Sarpanch Caste | K1: Sarpanch Mobile No | L1: Male Voters | M1: Female Voters | N1: Total Voters | O1: 18-24 (F) Voters | P1: 25-44 (F) Voters | Q1: 45-59 (F) Voters | R1: 60+ (F) Voters | S1: 18-24 (M) Voters | T1: 25-44 (M) Voters | U1: 45-59 (M) Voters | V1: 60+ (M) Voters | W1: 18-24 | X1: 25-44 | Y1: 45-59 | Z1: 60+ | AA1: SC | AB1: ST | AC1: >50K Benf HH
A2: Jaggampeta | B2: Gandepalle | C2: Borrampalem | D2: Borrampalem | E2: Battleground | F2: 1 | G2: Pokala Subbarao | H2: YCP | I2: UR(G) | J2: Perika | K2: 9705171931 | L2: 515 | M2: 502 | N2: 1017 | O2: 49 | P2: 205 | Q2: 160 | R2: 87 | S2: 57 | T2: 257 | U2: 125 | V2: 76 | AC2: 67
A3: Jaggampeta | B3: Gandepalle | C3: Gandepalle | D3: Gandepalle | E3: Favourable | F3: 2 | G3: Rutthala Lalitha Devi | H3: YCP | I3: BC(W) | J3: Velama | K3: 6300566579 | L3: 1096 | M3: 1114 | N3: 2211 | O3: 59 | P3: 433 | Q3: 380 | R3: 242 | S3: 70 | T3: 422 | U3: 329 | V3: 275 | AC3: 61
A4: Jaggampeta | B4: Gandepalle | C4: K. Nayakampalle | D4: K. Nayakampalle | E4: Safe | F4: 1 | G4: Mallireddy Mahalakshmi Varahalu | H4: YCP | I4: UR(W) | J4: Kamma | K4: 9441246682 | L4: 402 | M4: 415 | N4: 817 | O4: 29 | P4: 179 | Q4: 114 | R4: 93 | S4: 24 | T4: 193 | U4: 104 | V4: 81 | AC4: 66
A5: Jaggampeta | B5: Gandepalle | C5: K.Gopalapuram | D5: K.Gopalapuram | E5: Battleground | F5: 6 | G5: Karri Suryakantham | H5: OTHERS | I5: UR(W) | J5: T.Kapu | K5: 9502562392 | L5: 2900 | M5: 2950 | N5: 5854 | O5: 164 | P5: 1374 | Q5: 827 | R5: 585 | S5: 231 | T5: 1480 | U5: 713 | V5: 475 | AC5: 83
A6: Jaggampeta | B6: Gandepalle | C6: Mallepalli | D6: Mallepalli | E6: Battleground | F6: 4 | G6: Ballireddy Varalakshmi | H6: YCP | I6: BC(W) | J6: T.Kapu | K6: 9493839571 | L6: 2006 | M6: 1951 | N6: 3957 | O6: 110 | P6: 913 | Q6: 514 | R6: 412 | S6: 138 | T6: 1063 | U6: 459 | V6: 346 | AC6: 83
A7: Jaggampeta | B7: Gandepalle | C7: Mallepalli | D7: Pathuru | E7: Battleground | F7: 1 | G7: Ballireddy Varalakshmi | H7: YCP | I7: BC(W) | J7: T.Kapu | K7: 9493839571 | L7: 470 | M7: 513 | N7: 983 | O7: 21 | P7: 223 | Q7: 152 | R7: 117 | S7: 23 | T7: 252 | U7: 124 | V7: 71 | AC7: 83
A8: Jaggampeta | B8: Gandepalle | C8: Murari | D8: Murari | E8: Favourable | F8: 3 | G8: Kukkala Ananda Babu | H8: OTHERS | I8: SC(G) | J8: Mala | K8: 9949147450 | L8: 1659 | M8: 1732 | N8: 3392 | O8: 95 | P8: 831 | Q8: 453 | R8: 352 | S8: 124 | T8: 829 | U8: 422 | V8: 283 | AC8: 62
A9: Jaggampeta | B9: Gandepalle | C9: N.T.Rajapuram | D9: N.T.Rajapuram | E9: Battleground | F9: 2 | G9: Bikkina Devi Durga | H9: YCP | I9: UR(W) | J9: Kamma | K9: 8309596673 | L9: 718 | M9: 765 | N9: 1484 | O9: 44 | P9: 375 | Q9: 225 | R9: 121 | S9: 59 | T9: 373 | U9: 176 | V9: 110 | AC9: 90
A10: Jaggampeta | B10: Gandepalle | C10: Neeladriraopeta | D10: Neeladriraopeta | E10: Battleground | F10: 5 | G10: Mulampaka Suresh Babu | H10: YCP | I10: BC(G) | J10: Kummari | K10: 9059315666 | L10: 2396 | M10: 2407 | N10: 4804 | O10: 152 | P10: 1134 | Q10: 702 | R10: 417 | S10: 205 | T10: 1248 | U10: 586 | V10: 357 | AC10: 87
A11: Jaggampeta | B11: Gandepalle | C11: P. Nayakampalle | D11: P. Nayakampalle | E11: Battleground | F11: 2 | G11: Mallireddy Annapurna | H11: YCP | I11: UR(W) | J11: Kamma | K11: 9692879999 | L11: 871 | M11: 876 | N11: 1749 | O11: 53 | P11: 422 | Q11: 217 | R11: 183 | S11: 58 | T11: 417 | U11: 240 | V11: 156 | AC11: 66
A12: Jaggampeta | B12: Gandepalle | C12: P.Surampalem | D12: P.Surampalem | E12: Battleground | F12: 2 | G12: Marisetti Gangabhavani | H12: YCP | I12: BC(W) | J12: Setti Balija | K12: 8897945154 | L12: 876 | M12: 854 | N12: 1731 | O12: 78 | P12: 427 | Q12: 221 | R12: 128 | S12: 83 | T12: 433 | U12: 238 | V12: 122 | AC12: 82
A13: Jaggampeta | B13: Gandepalle | C13: P.Surampalem | D13: K.Surampalem | E13: Battleground | F13: 2 | G13: Marisetti Gangabhavani | H13: YCP | I13: BC(W) | J13: Setti Balija | K13: 8897945154 | L13: 839 | M13: 757 | N13: 1596 | O13: 37 | P13: 324 | Q13: 235 | R13: 161 | S13: 54 | T13: 360 | U13: 272 | V13: 153 | AC13: 82
... A23: Jaggampeta | B23: Gokavaram | C23: Gadelapalem | D23: Gadelapalem | E23: Battleground | F23: 2 | G23: Atchibabu Kammila | H23: YCP | I23: UR(G) | J23: Kapu | K23: 9443586869 | L23: 748 | M23: 762 | N23: 1510 | O23: 64 | P23: 358 | Q23: 212 | R23: 128 | S23: 61 | T23: 353 | U23: 210 | V23: 124 | AC23: 87
A24: Jaggampeta | B24: Gokavaram | C24: Gangam Palem | D24: Gangam Palem | E24: Battleground | F24: 1 | G24: Doddi Venkata Lakshmi | H24: YCP | I24: UR(W) | J24: Gavara | K24: 9010545620 | L24: 589 | M24: 590 | N24: 1179 | O24: 42 | P24: 266 | Q24: 216 | R24: 66 | S24: 64 | T24: 285 | U24: 164 | V24: 76
A25: Jaggampeta | B25: Gokavaram | C25: Gangam Palem | D25: Takurupalem | E25: Battleground | F25: 1 | G25: Doddi Venkata Lakshmi | H25: YCP | I25: UR(W) | J25: Gavara | K25: 9010545620 | L25: 234 | M25: 263 | N25: 497 | O25: 24 | P25: 114 | Q25: 74 | R25: 50 | S25: 24 | T25: 116 | U25: 53 | V25: 41
A26: Jaggampeta | B26: Gokavaram | C26: Gokavaram | D26: Gokavaram | E26: Battleground | F26: 13 | G26: Sravani Komaram | H26: TDP | I26: ST(W) | J26: Reddika | K26: 9866737300 | L26: 5198 | M26: 5750 | N26: 12062 | O26: 331 | P26: 2678 | Q26: 1727 | R26: 1012 | S26: 345 | T26: 2466 | U26: 1534 | V26: 853 | AC26: 76
A27: Jaggampeta | B27: Gokavaram | C27: Gummalladuddi | D27: Gummalladuddi | E27: Favourable | F27: 2 | G27: Sarakanam Ramalakshmi | H27: YCP | I27: BC(W) | J27: Gavara | K27: 7702072955 | L27: 980 | M27: 998 | N27: 1978 | O27: 35 | P27: 468 | Q27: 318 | R27: 177 | S27: 64 | T27: 465 | U27: 283 | V27: 168 | AC27: 76
A28: Jaggampeta | B28: Gokavaram | C28: Itikayala Palle | D28: Itikayala Palle | E28: Favourable | F28: 1 | G28: Dara Ramakrishna | H28: TDP | I28: UR(G) | J28: Setti Balija | K28: 9849668073 | L28: 515 | M28: 564 | N28: 1079 | O28: 26 | P28: 246 | Q28: 194 | R28: 98 | S28: 30 | T28: 246 | U28: 155 | V28: 84
A29: Jaggampeta | B29: Gokavaram | C29: Kamaraju Peta | D29: Kamaraju Peta | E29: Favourable | F29: 5 | G29: Venkatarao Adapa | H29: TDP | I29: BC(G) | J29: Yadava | K29: 9640604838 | L29: 0 | M29: 0 | N29: 4938 | O29: 0 | P29: 0 | Q29: 0 | R29: 0 | S29: 0 | T29: 0 | U29: 0 | V29: 0
A30: Jaggampeta | B30: Gokavaram | C30: Kothapalle | D30: Kothapalle | E30: Battleground | F30: 7 | G30: Kanchumarthi Katama Swamy | H30: YCP | I30: SC(G) | J30: Mala | K30: 9652219718 | L30: 2868 | M30: 3032 | N30: 5917 | O30: 52 | P30: 531 | Q30: 405 | R30: 343 | S30: 55 | T30: 546 | U30: 431 | V30: 255 | AC30: 78
A31: Jaggampeta | B31: Gokavaram | C31: Krishnuni Palem | D31: Krishnuni Palem | E31: Battleground | F31: 5 | G31: Adilakshmi Rowthu | H31: YCP | I31: UR(W) | J31: Velama | K31: 9359889999 | L31: 1621 | M31: 2071 | N31: 4953 | O31: 129 | P31: 933 | Q31: 644 | R31: 364 | S31: 124 | T31: 811 | U31: 437 | V31: 249 | AC31: 84
A32: Jaggampeta | B32: Gokavaram | C32: Mallavaram | D32: Mallavaram | E32: Battleground | F32: 6 | G32: Idudala Lakshmi | H32: TDP | I32: BC(W) | J32: T.Kapu | K32: 8099534455 | L32: 0 | M32: 0 | N32: 4652 | O32: 0 | P32: 0 | Q32: 0 | R32: 0 | S32: 0 | T32: 0 | U32: 0 | V32: 0 | AC32: 67
A33: Jaggampeta | B33: Gokavaram | C33: Mallavaram | D33: Sivaramapatnam | E33: Favourable | F33: 1 | G33: Idudala Lakshmi | H33: TDP | I33: BC(W) | J33: T.Kapu | K33: 8099534455 | L33: 0 | M33: 0 | N33: 1004 | O33: 0 | P33: 0 | Q33: 0 | R33: 0 | S33: 0 | T33: 0 | U33: 0 | V33: 0 | AC33: 67
A34: Jaggampeta | B34: Gokavaram | C34: Rampa Yerrampalem | D34: Rampa Yerrampalem | E34: Favourable | F34: 7 | G34: Badampudi Harshita | H34: TDP | I34: SC(W) | J34: Mala | K34: 9441596400 | L34: 2589 | M34: 2711 | N34: 5301 | O34: 116 | P34: 1225 | Q34: 826 | R34: 543 | S34: 164 | T34: 1231 | U34: 784 | V34: 409 | AC34: 79
A35: Jaggampeta | B35: Gokavaram | C35: Thanti Konda | D35: Thanti Konda | E35: Battleground | F35: 4 | G35: Satyanarayanamma Baddireddy | H35: YCP | I35: UR(W) | J35: Kapu | K35: 9848106951 | L35: 1660 | M35: 1716 | N35: 3377 | O35: 102 | P35: 785 | Q35: 465 | R35: 364 | S35: 126 | T35: 793 | U35: 433 | V35: 308 | AC35: 78
A36: Jaggampeta | B36: Gokavaram | C36: Tirumalayapalem | D36: Tirumalayapalem | E36: Battleground | F36: 4 | G36: Puramsetti Chandra Sekhar | H36: TDP | I36: UR(G) | J36: Kapu | K36: 9573277999 | L36: 912 | M36: 940 | N36: 2608 | O36: 36 | P36: 407 | Q36: 297 | R36: 200 | S36: 73 | T36: 399 | U36: 285 | V36: 154 | AC36: 87
A37: Jaggampeta | B37: Gokavaram | C37: Vedurupaka | D37: Vedurupaka | E37: Favourable | F37: 2 | G37: Dasari Singaramma | H37: YCP | I37: BC(G) | J37: T.Kapu | K37: 9618328505 | L37: 672 | M37: 700 | N37: 1372 | O37: 44 | P37: 315 | Q37: 213 | R37: 128 | S37: 35 | T37: 351 | U37: 170 | V37: 115
A38: Jaggampeta | B38: Gokavaram | C38: Vedurupaka | D38: Bavojipeta | E38: Safe | F38: 1 | G38: Dasari Singaramma | H38: YCP | I38: BC(G) | J38: T.Kapu | K38: 9618328505 | L38: 370 | M38: 351 | N38: 721 | O38: 19 | P38: 184 | Q38: 89 | R38: 59 | S38: 24 | T38: 203 | U38: 96 | V38: 47
A39: Jaggampeta | B39: Jaggampeta | C39: Gollalagunta | D39: Gollalagunta | E39: Battleground | F39: 2 | G39: Tirumalaraju Kumari | H39: YCP | I39: UR(W) | J39: Kapu | K39: 9505415559 | L39: 680 | M39: 648 | N39: 1328 | O39: 46 | P39: 312 | Q39: 184 | R39: 106 | S39: 77 | T39: 331 | U39: 164 | V39: 108 | AC39: 78
A40: Jaggampeta | B40: Jaggampeta | C40: Govindapuram | D40: Govindapuram | E40: Battleground | F40: 2 | G40: Kammila Venkateswara Rao | H40: TDP | I40: UR(G) | J40: Kamma | K40: 9959432912 | L40: 752 | M40: 795 | N40: 1547 | O40: 65 | P40: 407 | Q40: 189 | R40: 134 | S40: 76 | T40: 395 | U40: 169 | V40: 112 | AC40: 85
A41: Jaggampeta | B41: Jaggampeta | C41: Gurra Palem | D41: Balabhadrapuram | E41: Battleground | F41: 1 | G41: Cheepurupalli Lakshmi | H41: YCP | I41: BC(G) | J41: Velama | K41: 9010126289 | L41: 190 | M41: 176 | N41: 366 | O41: 6 | P41: 95 | Q41: 45 | R41: 30 | S41: 14 | T41: 99 | U41: 45 | V41: 32 | AC41: 80
A42: Jaggampeta | B42: Jaggampeta | C42: Gurra Palem | D42: Gurra Palem | E42: Battleground | F42: 2 | G42: Cheepurupalli Lakshmi | H42: YCP | I42: BC(G) | J42: Velama | K42: 9010126289 | L42: 1039 | M42: 1013 | N42: 2052 | O42: 76 | P42: 506 | Q42: 271 | R42: 160 | S42: 155 | T42: 503 | U42: 262 | V42: 118 | AC42: 80
A43: Jaggampeta | B43: Jaggampeta | C43: Irripaka | D43: Irripaka | E43: Battleground | F43: 4 | G43: Thirri Devi | H43: YCP | I43: BC(W) | J43: T.Kapu | K43: 9885898499 | L43: 1354 | M43: 1436 | N43: 2790 | O43: 57 | P43: 683 | Q43: 413 | R43: 283 | S43: 91 | T43: 675 | U43: 379 | V43: 209 | AC43: 71
A44: Jaggampeta | B44: Jaggampeta | C44: J.Kothuru | D44: J.Kothuru | E44: Battleground | F44: 3 | G44: Nakireddy Nageswara Rao | H44: YCP | I44: UR(G) | J44: Kapu | K44: 9959581167 | L44: 1386 | M44: 1393 | N44: 2779 | O44: 92 | P44: 703 | Q44: 356 | R44: 242 | S44: 120 | T44: 745 | U44: 337 | V44: 182 | AC44: 72
A45: Jaggampeta | B45: Jaggampeta | C45: Jaggampeta | D45: Jaggampeta | E45: Battleground | F45: 18 | G45: Nagaratnam Batchala | H45: YCP | I45: SC(W) | J45: Mala | K45: 9666892228 | L45: 7495 | M45: 8184 | N45: 15688 | O45: 540 | P45: 4108 | Q45: 2248 | R45: 1286 | S45: 566 | T45: 3847 | U45: 1948 | V45: 1134 | AC45: 82
A46: Jaggampeta | B46: Jaggampeta | C46: Jaggampeta | D46: Seethanagaram | E46: Safe | F46: 1 | G46: Nagaratnam Batchala | H46: YCP | I46: SC(W) | J46: Mala | K46: 9666892228 | L46: 466 | M46: 469 | N46: 935 | O46: 39 | P46: 196 | Q46: 137 | R46: 96 | S46: 36 | T46: 191 | U46: 146 | V46: 93 | AC46: 82
A47: Jaggampeta | B47: Jaggampeta | C47: Kandregula | D47: Kandregula | E47: Battleground | F47: 2 | G47: Bodireddy Chakra Rao | H47: YCP | I47: UR(G) | J47: Kapu | K47: 9573060895 | L47: 994 | M47: 936 | N47: 1930 | O47: 64 | P47: 466 | Q47: 256 | R47: 150 | S47: 67 | T47: 541 | U47: 237 | V47: 149 | AC47: 50
A48: Jaggampeta | B48: Jaggampeta | C48: Katravulapalle | D48: Katravulapalle | E48: Battleground | F48: 9 | G48: Pitta Sugunarao | H48: YCP | I48: SC(G) | J48: Mala | K48: 9885244148 | L48: 4324 | M48: 4310 | N48: 8634 | O48: 160 | P48: 2232 | Q48: 1166 | R48: 751 | S48: 301 | T48: 2270 | U48: 1101 | V48: 651 | AC48: 82
A49: Jaggampeta | B49: Jaggampeta | C49: Mallisala | D49: Mallisala | E49: Battleground | F49: 4 | G49: Sarvasiddi Nukaratnam | H49: YCP | I49: BC(W) | J49: Yadava | K49: 9951526664 | L49: 1754 | M49: 1766 | N49: 3520 | O49: 101 | P49: 842 | Q49: 479 | R49: 344 | S49: 126 | T49: 935 | U49: 434 | V49: 257 | AC49: 87
A50: Jaggampeta | B50: Jaggampeta | C50: Mamidada | D50: Mamidada | E50: Battleground | F50: 3 | G50: Karri Suryakumari | H50: YCP | I50: BC(W) | J50: Gavara | K50: 7731959657 | L50: 1157 | M50: 1206 | N50: 2363 | O50: 58 | P50: 602 | Q50: 319 | R50: 227 | S50: 99 | T50: 557 | U50: 319 | V50: 180 | AC50: 73
... A68: Jaggampeta | B68: Kirlampudi | C68: Mukkollu | D68: Mukkollu | E68: Battleground | F68: 2 | G68: Jyothula Rambabu | H68: TDP | I68: UR(G) | J68: Kapu | K68: 8886766667 | L68: 961 | M68: 942 | N68: 1903 | O68: 51 | P68: 436 | Q68: 254 | R68: 201 | S68: 63 | T68: 501 | U68: 257 | V68: 140 | AC68: 90
A69: Jaggampeta | B69: Kirlampudi | C69: Palem | D69: Palem | E69: Battleground | F69: 2 | G69: Adabala Sandya | H69: YCP | I69: UR(W) | J69: Kapu | K69: 8639927455 | L69: 703 | M69: 693 | N69: 1396 | O69: 64 | P69: 332 | Q69: 175 | R69: 122 | S69: 88 | T69: 331 | U69: 189 | V69: 95
A70: Jaggampeta | B70: Kirlampudi | C70: Rajupalem | D70: Rajupalem | E70: Battleground | F70: 2 | G70: Gode Padmavathi | H70: YCP | I70: BC(W) | J70: Perika | K70: 8790885023 | L70: 871 | M70: 929 | N70: 1800 | O70: 64 | P70: 446 | Q70: 247 | R70: 172 | S70: 100 | T70: 430 | U70: 224 | V70: 117 | AC70: 67
A71: Jaggampeta | B71: Kirlampudi | C71: Ramachandra Puram | D71: Ramachandra Puram | E71: Battleground | F71: 2 | G71: Thummalapalli Sai Guna Sekhar | H71: YCP | I71: UR(G) | J71: Kapu | K71: 9848258999 | L71: 862 | M71: 858 | N71: 1721 | O71: 69 | P71: 461 | Q71: 218 | R71: 110 | S71: 67 | T71: 453 | U71: 236 | V71: 106
A72: Jaggampeta | B72: Kirlampudi | C72: Ramakrishnapuram | D72: Ramakrishnapuram | E72: Battleground | F72: 1 | G72: Saraswathi Kanta | H72: TDP | I72: UR(W) | J72: Perika | K72: 9493882666 | L72: 481 | M72: 528 | N72: 1011 | O72: 21 | P72: 246 | Q72: 130 | R72: 130 | S72: 30 | T72: 247 | U72: 123 | V72: 81 | AC72: 75
A73: Jaggampeta | B73: Kirlampudi | C73: S.Thimmapuram | D73: S.Thimmapuram | E73: Battleground | F73: 2 | G73: Mandeti Veeralakshmi | H73: YCP | I73: SC(W) | J73: Mala | K73: 9959624492 | L73: 758 | M73: 744 | N73: 1502 | O73: 40 | P73: 380 | Q73: 186 | R73: 138 | S73: 74 | T73: 404 | U73: 174 | V73: 105 | AC73: 85
A74: Jaggampeta | B74: Kirlampudi | C74: Simhadri Puram | D74: Simhadri Puram | E74: Battleground | F74: 3 | G74: Kalapureddy Papayamma | H74: YCP | I74: UR(W) | J74: Kapu | K74: 9951135685 | L74: 1170 | M74: 1079 | N74: 2249 | O74: 49 | P74: 542 | Q74: 274 | R74: 214 | S74: 77 | T74: 601 | U74: 293 | V74: 199
A75: Jaggampeta | B75: Kirlampudi | C75: Somanarayani Peta | D75: Somanarayani Peta | E75: Battleground | F75: 2 | G75: Sarise Lakshmi Parvathi | H75: YCP | I75: BC(G) | J75: Gavara | K75: 9490153453 | L75: 625 | M75: 648 | N75: 1273 | O75: 54 | P75: 333 | Q75: 165 | R75: 96 | S75: 40 | T75: 346 | U75: 148 | V75: 91
A76: Jaggampeta | B76: Kirlampudi | C76: Somavaram | D76: Somavaram | E76: Battleground | F76: 3 | G76: Jyothula Seeta Rama Lakshmi | H76: YCP | I76: UR(W) | J76: Kapu | K76: 8686864047 | L76: 1461 | M76: 1377 | N76: 2840 | O76: 64 | P76: 685 | Q76: 388 | R76: 240 | S76: 117 | T76: 726 | U76: 402 | V76: 216 | AC76: 88
A77: Jaggampeta | B77: Kirlampudi | C77: Sungarayunipalem | D77: Sungarayunipalem | E77: Battleground | F77: 2 | G77: Pattu Chantibabu | H77: YCP | I77: BC(G) | J77: Perika | K77: 9848652974 | L77: 1180 | M77: 1157 | N77: 2337 | O77: 60 | P77: 533 | Q77: 339 | R77: 225 | S77: 97 | T77: 541 | U77: 347 | V77: 195 | AC77: 77
A78: Jaggampeta | B78: Kirlampudi | C78: Thamarada | D78: Thamarada | E78: Battleground | F78: 3 | G78: Thota Annayya | H78: YCP | I78: UR(G) | J78: Kapu | K78: 8309332929 | L78: 1287 | M78: 1293 | N78: 2582 | O78: 55 | P78: 687 | Q78: 335 | R78: 216 | S78: 107 | T78: 659 | U78: 355 | V78: 165 | AC78: 72
A79: Jaggampeta | B79: Kirlampudi | C79: Veeravaram | D79: Veeravaram | E79: Battleground | F79: 6 | G79: Ambati Bujjamma | H79: YCP | I79: SC(G) | J79: Mala | K79: 9441807628 | L79: 2257 | M79: 2252 | N79: 4512 | O79: 91 | P79: 1029 | Q79: 633 | R79: 499 | S79: 180 | T79: 1043 | U79: 591 | V79: 443 | AC79: 86
A80: Jaggampeta | B80: Kirlampudi | C80: Velanka | D80: Velanka | E80: Battleground | F80: 4 | G80: Rayudu Swami | H80: TDP | I80: BC(G) | J80: Setti Balija | K80: 9247855118 | L80: 1597 | M80: 1594 | N80: 3193 | O80: 79 | P80: 749 | Q80: 480 | R80: 286 | S80: 118 | T80: 791 | U80: 455 | V80: 233 | AC80: 80
A81: Kakinada Rural | B81: Kakinada (Rural) | C81: Chidiga | D81: Chidiga | E81: Battleground | F81: 7 | G81: DNA | H81: DNA | I81: DNA | J81: DNA | K81: DNA | L81: 3032 | M81: 3084 | N81: 6124 | O81: 191 | P81: 1482 | Q81: 877 | R81: 533 | S81: 208 | T81: 1398 | U81: 846 | V81: 579 | AC81: 48
A82: Kakinada Rural | B82: Kakinada (Rural) | C82: Ganganapalli | D82: Ganganapalli | E82: Battleground | F82: 7 | G82: GEESALA MAHALAKSHMI | H82: YCP | K82: 9160699909 | L82: 3316 | M82: 3449 | N82: 6777 | O82: 246 | P82: 1643 | Q82: 964 | R82: 594 | S82: 301 | T82: 1624 | U82: 814 | V82: 576 | AC82: #N/A
A83: Kakinada Rural | B83: Kakinada (Rural) | C83: Indra Palem | D83: Indra Palem | E83: Battleground | F83: 10 | G83: DNA | H83: DNA | I83: DNA | J83: DNA | K83: DNA | L83: 4387 | M83: 4496 | N83: 8897 | O83: 272 | P83: 2148 | Q83: 1312 | R83: 763 | S83: 289 | T83: 2082 | U83: 1273 | V83: 742
A84: Kakinada Rural | B84: Kakinada (Rural) | C84: Kovvada | D84: Kovvada | E84: Battleground | F84: 5 | G84: Kotipalli Uma | H84: YCP | I84: UR(G) | K84: 9966097546 | L84: 2481 | M84: 2482 | N84: 4967 | O84: 173 | P84: 1166 | Q84: 700 | R84: 441 | S84: 201 | T84: 1152 | U84: 676 | V84: 449 | AC84: 60
A85: Kakinada Rural | B85: Kakinada (Rural) | C85: Kovvuru | D85: Kovvuru | E85: Battleground | F85: 7 | G85: Pilli Chakrarao | H85: YCP | I85: BC(G) | J85: Setti Balija | K85: 9848398161 | L85: 3095 | M85: 3173 | N85: 6271 | O85: 212 | P85: 1510 | Q85: 959 | R85: 490 | S85: 220 | T85: 1490 | U85: 922 | V85: 463 | AC85: 87
A86: Kakinada Rural | B86: Kakinada (Rural) | C86: Nemam | D86: Nemam | E86: Battleground | F86: 4 | G86: Ramadevu Suryaprakasarao | H86: YCP | I86: UR(G) | J86: Kapu | K86: 9705389099 | L86: 1750 | M86: 1705 | N86: 3455 | O86: 131 | P86: 834 | Q86: 446 | R86: 293 | S86: 166 | T86: 896 | U86: 420 | V86: 265 | AC86: 66
A87: Kakinada Rural | B87: Kakinada (Rural) | C87: P.Venkatapuram | D87: P.Venkatapuram | E87: Safe | F87: 2 | G87: Penke Lakshmi | H87: YCP | I87: UR(W) | J87: Setti Balija | K87: 9908909820 | L87: 887 | M87: 927 | N87: 1814 | O87: 99 | P87: 438 | Q87: 238 | R87: 151 | S87: 69 | T87: 436 | U87: 245 | V87: 137 | AC87: 63
A88: Kakinada Rural | B88: Kakinada (Rural) | C88: Panduru | D88: Panduru | E88: Battleground | F88: 5 | G88: Valavala Ammaji | H88: YCP | I88: UR(W) | J88: Kapu | K88: 9848754599 | L88: 2178 | M88: 2062 | N88: 4241 | O88: 154 | P88: 907 | Q88: 613 | R88: 388 | S88: 170 | T88: 1035 | U88: 640 | V88: 333 | AC88: 63
A89: Kakinada Rural | B89: Kakinada (Rural) | C89: Penumarthi | D89: Penumarthi | E89: Battleground | F89: 2 | G89: Penke Anand Kumar | H89: INDEPENDENT | I89: UR(G) | J89: Setti Balija | K89: 7893576090 | L89: 668 | M89: 671 | N89: 1339 | O89: 52 | P89: 357 | Q89: 138 | R89: 124 | S89: 64 | T89: 361 | U89: 128 | V89: 114 | AC89: 86
A90: Kakinada Rural | B90: Kakinada (Rural) | C90: Ramanayyapeta | D90: Ramanayyapeta | E90: Battleground | F90: 33 | G90: DNA | H90: DNA | I90: DNA | J90: DNA | K90: DNA | L90: 15514 | M90: 15698 | N90: 34137 | O90: 832 | P90: 7259 | Q90: 4575 | R90: 2988 | S90: 1014 | T90: 6573 | U90: 4546 | V90: 3335 | AC90: 37
A91: Kakinada Rural | B91: Kakinada (Rural) | C91: Repuru | D91: Repuru | E91: Battleground | F91: 2 | G91: Nakka Veeranna | H91: YCP | I91: UR(G) | J91: Kapu | K91: 9948291614 | L91: 1139 | M91: 1127 | N91: 2268 | O91: 76 | P91: 574 | Q91: 294 | R91: 183 | S91: 75 | T91: 556 | U91: 317 | V91: 191 | AC91: 1
A92: Kakinada Rural | B92: Kakinada (Rural) | C92: S. Atchuthapuram | D92: S. Atchuthapuram | E92: Battleground | F92: 10 | G92: DNA | H92: DNA | I92: DNA | J92: DNA | K92: DNA | L92: 4428 | M92: 4402 | N92: 9434 | O92: 270 | P92: 1943 | Q92: 1235 | R92: 946 | S92: 262 | T92: 1853 | U92: 1282 | V92: 1026
A93: Kakinada Rural | B93: Kakinada (Rural) | C93: Sarpavaram | D93: Sarpavaram | E93: Battleground | F93: 13 | G93: Seelam Nageswara Rao | H93: YCP | I93: BC(G) | J93: Setti Balija | K93: 9848743953 | L93: 6093 | M93: 5949 | N93: 12820 | O93: 479 | P93: 2951 | Q93: 1567 | R93: 947 | S93: 569 | T93: 2994 | U93: 1566 | V93: 963 | AC93: 59
A94: Kakinada Rural | B94: Kakinada (Rural) | C94: Suryarao Peta | D94: Suryarao Peta | E94: Favourable | F94: 4 | G94: Surada Chinni | H94: YCP | I94: BC(W) | J94: Vadabalija | K94: 9912671919 | L94: 1897 | M94: 1928 | N94: 3834 | O94: 92 | P94: 844 | Q94: 583 | R94: 409 | S94: 110 | T94: 740 | U94: 621 | V94: 425 | AC94: 49
A95: Kakinada Rural | B95: Kakinada (Rural) | C95: Swamynagar | D95: Swamynagar | E95: Favourable | F95: 1 | G95: #N/A | L95: 361 | M95: 432 | N95: 793 | O95: 24 | P95: 229 | Q95: 102 | R95: 77 | S95: 19 | T95: 199 | U95: 85 | V95: 58 | AC95: #N/A
A96: Kakinada Rural | B96: Kakinada (Rural) | C96: Thammavaram | D96: Thammavaram | E96: Battleground | F96: 8 | G96: Gollapalli Ramaswamy | H96: YCP | I96: UR(G) | J96: T.Kapu | K96: 9849998334 | L96: 3533 | M96: 3387 | N96: 6920 | O96: 268 | P96: 1669 | Q96: 879 | R96: 570 | S96: 370 | T96: 1837 | U96: 862 | V96: 462 | AC96: 74
A97: Kakinada Rural | B97: Kakinada (Rural) | C97: Thimmapuram | D97: Thimmapuram | E97: Battleground | F97: 8 | G97: Bezwada Veera Venkata Satyanarayana | H97: YCP | I97: UR(G) | J97: T.Kapu | K97: 9848443334 | L97: 3671 | M97: 3717 | N97: 7389 | O97: 289 | P97: 1841 | Q97: 955 | R97: 630 | S97: 316 | T97: 1796 | U97: 968 | V97: 591 | AC97: 71
A98: Kakinada Rural | B98: Kakinada (Rural) | C98: Toorangi | D98: Toorangi | E98: Battleground | F98: 22 | G98: DNA | H98: DNA | I98: DNA | J98: DNA | K98: DNA | L98: 8806 | M98: 9156 | N98: 19887 | O98: 587 | P98: 4524 | Q98: 2550 | R98: 1492 | S98: 613 | T98: 4269 | U98: 2437 | V98: 1482 | AC98: 59
A99: Kakinada Rural | B99: Kakinada (Rural) | C99: Vakalapudi | D99: Vakalapudi | E99: Battleground | F99: 10 | G99: DNA | H99: DNA | I99: DNA | J99: DNA | K99: DNA | L99: 4668 | M99: 4735 | N99: 9406 | O99: 335 | P99: 2326 | Q99: 1187 | R99: 882 | S99: 340 | T99: 2213 | U99: 1192 | V99: 920 | AC99: 59
A100: Kakinada Rural | B100: Kakinada (Rural) | C100: Valasapakalu | D100: Valasapakalu | E100: Favourable | F100: 9 | G100: DNA | H100: DNA | I100: DNA | J100: DNA | K100: DNA | L100: 4114 | M100: 4126 | N100: 8778 | O100: 241 | P100: 1903 | Q100: 1197 | R100: 746 | S100: 264 | T100: 1726 | U100: 1243 | V100: 845
A101: Kakinada Rural | B101: Karapa | C101: Aratlakatta | D101: Aratlakatta | E101: Favourable | F101: 4 | G101: Satyaveni Gopi | H101: YCP | I101: BC(W) | K101: 7993605566 | L101: 1971 | M101: 2022 | N101: 3993 | O101: 116 | P101: 994 | Q101: 513 | R101: 399 | S101: 160 | T101: 1018 | U101: 463 | V101: 329 | AC101: 69
A102: Kakinada Rural | B102: Karapa | C102: G. Bhavaram | D102: G. Bhavaram | E102: Battleground | F102: 1 | G102: Ganiraju Roakkala | H102: YCP | I102: UR(G) | K102: 9502319888 | L102: 376 | M102: 334 | N102: 710 | O102: 15 | P102: 139 | Q102: 87 | R102: 93 | S102: 35 | T102: 176 | U102: 104 | V102: 61 | AC102: 66
A103: Kakinada Rural | B103: Karapa | C103: Goddatipalem | D103: Goddatipalem | E103: Favourable | F103: 1 | G103: #N/A | L103: 417 | M103: 413 | N103: 830 | O103: 29 | P103: 193 | Q103: 101 | R103: 90 | S103: 28 | T103: 229 | U103: 78 | V103: 82 | AC103: #N/A
A104: Kakinada Rural | B104: Karapa | C104: Gorripudi | D104: Gorripudi | E104: Battleground | F104: 5 | G104: Kanuri Ramadevi | H104: YCP | I104: BC(W) | J104: Padmasali | K104: 6301293869 | L104: 2479 | M104: 2518 | N104: 4999 | O104: 157 | P104: 1266 | Q104: 641 | R104: 453 | S104: 215 | T104: 1291 | U104: 574 | V104: 399 | AC104: 84
A105: Kakinada Rural | B105: Karapa | C105: Gurajanapalle | D105: Gurajanapalle | E105: Battleground | F105: 4 | G105: Anusuri Srinivasarao | H105: YCP | I105: BC(G) | K105: 9640273737 | L105: 1893 | M105: 1858 | N105: 3754 | O105: 112 | P105: 881 | Q105: 511 | R105: 354 | S105: 104 | T105: 961 | U105: 495 | V105: 333 | AC105: 88
A106: Kakinada Rural | B106: Karapa | C106: Karapa | D106: Karapa | E106: Battleground | F106: 10 | G106: Sade Asha Jyothi | H106: YCP | I106: SC(W) | K106: 9532066467 | L106: 4574 | M106: 4485 | N106: 9062 | O106: 275 | P106: 2132 | Q106: 1179 | R106: 896 | S106: 350 | T106: 2243 | U106: 1156 | V106: 824 | AC106: 80
A107: Kakinada Rural | B107: Karapa | C107: Kongodu | D107: Kongodu | E107: Battleground | F107: 2 | G107: Nakka Appala Swamy | H107: YCP | I107: UR(G) | J107: Kapu | K107: 9494106999 | L107: 893 | M107: 877 | N107: 1770 | O107: 85 | P107: 418 | Q107: 212 | R107: 161 | S107: 103 | T107: 409 | U107: 231 | V107: 149 | AC107: 84
A108: Kakinada Rural | B108: Karapa | C108: Koripalle | D108: Koripalle | E108: Battleground | F108: 2 | G108: Palivela Nageswara Rao | H108: YCP | I108: UR(G) | K108: 9666375249 | L108: 730 | M108: 706 | N108: 1436 | O108: 57 | P108: 331 | Q108: 193 | R108: 125 | S108: 70 | T108: 326 | U108: 217 | V108: 117 | AC108: 75
A109: Kakinada Rural | B109: Karapa | C109: Kurada | D109: China Mamidada | E109: Battleground | F109: 1 | G109: Vasamsetti Venkata Ramana | H109: YCP | I109: BC(G) | K109: 9849698654 | L109: 294 | M109: 316 | N109: 611 | O109: 15 | P109: 130 | Q109: 91 | R109: 79 | S109: 14 | T109: 143 | U109: 75 | V109: 62 | AC109: 52
A110: Kakinada Rural | B110: Karapa | C110: Kurada | D110: Kurada | E110: Battleground | F110: 2 | G110: Vasamsetti Venkata Ramana | H110: YCP | I110: BC(G) | K110: 9849698654 | L110: 936 | M110: 916 | N110: 1852 | O110: 50 | P110: 372 | Q110: 280 | R110: 214 | S110: 52 | T110: 418 | U110: 258 | V110: 208 | AC110: 52
A111: Kakinada Rural | B111: Karapa | C111: Nadakuduru | D111: Nadakuduru | E111: Battleground | F111: 6 | G111: Degala Lalitha Kumari | H111: YCP | I111: SC(G) | J111: Mala | K111: 9666566235 | L111: 2839 | M111: 2781 | N111: 5620 | O111: 198 | P111: 1326 | Q111: 766 | R111: 486 | S111: 228 | T111: 1376 | U111: 771 | V111: 464 | AC111: 63
A112: Kakinada Rural | B112: Karapa | C112: Patharlagadda | D112: Patharlagadda | E112: Favourable | F112: 1 | G112: Esubabu Nagireddy | H112: YCP | I112: UR(G) | J112: Kapu | K112: 9948445419 | L112: 453 | M112: 488 | N112: 941 | O112: 56 | P112: 237 | Q112: 134 | R112: 61 | S112: 51 | T112: 216 | U112: 125 | V112: 61 | AC112: 78
A113: Kakinada Rural | B113: Karapa | C113: Peda Kothuru | D113: Peda Kothuru | E113: Battleground | F113: 1 | G113: Chinta Nagalakshmi | H113: YCP | I113: UR(W) | K113: 9848295290 | L113: 414 | M113: 421 | N113: 836 | O113: 33 | P113: 215 | Q113: 92 | R113: 81 | S113: 56 | T113: 202 | U113: 95 | V113: 61 | AC113: 68
A114: Kakinada Rural | B114: Karapa | C114: Peddapurappadu | D114: Peddapurappadu | E114: Battleground | F114: 2 | G114: Biruda Saraswathi | H114: OTHERS | I114: UR(W) | K114: 7993903954 | L114: 1160 | M114: 1114 | N114: 2275 | O114: 68 | P114: 509 | Q114: 301 | R114: 236 | S114: 95 | T114: 561 | U114: 300 | V114: 204 | AC114: 80
A115: Kakinada Rural | B115: Karapa | C115: Penuguduru | D115: Penuguduru | E115: Battleground | F115: 4 | G115: Reddipalli Venkata Madhavi | H115: INDEPENDENT | I115: UR(W) | J115: Kapu | K115: 8498033555 | L115: 1770 | M115: 1790 | N115: 3566 | O115: 110 | P115: 923 | Q115: 464 | R115: 292 | S115: 122 | T115: 897 | U115: 454 | V115: 295 | AC115: 85
A116: Kakinada Rural | B116: Karapa | C116: Siripuram | D116: Siripuram | E116: Battleground | F116: 1 | G116: Sujatha Nunna | H116: YCP | I116: UR(W) | J116: Kapu | K116: 9989417657 | L116: 565 | M116: 562 | N116: 1129 | O116: 44 | P116: 253 | Q116: 140 | R116: 125 | S116: 61 | T116: 248 | U116: 149 | V116: 107 | AC116: 61
A117: Kakinada Rural | B117: Karapa | C117: Uppalanka | D117: Uppalanka | E117: Favourable | F117: 2 | G117: Bommidi Nayomi | H117: YCP | I117: BC(W) | K117: 6305247836 | L117: 944 | M117: 970 | N117: 1914 | O117: 95 | P117: 534 | Q117: 210 | R117: 131 | S117: 105 | T117: 528 | U117: 235 | V117: 76 | AC117: 88
A118: Kakinada Rural | B118: Karapa | C118: Vakada | D118: Vakada | E118: Battleground | F118: 2 | G118: Adabala Satya | H118: YCP | I118: UR(W) | K118: 9951975888 | L118: 949 | M118: 957 | N118: 1907 | O118: 79 | P118: 459 | Q118: 237 | R118: 182 | S118: 77 | T118: 488 | U118: 211 | V118: 173 | AC118: 72
A119: Kakinada Rural | B119: Karapa | C119: Valasapakulu | D119: Valasapakulu | E119: Battleground | F119: 1 | G119: Vasamsetti Ramarao | H119: YCP | I119: BC(G) | K119: 9553395145 | L119: 601 | M119: 566 | N119: 1167 | O119: 13 | P119: 265 | Q119: 174 | R119: 113 | S119: 37 | T119: 295 | U119: 165 | V119: 103 | AC119: 63
A120: Kakinada Rural | B120: Karapa | C120: Velangi | D120: Velangi | E120: Battleground | F120: 6 | G120: Savile Neelima | H120: YCP | I120: SC(W) | K120: 8790503563 | L120: 2960 | M120: 3061 | N120: 6024 | O120: 165 | P120: 1259 | Q120: 949 | R120: 685 | S120: 216 | T120: 1297 | U120: 871 | V120: 575 | AC120: 67
A121: Kakinada Rural | B121: Karapa | C121: Vemulavada | D121: Vemulavada | E121: Battleground | F121: 3 | G121: Kamkidi Manga Devi | H121: YCP | I121: BC(W) | K121: 9959570866 | L121: 1435 | M121: 1463 | N121: 2898 | O121: 84 | P121: 671 | Q121: 381 | R121: 320 | S121: 83 | T121: 710 | U121: 364 | V121: 276 | AC121: 63
A122: Kakinada Rural | B122: Karapa | C122: Vijayarayudu Palem | D122: Vijayarayudu Palem | E122: Battleground | F122: 1 | G122: Velugubanti Seetha Rama Raghava | H122: YCP | I122: UR(G) | K122: 9182824192 | L122: 437 | M122: 423 | N122: 861 | O122: 22 | P122: 189 | Q122: 126 | R122: 86 | S122: 36 | T122: 184 | U122: 126 | V122: 89 | AC122: 80
A123: Kakinada Rural | B123: Karapa | C123: Yandamuru | D123: Yandamuru | E123: Battleground | F123: 3 | G123: Marella Srinivasarao | H123: TDP | I123: SC(G) | K123: 8688433626 | L123: 1417 | M123: 1335 | N123: 2755 | O123: 85 | P123: 640 | Q123: 351 | R123: 259 | S123: 123 | T123: 703 | U123: 346 | V123: 243 | AC123: 68
A124: Kakinada Rural | B124: Karapa | C124: Z. Bhavaram | D124: Z. Bhavaram | E124: Battleground | F124: 1 | G124: Kotha Nagalakshmi | H124: YCP | I124: UR(W) | J124: Kapu | K124: 9014074678 | L124: 554 | M124: 557 | N124: 1113 | O124: 42 | P124: 251 | Q124: 135 | R124: 129 | S124: 40 | T124: 253 | U124: 131 | V124: 129 | AC124: 83
A125: Peddapuram | B125: Peddapuram | C125: Anuru | D125: Anuru | E125: Battleground | F125: 1 | G125: Nookapalli Anitha Rani | H125: YCP | I125: UR(W) | K125: 9515450642 | L125: 379 | M125: 358 | N125: 737 | O125: 15 | P125: 180 | Q125: 103 | R125: 60 | S125: 19 | T125: 211 | U125: 91 | V125: 58 | AC125: 53
A126: Peddapuram | B126: Peddapuram | C126: Anuru | D126: Rameswaram | E126: Battleground | F126: 1 | G126: Nookapalli Anitha Rani | H126: YCP | I126: UR(W) | K126: 9515450642 | L126: 954 | M126: 897 | N126: 1851 | O126: 78 | P126: 405 | Q126: 238 | R126: 175 | S126: 103 | T126: 484 | U126: 210 | V126: 157 | AC126: 53
...

Sheet Data
A1: S No | B1: Assembly | C1: Mandal | D1: Panchayat | E1: Village | F1: Current Sarpanch | G1: Sarpanch Current Party | H1: TDP Current Position | I1: 2024 GE Scenario | J1: 2020 Sarpanch Election Scenario | K1: Possible Reservation for Upcoming Panchayat Elections | L1: 2026 Sarpanch Aspirants - Aspirant Number - Aspirant Party - Aspirant Faction | M1: Key Leaders - Leader Mobile - Party - Faction | N1: Internal Factions | O1: Development Activities (2024-2026) | P1: Key Issues in Panchayat | Q1: Illegal Activities | R1: Any Aditional Information
A2: =ROW(A1) -> 1 | C2: Gollaprolu | D2: A.K.MALLAVARAM | F2: Satyanarayanamma Arigela - 9705934446
A3: =ROW(A2) -> 2 | C3: Gollaprolu | D3: A.P.Mallavaram | F3: Kadimasetti Suseela - 9666243208
A4: =ROW(A3) -> 3 | C4: Gollaprolu | D4: A.VIJAYANAGARAM | F4: M Satya Venkata Sita Ramakrishna Raju - 9618222288
A5: =ROW(A4) -> 4 | C5: Gollaprolu | D5: CHEBROLU | F5: Dondapati Lovathalli - 7386093635
A6: =ROW(A5) -> 5 | C6: Gollaprolu | D6: CHENDURTHI | F6: Alli Papa - 6281745507
A7: =ROW(A6) -> 6 | C7: Gollaprolu | D7: CHINA JAGGAMPETA | F7: Vammi Veeralakshmi - 9959354489
A8: =ROW(A7) -> 7 | C8: Gollaprolu | D8: Durgada | F8: Pampana Subbalakshmi - 9290933688
A9: =ROW(A8) -> 8 | C9: Gollaprolu | D9: KODAVALI | F9: Burra Naga Ramachandra - 9866027338
A10: =ROW(A9) -> 9 | C10: Gollaprolu | D10: TATIPARTHI | F10: Katta Bulleswararao - 9848074541
A11: =ROW(A10) -> 10 | C11: Gollaprolu | D11: VANNEPUDI | F11: Kanda Subrahmanyam - 9848657992
A12: =ROW(A11) -> 11 | C12: Kakinada Rural | D12: GANGANAPALLI | F12: Geesala Mahalakshmi - 9160699909
A13: =ROW(A12) -> 12 | C13: Kakinada Rural | D13: KOVVADA | F13: Kotipalli Uma - 9966097546
... A106: =ROW(A105) -> 105 | C106: U.Kothapalli | D106: YENDAPALLI | F106: Pedda Apparao Seelam - 7013609519
A107: =ROW(A106) -> 106 | B107: Jaggampeta | C107: Gandepalli | D107: Borrampalem | F107: Pokala Subbarao - 9705171931 | G107: YSRCP | H107: Battleground | I107: In General election TDP got good majority ove YCP, Sarpanch is extremely disgruntled with how YCP handled local leaders taking away sarpanch powers funds, the money distribution during the elections were also not in control of the Sarpanch. The village is domianted by BC comminity especially Pereka. | J107: This is predominantly a INC and YCP supported village, this foundationala support along with YSRCP being in power led to a decent win for YCP contestant. | K107: BC (Gen) | L107: Pokala Subbarao (Perika) will contest if the reservation is BC or general. | M107: Pokala Subbarao YCP and his close family member Pallapu Vishnu Chakram (Ex-Sarpanch) are key leaders in YCP, Kalapu Subbarao and his relative Yerramsetti Chandra Rao (Babji) his wife Venkatalaxmi (Ex-ZPTC) are key leaders in TDP.
A108: =ROW(A107) -> 107 | B108: Jaggampeta | C108: Gandepalli | D108: Gandepalli | E108: Gandepalli | F108: Rutthala Lalitha Devi - 6300566579 | G108: YSRCP | H108: Favourable | I108: This village is dominated by Kamma community where TDP secured majority in 2014 and 2019 AEs despite losing the elections due to Kamma's influence on Koppula Velama community. Palakurthi Aadi Narayana (Cluster Incharge) and Pyla Venkanna (Sarpanch Contestant) are very active in TDP. Bodha Rami Reddy (YSRCP- Village President) is leading the YSRCP along with Maddipatla Rama Krishna (MPTC- Kamma). Bodha Rami Reddy is close to Muthyala Srinivas (Ex AC Incharge of YSRCP -2016) and proposing hsi name for YSRCP Incharge. | K108: General | L108: Maddipatla Rama Krishna (Kamma- YSRCP - Ex -MPTC) | P108: 1. Draniage is key issue in Gandepalli Village 2. 250 Housing Sites were allotted near Polavaram Canal where houses construction not materialised
A109: =ROW(A108) -> 108 | B109: Jaggampeta | C109: Gandepalli | D109: K.Gopalapuram | E109: K.Gopalapuram | F109: Karri Suryakantham - 9502562392 | G109: YSRCP | H109: Favourable | I109: TDP was able to secure the majority of 280 votes in the village as Village YSRCP is divided into 2 Groups, Karri Ramanjaneyulu (Thota Narsimham's group) and Parthasarthi (Jyothula Chanti Babu Group) which helped TDP MLA Nehru in elections. Parthasarathi owns around 100 acres in village belongs to Karnam community stayed neutral in elections. On the other hand TDP is led by Bala Subramanyam (Karnalu - Babai of Parthasarathi) who is a 3 times Sarpanch and holds good support in village. Bala Subramanyam stays in Rajahmundry and owns house in the village | J109: Karri Suryakantham was unanimously elected as Sarpanch with YSRCP support | K109: General | L109: 1.Parthasarathi (YSRCP- Karnalu - Financially Strong 2. Bala Subramanyam (TDP -Karnalu -3 times Sarpanch) | M109: 1. Karri Krishna (YSRCP -Turpu Kapu - Active Member of Party) 2. Karri Ramanjaneyulu (YSRCP - Turpu Kapu - Sarpanch Husband) | O109: 1. Road connecvity from K. Gopalapuram to Gandepalli Via NT Rajapuram is completely damaged
A110: =ROW(A109) -> 109 | B110: Jaggampeta | C110: Gandepalli | D110: K.Nayakampalli | F110: Mallireddy Mahalakshmi Varahalu - 9441246682
A111: =ROW(A110) -> 110 | B111: Jaggampeta | C111: Gandepalli | D111: Mallepalli | F111: Ballireddy Varalakshmi - 9493839571 | G111: YSRCP | H111: Battleground | I111: TDP got majority in the village, Domma Srinu (Kapu) joined TDP from YCP before elections. | J111: YCP sarpanch Balireddy Varalaxmi wife of Gangaraju won with 1300 votes majority, with 2 MPTC and 10 wards while TDP got 4 wards, Gangaraju does politics without parties and have good relations with everyone, he is a pastor and the village have more than 400 Christians. | K111: General | L111: Ramkurthi Narasimha-JSP-Kapu Balireddy Gangaraju-Turpu Kapu-YCP-Pastor Domma Srinu-Kapu-TDP | M111: Ramkurthi Narasimha-JSP-Kapu Balireddy Gangaraju-Turpu Kapu-YCP-Pastor Domma Srinu-Kapu-TDP | P111: The village only has dirt roads and gravel roads, the village is in need of CC roads.
A112: =ROW(A111) -> 111 | B112: Jaggampeta | C112: Gandepalli | D112: Murari | F112: Kukkala Ananda Babu - 9949147450 | G112: TDP | H112: Favourable | I112: TDP got 500 votes majority in this village in the elections. | J112: There was no election, the decision was unanimous, Chinnam Matha mother of Chinnam Duragao rao tried to contest but the village farmers decided for unanimous decision, TDP was not eager in participating in the elections. | K112: General | L112: The village might got for unanimous this time as well, late Kondaiah Dora's brother Chittibabu who is from Z Ragampeta used to involve alot in the village politics but not involved now. OC General reservation in the village might stimualte a strong rivalry in the village if Chengala Dorababu (Kamma) YCP decide to contest, against any candidate fielded by Jasthi Vasanth son of Kondaiah Dora | O112: CC roads are needed Community hall is expected by the village
A113: =ROW(A112) -> 112 | B113: Jaggampeta | C113: Gandepalli | D113: N.T.Rajapuram | F113: Bikkina Devi Durga - 8309596673 | G113: TDP | H113: Favourable | I113: TDP got 330 votes majority major YCP leaders like Parimi Veera Venkata Sathyanarayana (Parimibabu) ZPTC and sarpanch Bikkina Devi wife of Bikkina gangadher joined TDP right before elections. | J113: Kathina Santhosh Kumar wife of Kathina Venkanna Chowdhary was the original YCP candidate and Bikkina Devi is the rebel candidate from YCP there was no canddiate from TDP, rebel candidate won with the support of Parimbabu in the elections. Kathina Venkanna Chowdhary also came to TDP before elections he is a follower of Chantibabu and went to YCP with Chantibabu from TDP before. He is with the Kantipudi Sathyanarayana group in TDP now. | K113: SC (Gen) | L113: Kantipudi Sathayanarayana TDP, and parimbabu TDP are two groups in the village now, Parimbabu is ZPTC and Bikkina Devi Durga are one group now after joining TDP, he is accused of 23 crores of fraud in DCCB with ED and money laundering cases. Kantipudi Sathyanarayana was Agriculturte society president and PAC chairman before. Parimi Venkateshwar Rao (YCP) (ex sarpanch) but might not contest as TDP might be in two factions but he might get support from Parimbabu if party orders prevent Parimbabu to contest a candidate. Parimbabu have Bikkina Ramana, Bikkina Vamshi, Bikkina Venkat rao and Palacharla Sathyanarayna in line to contest as sarpanch candidates they are all his relatives. Parimbabu was society chairman from TDP in 2004 and went to YCP around 2011 with Nehru, he came back with Nehru 2017, he went to YCP in 2019, he is having CB CID enquiry. people are angry with them as his scams made the banks hike the interest rates. | P113: The village have alot of oil palms and Thalluri lift irrigation is important to this village as the village ground water is depleteed now and need this water to even feed their cattle, the bill is granted but the contract is not started yet, House spaces promised by TDP are also a point of contention from people now. village needs drainages and cemetary, Naveen has negative view because he is encouraging Parimbabu, and there is alot of gravel mining in this village and neighbouring village Gopalpuram, the road contract from Yellamilli to Gopalpuram is only completed 50% becasue the gravel lorries will destroy the road and the contractor wont get the bill, mining lorries were issue for people and MLA asked them to do it only at night now and not allowing in day time, people believe MLA has percentage in this.
A114: =ROW(A113) -> 113 | B114: Jaggampeta | C114: Gandepalli | D114: NEELADRIRAOPETA | F114: Mulampaka Suresh Babu - 9059315666 | G114: YSRCP | H114: Battleground | I114: TDP got a comfortable 1500 over YCP | J114: There were strong contestants from TDP, YCP and JSP as well here but YCP got 830 votes majoriy, Nakka Manish (Sagara) from TDP and Darballa Sadguru Murthy from (JSP) contested, from TDP Gajji Laxmi (Yadava) also contested in the elections. | K114: General | L114: There is a chance for rebel nominations in TDP, Chityala Babji (Kapu) Kurukuri Venkatesh Chowdhary (Kamma), Palla Prasad (Kapu) TDP, Suresh Babu (Sagara) YCP, Nakka Venkateshwar Rao (Sagara) and Nakka Annavaram Sathyanarayana Murthy might contest with the support of Suresh Babu | M114: Darballa Rambabu (ex Sarpanch) Nakka Venkateshwar Rao (YCP) Kurukuri Venkatesh Chowdhary Kamma TDP Dareballa Sadhguru (JSP) | N114: Sarpanch is supporter of Narasimha and claims the cadre here is party loyal and not candidate loyal, claimed Narasimha organized weekly meetings with cadre every week and visits some one every week. | O114: Pushkar canal bridge, water tanks facility in the village
A115: =ROW(A114) -> 114 | B115: Jaggampeta | C115: Gandepalli | D115: P.Nayakampalli | F115: Mallireddy Annapurna - 9692879999 | G115: YSRCP | H115: Battleground | I115: TDP got 280 majority in this village over YCP, YCP Sarpanch Annapurna's Husband Mallireddy Venkataramana passed away his brother Mallireddy Suresh takes care of things now. | J115: There was no election, it was unanimous, TDP cadre was not willing to participate and TDP Ex-sarpanch from previous term moved to YCP before 2019 elections. | K115: BC (Woman) | L115: Dammu Apparao (Settibalija) YCP Chemmangi Srinu (Settibalija) TDP school committee chairman Medisetti Subbarai (Settibalija) TDP | M115: Malireddy Suresh (Kamma) YCP Vundavalli Narayana Murthy (Kamma) YCP Ex-sarpanch Vundavalli Chandra Rao (TDP) Ex MPTC Kamma
A116: =ROW(A115) -> 115 | B116: Jaggampeta | C116: Gandepalli | D116: Ramayyapalem | F116: Mylavarapu Venkatalakshmi - 9618098937 | G116: YSRCP | H116: Battleground | I116: - Jyothula Nehru has got a majority of 260 votes (543 for TDP and 283 for YSRCP) - Village is fully dominated by Turpu Kapu | J116: - Contestants include Mylavarapu Srinivas (Defacto Sarpanch for his Wife | YSRCP) and Golavilli Babu Rao (TDP | Ex-Sarpanch 2014) - Mylavarapu Srinivas has won with a majority of 220 votes (Got around 500) over Baburao (got around 280 votes) - Mylavarapu Srinivas was backed by Chantibabu during the Sarpanch elections but he is currently with Thota Narasimham - Kona Peddhayya(Currently TDP - Nehru), a 3 term sarpanch before 2014 still has his candidates stood up in sarpanch elections | K116: BC (Gen) | L116: - Rowthu Sathibabu, relatively a cousin to current Sarpanch Srinivas, and belongs to Thota Narasimham's faction is the major aspirant from YSRCP - Kona Peddhayya will have one of his candidates in the race from TDP - Babu Rao, Ex- Sarpanch-2014; Contestant 2020, is also in the race from TDP - But both Babu Rao and Kona Peddhayya are in Jyothula Nehru's faction - Golavilli Annavaram, elder brother of Golavilli Baburao also has differences | N116: - TDP has two major factions: 1 - Kona Peddhayya; and 2 - Golavilli Babu Rao - YSRCP has Rowthu Sathibabu (2026 aspirant) and Mylavarapu Srinivas (Defacto Sarpanch-2020) factions but as Srinivas is not expecting ticket for YSRCP is likely to support Sathibabu during the elections | O116: - No development activities in the new tenure | P116: - Severe drinking water scarcity - Irrigation water scarcity
A117: =ROW(A116) -> 116 | B117: Jaggampeta | C117: Gandepalli | D117: Singarampalem | F117: Buddaraju Ganapathiraju - 9882298866
A118: =ROW(A117) -> 117 | B118: Jaggampeta | C118: Gandepalli | D118: SUBBAYAMMA PETA | F118: Bobbara Sivakumar - 9492885777
A119: =ROW(A118) -> 118 | B119: Jaggampeta | C119: Gandepalli | D119: Surampalem | F119: Marisetti Gangabhavani - 8897945154
A120: =ROW(A119) -> 119 | B120: Jaggampeta | C120: Gandepalli | D120: Talluru | F120: Seelamanthula Veerababu - 8309719191 | G120: TDP | H120: Favourable | I120: - Jyothula Nehru has got a majority of around 670 votes - Param Cherla Sathyanarayana (Ex Sarpanch | Kamma), Paindi Venkateshwarav Rao(Ex Sarpanch | Kamma) and Seelamanthula Veerababu (Sarpanch | Padmashali | Converted Christian) are the major TDP leaders whose support has brought reasonable Kamma, SC and BC (Padmashali and Yadava) | J120: - Seelamanthula Veerababu (Sarpanch | Padmashali | Converted Christian) was in YSRCP during the general elections but came into TDP party on the understanding between him and Param Cherla Sathyanarayana, Paindi Venkateshwarav Rao as the village is dominated by TDP mostly - It was BC(G) reservation for which Seelamanthula Veerababu who is aspiring for political benefits has contested with own resources - Anivelli Rambabu (Dummy candidated from YSRCP), supported by Obinni Veerababu was the contestant against current sarpanch Seelamanthula Veerababu. - Seelamanthula Veerababu has won with a majority of 227 votes | K120: SC (Woman) | L120: - One backed by Obinni Veerababu from YSRCP - One backed by Param Cherla Sathyanarayana and Paindi Venkateshwarav Rao from TDP, if SC or one among these if its General | N120: - YSRCP has no major faction but just one Obinni Veerababu who is with Thota Narasimham - TDP may split to two if Param Cherla Sathyanarayana and Paindi Venkateshwarav Rao does not back current sarpanch Seelamanthula Veerababu | O120: - CC Roads worth 50 Lakhs with a stretch of 1.5 KM - Cemetary for BCs | P120: - Cemetary for SCs - 2-3 internal roads
A121: =ROW(A120) -> 120 | B121: Jaggampeta | C121: Gandepalli | D121: Uppalapadu | F121: Adabala Ramanjaneyulu - 9951557676 | G121: TDP | H121: Favourable | I121: - Jyothula Nehru has got a majority of around 650 votes against Thota Narasimham - Adabala family who are in TDP and village being dominated by Kapu community has helped get the majority | J121: - Adabala Ramanjaneyulu (Sarpanch) has won with a majority of around 200 votes against Ramakurthy Ramakrishna Murthy - Adabala Ramanjaneyulu actually won from YSRCP but later joined TDP - Adabala Ramanjaneyulu's brother Adabala Bhasker had differences but they both are currently in TDP - Ramakurthy Ramakrishna Murthy actully contested two times and lost both the times. | K121: SC (Woman) | L121: - Adabala Anjaneyulu is ready to contest the elections if he gets support from the party and Ramakurthy Ramakrishna Murthy will be the other contestant supported by Thota Narasimham | N121: - Currently no major internal factions in both the parties but there is a chance of TDP becoming two getting divided betwen Adabala brothers | O121: - 3KM CC roads were laid and another 6 KM roads are sanctioned | P121: - Drianage system must be improvised
A122: =ROW(A121) -> 121 | B122: Jaggampeta | C122: Gandepalli | D122: Yellamilli | F122: N. Naga Jyothi - 9502850451
A123: =ROW(A122) -> 122 | B123: Jaggampeta | C123: Gandepalli | D123: Yerrampalem | F123: Ijjina Chinnari - 8897265258
A124: =ROW(A123) -> 123 | B124: Jaggampeta | C124: Gandepalli | D124: Z.Ragampeta | F124: Sri Kandula Chittibabu - 9618721999
A125: =ROW(A124) -> 124 | B125: Jaggampeta | C125: Jaggampeta | D125: GOLLALAGUNTA | F125: Tirumalaraju Kumari - 9505415559
A126: =ROW(A125) -> 125 | B126: Jaggampeta | C126: Jaggampeta | D126: GOVINDAPURAM | F126: Kammila Venkateswara Rao - 9959432912
A127: =ROW(A126) -> 126 | B127: Jaggampeta | C127: Jaggampeta | D127: GURRAPPALEM | F127: Cheepurupalli Lakshmi - 9010126289
A128: =ROW(A127) -> 127 | B128: Jaggampeta | C128: Jaggampeta | D128: IRRIPAKA | F128: Thirri Devi - 9885898499 | G128: YSRCP | H128: Favourable | I128: This is the native village of Nehru even Chanti Babu supported fully after he is denied ticket in YSRCP.TDP was able to secure the majority of around 800 votes. Pantham Babu ( - Previously contested against Jyothula Naveen's Wife -Close to Thota Narsimham) shifted to TDP during 2024 elections after he was promised Sarpanch seat in local elections | J128: Tirri Devi (W/o Tirri Venkat Ramana - Previously close to Chanti Babu) secured Sarpanch position with 396 votes majority against Surla Satyavathi (Velama - suppoorted by Nehru), later supported Thota Narsimham in assembly elections. | K128: General | M128: 1. Tirri Venkata Ramana (YSRCP - T.Kapu - Sarpanch Husband) 2. Yalla Ramana (YSRCP - T.Kapu - Active Leader) 2. Pantham Babu (Kapu -TDP - Shifted frpm YSRCP in 2024 - Sarpanch Contestant) 3. Jyothula Naga Babu (TDP -Kapu - Close to Jyothula Naveen) | P128: 1. High school should be upgraded to 10th class, adject villages Mamidada, Somavaram already upgraded to 10th 2. Irrigation water is the major issue, though Yeleru canal passes through village only Nehru and Chanti Babu and few others pump throgh motors and charges 6,000 per farmer to supply the water to them 3. 220 Housing pattas sanctioned even 2 acres of land bought during YSRCP government but not materialised
A129: =ROW(A128) -> 128 | B129: Jaggampeta | C129: Jaggampeta | D129: J.KOTHURU | F129: Nakireddy Nageswara Rao - 9959581167
A130: =ROW(A129) -> 129 | B130: Jaggampeta | C130: Jaggampeta | D130: JAGGAMPETA | F130: Nagaratnam Batchala - 9666892228 | G130: YSRCP | H130: Battleground | I130: TDP MLA candidate Jyothula Nehru was able to secure 4042 votes due to | J130: Jaggampeta Village is reserved for SC (W) where Bandaru Raja (Vice Sarpanch) handled all the elections and played second fidel to MLA Chanti Babu. The margin for Sarpanch election is around 800 votes against TDP candidate Sambatula Susheela. | K130: BC (Gen) | L130: Pandrangi Ram Babu (TDP - Turpu Kapu - Senior Leader - ZPTC Contestant) Rayi Sai (Kapu - Close to Chanti Babu - later joined TDP) | M130: Bandaru Raja (YSRCP - Kapu - Vice Sarpanch) Chittamani Satya Narayana (MPTC - Setti Balija - YCP) Jeeni Mani Babu (Kapu - YSRCP) Rayi Sai (Youth Leader - Kapu) Vommi Raghu Ram (ZPTC - Yadava - YSRCP) | N130: YSRCP divided into 2 Groups Bandaru Raja (Kapu - Vice Sarpanch - YSRCP) Ghafoor (Senior leader) TDP divided into 2 Groups Marisetty Badram (Kapu - TDP - Senior leader) Jeeni Manikyala Rao (JVR - Kapu - Mandal President) | P130: 1. Drainage is the major issue in Jaggampeta 2. Internal Roads in Jaggampeta Village
A131: =ROW(A130) -> 130 | B131: Jaggampeta | C131: Jaggampeta | D131: KANDREGULA | F131: Bodireddy Chakra Rao - 9573060895
A132: =ROW(A131) -> 131 | B132: Jaggampeta | C132: Jaggampeta | D132: KATRAVULAPALLE | F132: Pitta Sugunarao - 9885244148 | G132: YSRCP | H132: Favourable | I132: TDP got more than 3000 majority in this region, the Kapu voter base of YSRCP moved towards the TDP JSP alliance, TDP also had strong leaders in the village who are financially able to manage the party. | J132: The SC reservation seat went to YSRCP where the MLA intentionally changed the reservation to SC to favour the party. As the government was also in power YSRCP was able to win easily as TDP did not work hard to win. | K132: General | L132: Yeleti Bobby (Kamma)-TDP (strong leader in village) Yeleti Dhanukonda (Kamma)-YCP (Grand father was Sarpanch) | M132: Yeleti Bobby (Kamma) TDP Bindani brothers Bindali Perraju and Arjun Rao Perraju is YCP committee president.
A133: =ROW(A132) -> 132 | B133: Jaggampeta | C133: Jaggampeta | D133: MALLISALA | F133: Sarvasiddi Nukaratnam - 9951526664 | G133: TDP | H133: Favourable | I133: TDP got 379 votes majority in this village in general elections. | J133: TDP supported Rebel surpanch candidate Sarvasiddi Nukaratnam wife of Sarvasiddi Laxaman Rao (Mandal general secreatary TDP) joined TDP after winning, they won against Chalapareddy Nukaratnam wife of Chalapareddy Appalakonda with 39 votes majority. | K133: General | L133: Paidipala Venkata Suryanarayana (OC Kapu) cluster incharge and Athma committe member) | M133: Attuluri Nageshwar rao (Nagababu) (Vysya) MPP, and MPTC of Kandregula, his wife Attuluri Nagaratnam is MPTC from Mallisala Sarvasiddi Laxman Rao (Yadava) sarpanch husband Palepureddy Sathyanarayana (OC) YCP Narasimham follower Vanasi Subramanyam (SC Mala) YCP Narasimham follower Attuluri Saibabu (Vysya) YCP Chantibabu follower | N133: Palepureddy Sathyanarayana (OC) YCP Narasimham follower Vanasi Subramanyam (SC Mala) YCP Narasimham follower Attuluri Saibabu (Vysya) YCP Chantibabu follower | O133: 50 lakhs cc roads MPP funds 10 lakhs for drains | P133: Housing 2.5 lakhs sceme waiting for bills Widow pensions and Disabled pensions are facing issues Cancer and HIV pensions are taken care by party but widow and PH pensions are not getting the attentions
A134: =ROW(A133) -> 133 | B134: Jaggampeta | C134: Jaggampeta | D134: MAMIDADA | E134: MAMIDADA | F134: Karri Suryakumari - 7731959657 | G134: YSRCP | H134: Favourable | I134: This village is adjcent to Nehru's native village Irripaka where holds strong influence in the village, Chanti Babu was denied which helped Nehru's to gain majority of 350 votes in the villages | J134: YSRCP was able secure the Sarpanch position with a mere margin of 35 votes as Nehru holds good command in the village. Penkota Jaya Laxmi (Gavara W/o Penkota Satya Narayana) contested from TDP lost by small margin due to YSRCP government presence at state level. | K134: General | L134: 1. Penkota Satya Narayana (Gavara- TDP-- Wife Contested as Sarpanch) 2. Boddedi Suman (Gavara, TDP) 3. Desetti Srinivas (TDP- Devanga) 4. Dadi Venkateshwar Rao (Gavara TDP) 5. Vegi Rama Krishna (Gavara -TDP) | N134: YSRCP divided into 2 Groups Karri Srinivas (Gavara - Wife Sarpanch - Close to Chanti Babu) Sharanam Atchi Raju (Gavara - Close to Thota Narsimham) | O134: 20 Lakhs worth CC roads laid in the village | P134: Silt from drainages is not removed regularly which is causing an issue to public
A135: =ROW(A134) -> 134 | B135: Jaggampeta | C135: Jaggampeta | D135: MANYANVARIPALEM | F135: Potru Veerraju - 9010804737
A136: =ROW(A135) -> 135 | B136: Jaggampeta | C136: Jaggampeta | D136: MARRIPAKA | F136: Jagatham Anandarao - 9177420734
A137: =ROW(A136) -> 136 | B137: Jaggampeta | C137: Jaggampeta | D137: NARENDRAPATNAM | F137: Burri Lakshmi - 9959466333 | G137: YSRCP | H137: Battleground | I137: TDP got over 200 votes majority in the 2024 AE elections | J137: Burri Lakshmi wife of Burri Chakrababu (Kapu) YCP won over Burri Ratnakumari wife of Burri Sathyanarayana (Ex-PAC) TDP. Burri Chakrababu and his candidates won Sarpanch elections 4 times now and he was PAC chairman during YCP tenure. | K137: SC (Gen) | L137: Any proxy SC candidate from Burri Chakrababu Any proxy SC or BC candidate by Burri Sathyanarayana | O137: 20 lakhs worth cc roads | P137: Jagan Anna Colony land layout distribution issue, people are waiting for 2.5 Lakh money for basement level constructions.
A138: =ROW(A137) -> 137 | B138: Jaggampeta | C138: Jaggampeta | D138: RAJAPUDI | F138: Busala Vishnu Murthy - 9966327502 | G138: TDP | H138: Favourable | I138: - Jyothula Nehru has got a majority of 640 votes over Thota Narasimham - Busala Vishnu Murthy(Sarpanch), Chantibabu's faction had shifted to TDP before elctions brongng YSRCP, Chantibabu's cadre votes | J138: - All the three major contestants were of YSRCP; Busala Vishnu Murthy (Currently TDP, went Against Chantibabu to contest); Jami Peddakapu (Backed by Thota Trimurtulu), Mummana Somaraju (Backed by Jyothula Chantibabu) - Busala Vishnu Murthy has won with a majority of 350 even tho others promissed of giving personal funds for the Shivalaya Temple and he didn't commit for the same | K138: General | L138: - Busal Vishnu Murty (expecting from TDP); - Both the previous YSRCP contestants are not going to contest this time - Any Yadav leader may emerge as "Yadav has never been a sarpanch" even tho they have 2nd majority voters(1200) after Turpu Kapu - TDP may go for Reka Bulraju if Yadavs revolt and Vishnu Murty may again change his faction to Thota Narasimham if he doesnt get backup from TDP | N138: - No major internal factions in both the parties as YSRCP is almost silent this time and TDP no other powerful leader than Vishnu Murty currently | O138: - Recently Koneru development works are santioned (worth yet to decide as of 5th Feb 2026) - Worth of 20lakh CC-roads were laid in new tenure - 11 KM interlinked roads to other panchayats are laid - 3 Cemetaries are developed with power supply and water borewells and taps to bath - About 52 cr wrere sanctioned for a lift repair which supplies irrigation water to multiple villages (been pending since 3 years) | R138: - 80% Sagaras in this village always supports Nehru, irrespictive of party
A139: =ROW(A138) -> 138 | B139: Jaggampeta | C139: Jaggampeta | D139: RAMAVARAM | F139: Chayadevi Vatsavayi - 9963930222 | G139: Neutral | H139: Favourable | I139: - Jyothula Nehru (TDP), got about 540 votes majority. - Current Sarpanch, Sathibabu Raju is Chantibabu's cadre and Ganesh Raja(Contestant) is in Narasimham's Cadre due to which the Chantibabu's cadre did not vote for YSRCP - And Adapala Venkateshwar Rao has given his complete support to Jyothula Nehru as he holds Telugu Yuvatha State Vice President | J139: - Major Contestants are Vasthavayu Sathibabu Raju (Current Defacto Sarpanch| Kshatriya | currently Neautral | Chantibabu's Faction; Ganeshula Raja (2nd Place | Kapu | YSRCP | Thota Narasimham's Faction); Adabala Venkateshwara (TDP | Jyothula Nehru's Faction) - Sathibabu Raju has won with a majority of 600 votes | K139: General | L139: - Ganeshula Raju - YSRCP - Thota Narasimham's Faction - Adabala Venkateshwara as De-Facto as he is trying contest for ZPTC elections. - Current Sarpanch, Sathibabu is politically Not Active and currently not thinking to contest for upcoming elections | N139: - TDP has complete support as the JSP Mandal President, Doddu Srinu has won as MPTC with clear support from Adabala Venkateshwara - YSRCP's Ganeshula Raja is the only major leader form YSRCP and there is a possibility of another Kapu leader raising through Chantibabu, as there is a politically factional vaccum - Adabala Suryanarayana, who was in YSRCP (Earlier Chantibabu's faction) is now supporting his younger brother Adabala Venkateshwara - Adabala Suryanarayana has exitted YSRCP as Chantibabu did not support him for MPTC elections due to which both him and chantibabu's faction had to loose MPTC to Dodda Srinivas (JSP) | O139: - Around 30 lakh rupees worth CC-Roads with a stretch of 2KM has been laid during the new govt. tenure - Marripaka Raod (3 KM) contruction also was completed
A140: =ROW(A139) -> 139 | B140: Jaggampeta | C140: Jaggampeta | D140: VENGAYAMMA PURAM | F140: Challa Kumari - 6300843620
A141: =ROW(A140) -> 140 | B141: Jaggampeta | C141: Kirlampudi | D141: Bhupalapatnam | F141: Veeramreddy Ramalingeswara Swami - 9132631999
A142: =ROW(A141) -> 141 | B142: Jaggampeta | C142: Kirlampudi | D142: Burugupudi | F142: Aasapu Ramalakshmi - 7386404556 | G142: YSRCP | H142: Battleground | I142: In 2024 for MLA seat TDP lost around 1600 votes to Patamsetty Suryachandra who contested independently, Patamsetty Suryachandra who is native to Burgupudi village convinced people to vote for him for MLA and vote for Sunil for MP which reflected in the election results as JSP MP candidate (Uday) did not get near the same amount of votes as TDP MLA candidate (Nehru) | J142: In 2020 Patamsetty Nageshwar Rao (Ravi) (Kapu Ex-MPTC) backed Gurajarapu Sathibabu's wife Laxmi (Rajaka) against Asapu Badrarao's wife Asapu Ramalakshmi (Padhmashali, Devanga) | K142: General (Woman) | L142: Patamsetty Krishnamurthy , his wife Sathyavathi was MPTP and Vice-MPP won with about 1200 majority. Patamsetty Suryachandra wife Sridevi might contest in the elections. Suryachandra was able to get 1600 votes when he contested for MLA in 2024 from this village. | M142: Kunche Sathyanarayana (Thathaji)-TDP Patamsetti Krishnamurthy-YCP-Thota Narasimha Patamsetty Nageshwar Rao Ravi(MPTC)-TDP Kunche Sitharamayya (Thathaji)-TDP | O142: CC road worth 20 lakhs
A143: =ROW(A142) -> 142 | B143: Jaggampeta | C143: Kirlampudi | D143: Geddanapalli | F143: Molleti Ganga Bahvani - 9010865217 | G143: YSRCP | H143: Battleground | I143: - Pantham Gandhi&Chantibabu from YSRCP has more cadre than Narasimham in this panchayat - Surishetti Venkatashiva Ex-Sarpanch YSRCP joined TDP is the major leader for TDP Nehru's faction. - Nehru gained 734 votes majority in General Elections 2024 as Chantibabu's and Narasimham's factions got devided - Late. Govindu (MPTC) is the Narasimham's faction | J143: - Molleti Ganga Rao is the De-Facto Sarpanch for his wife Ganga Bhavani, won with a majority of around 800 votes - Surishetti Venkatashiva, who served as Sarpanch for 2 terms lost to Ganga Rao - Venkatashiva was alos in YSRCP but joined TDP during the general elections 2024 | K143: General | L143: - Akula Naveen (JSP | Kapu), who is seeking YSRCP (Pantham Gandhi's) support is the expected candidate with YSRCP - JSP alliance - Gangarao, current Sarpanch from YSRCP is thinking to drop out from the contest. - Surishetti Venkatashiva, is going to be the contestant from TDP even tho alliance JSP party supported Akula Naveen is going with YSRCP - Pantham Gandhi backed candidate always wins in the village | M143: - Pantham Gandhi (Ex-MLA) - - YSRCP - - Surishetti Venkatashiva (Ex-Sarpanch) - Gavara - TDP - Jyothula Nehru - Molleti Gangarao (De-Facto Sarpanch - Wife) - Gavara - YSRCP - Chantibabu&Pantham Gandhi - Akula Naveen (JSP Leader) - Kapu - JSP - Molleti Trimurtulu - Gavara - TDP - Jyothula Nehru (not so impactful) | N143: - YSRCP cadre is divided into two factions into Thota Narasimham&Chantibabu's - TDP has two factions into Venkatashiva and Trimurtulu but not so effective as Trimurtulu has no support - JSP, Kapu leader Akula Naveen is trying to join hands with the YSRCP and get ticket from the alliance of JSP and YSRCP, which can have Kapu and Gavara, two major caste vote banks | O143: - A 3 KM main road was laid during the new TDP tenure towards Kirlampudi | P143: - Drainage and Roads are the other major issues | R143: - MPTC Govinda who was one of the YSRCP leaders (Narasimha's faction) in the panchayat had passed away recently in an accident
A144: =ROW(A143) -> 143 | B144: Jaggampeta | C144: Kirlampudi | D144: Goneda | F144: Allu Vijaya Kumar - 9848068968 | G144: TDP | H144: Battleground | I144: - Allu Vijay, who won as Sarpanch in 2020 from YSRCP, joined the TDP (Nehru's Faction) during the 2024 General Election - Nehru got 990 votes majority from the village, which had never happened for him. - Uday also got 935 votes majority | J144: - Current reservation - UR(G) - Possible reservation - SC(G) - Allu Vijay&Pallikala Gangaraju both from YSRCP contested and the result was a "Tie" with around 1800 votes each - Allu Vijay won the toss adnd sarpanch chair - So, there is a possibility of three candidates contesting in 2026, if its general reservation as Vijay is thinking to change party from TDP to YSRCP and possible candidature factions are from Allu Vijay, Neelam Srinivas(TDP), and Pallikala Gangaraju(YSRCP). | K144: SC (Gen) | L144: If resrvation is "Gen" - Allu Vijay (Current Sarpanch) - 9848068968 - Currently TDP may change to YSRCP - - Pallikala Gangaraju (Contested Sarpanch) - - YSRCP (will leave if Vijay comes to YSRCP) - Thota Narasimham - Neelam Srinivas (Ex Defacto(SC Candidate) Sarpanch) - 9177928888 - TDP - Jyothula Nehru - Ulise Airaju (JSP Mandal President) - 9182335536 - JSP - Jyothula Nehru even tho JSP (May ask for JSP as part of alliance) If reservation is SC or Other - Dummy candidates by three of tthe above: Allu Vijay, Pallikala Gangaraju, Neelam Srinivas | N144: - If Allu Vijay is in TDP, two factions in TDP with Neelam Srinivas and Allu Vijay - And if Allu Vijay changes party to YSRCP, two factions in YSRCP with him and Pallikala Gangaraju - JSP, Airaju is in alliance with TDP and is Nehru's faction - Thota Narsimham is not ready to loose Pallikala Gangaraju for Allu Vijay for what Vijay has done during the General Elections 2024. Allu Vijay also has raised a complaint with YSRCP party as Thota Narasimham is not allowing him into party. | O144: - No major development activities during the new TDP tenure | P144: - Damaged road stretching from Rajupalem to Ramavaram and passing through this village. This 12 km stretch of road is severely damaged, causing inconvenience to villagers trying to reach Jaggampeta. (Not Resolved) | R144: 2nd Feb 2026 Allu Vijay: Sarpanch (2020) | Kapu | Gen | 54 | TDP - Allu Vijay's father has migrated to this village and was sarpanch for 10 years starting from 1981 - Sarpanch in 2001 - Allu Vijay has contested in 2014 ZPTC elections and lost to Veeramareddy Kashibabu with 2000 votes - He was in Chantibabu's faction during 2014 ZPTC elections and was also mandal president of TDP - TDP(chantibabu) --> YSRCP (Chantibabu) --> TDP (Nehru) --> thinking to change YSRCP Neelam Srinivas: Dafacto (SC) Ex Sarpanch | Kapu | Gen | 45 | TDP | Jyothula Nehru - His father contested against Allu Vijay in 2001 and lost - Supported a candidate when SC reserved and won - Cousin of Thota Subbarao - Follower of Jyothula Nehru Pallikala Ganagadhar: Contested Sarpanch (2020 Tie) | Kapu | Gen | | YSRCP | Thota Narsimham - Contested against Allu Vjay in 2020 sarpanch election and was a tie with 1800 votes - Thota Narasimham is backing him currently but may prefer Allu Vijay in future over him
A145: =ROW(A144) -> 144 | B145: Jaggampeta | C145: Kirlampudi | D145: JAGAPATHINAGARAM | F145: Mahendrada Sri Latha - 9160940340
A146: =ROW(A145) -> 145 | B146: Jaggampeta | C146: Kirlampudi | D146: Krishnavaram | F146: Gorakapudi Veera Anantha Lakshmi - Kapu | G146: YSRCP | H146: Battleground | I146: TDP got the majority of 96 votes despite huge wage across the AC, There are around 5 villages in entire Jaggampeta where majority for TDP is less than 100 votes and Krishnavaram village is one of them. This has been the traditionally strongold village for INC/YSRCP. For MP elections YSRCP secured majority of 58 votes which shows the dominance of YCP in the viilage | J146: For Sarpanch elections YSRCP candidate Veera Anantha Laxmi (W/o Gorakapudi Gopinath (GG) secured the majority of 596 votes due to his social work in the village. He runs a water plant with a capacity of 2500 Ltrs serves free water to villagers and a colony in adject village Somaravaram. GG's brother wife got elected as MPTC with 530 votes. GG works in DCCB bank Kakinada and his brother is Government Teacher. Their family have been winning elections for last 3 consecutive terms, TDP candidate Bodiredla Subba Rao (Close to Nehru) his mother elected as MPTC long back by defeating Ungala Satya. There is a perception that Bodireddla family never won Gorkapudi family in Krishnavaram. Bodireddla Thata Rao was a senior leader and his son Subba Rao now aspiring for Sarpanch Position | L146: For the last 4 elections reservation has been General and dominated by Kapu leaders YSRCP - Gorkapudi Veera Anantha Laxmi (GG Wife and Current Sarpanch) TDP - Bodireddla Subba Rao (Kapu - Jyothula Naveen Close aide) - He owns 2 Acres of land in Krishnavaram, Each acres values around 2 Crores - He runs seperate Toll Gate along Polavaram Canal and collects money for Sand Transporation | O146: 200 Meteres of road laid by TDP Government in the village in last 24 months 200 meters CC road and 180 Housing Sites distributed but only 15 under Construction during YSRCP
A147: =ROW(A146) -> 146 | B147: Jaggampeta | C147: Kirlampudi | D147: Mukkollu | F147: Jyothula Rambabu - 8886766667 | G147: TDP | H147: Favourable | I147: TDP secured 400 votes majority due to influence of Mukkolu Veera Babu | J147: This village is dominated by Bussa (Mukkolu) Veera Babu who is relative of Varapula Raja and Thota Venkata Chalam. His father Bussa Subba Rao previouslu served as Sarpanch of the Village. Mukkolu family constructed bridge and roads which gained positive image in the village. During Sarpanch elections Mediboina Nagarjuna (YSRCP) contested from YSRCP, MPTC candidate Viswandula Chakra Rao had issues after 2019 elections but compromised 1 week before elections but didn't yield positive results. Chakra Rao won as MPTC from YSRCP after 30 years currently neutral. He was stopped joining TDP from Mukkolu Veera Babu for 2024 elections. Jyouthula Ram Babu (Present Sarpanch) is fielded by Mukkolu Veera Babu who runs the show in the village. | N147: Two groups in YSRCP 1. Mediboina Nagarjuna (Sarpanch Contestant and Sachivalayam Conevenor - Runs Dairy Farm in Kakinada Town and Milk Centre in Village)
A148: =ROW(A147) -> 147 | B148: Jaggampeta | C148: Kirlampudi | D148: Palem | F148: Adabala Sandya - 8639927455
A149: =ROW(A148) -> 148 | B149: Jaggampeta | C149: Kirlampudi | D149: Rajupalem | F149: Gode Padmavathi - 8790885023 | G149: YSRCP | H149: Battleground | I149: - Thota Narasimham, home village, away just 1KM from Rajupalem has got 339 votes lesser than Jythula Nehru. - Twin Brothers Ganeshula Rambabu and Laxman Rao, big contractors are the supporters and close relatives of Mudragada Padmanabham and are major imactfull leaders in the viillage due to which Thota Narsimham has to losse votes even tho they are from YSRCP - Gandham Umamaheshwar Rao, and Gode Rajashekar and Varaprasad (brothers) are the major TDP leaders - Laxman Rao is also MPTC | J149: - Gode Yesu is the de-facto Sarpanch of the village for his wife and has a backup by the contractor twin brothers Rambabu and Laxman Rao - Won with a majority of 280, competing with Gandham Umamaheshwar Rao (Ex-Sarpanch, 2015), Advocate Jokka Srinu (De-Facto Ex Sarpanch-Mother, 2009), and Gode Rajeshekar - Twin brothers Rambabu and LaxmanRao are very close to Mudragada Padmanabgam and close relatives through Tuni | K149: SC (Gen) | L149: If reservation is General: - Gandham Umamaheshwar Rao (TDP) - Jokka Srinu (TDP) - One supported by Twin Brothers (YSRCP) If SC: - One supported by Umamaheshwar Rao (TDP) - One Supported by Twin Brothers (YSRCP) | N149: TDP: - Gandham Umamaheshwar Rao - Joka Srinu YSRCP: - Twin Brothers (Mudragada faction) - One may get raised by Thota Narasimha | O149: - 2-3 CC Roads were laid in new tenure of Kutami (Contracted by Gandham Umamaheshwaram&Jokka Srinu) | R149: - Ganeshula Rambabu (One among the Twin Brothers) is a close relative to Mudragada Padmanabham Mudragada Padmanbham's doughter was married to the same family from which Ganeshula Rambabu's daughter-in-law comes from(son's wife) - These twin brothers are in business with Jyothula Nehru as they deal many contracts and Nehru gives support in getting new contracts but when it comes to the politics none of them deal with any political benefits or mutual supports
A150: =ROW(A149) -> 149 | B150: Jaggampeta | C150: Kirlampudi | D150: Ramachandrapuram | F150: Thummalapalli Sai Guna Sekhar - 9848258999 | G150: JSP | H150: Battleground | I150: TDP got clear majority in general elections with 587 votes | J150: Katchumarthi Veera Raghava (Kapu) TDP lost elections to Thummalapalli Sai Guna Sekhar (Kapu) YCP by small margin. Thummalapalli Sai Guna Shekar is brother of Thummalapalli Ramesh, Thummalapalli Ramesh's support will play a key role in deciding the next sarpanch. Thummalapalli Sai Guna Shekar used to be in YCP | K150: BC (Gen) | L150: Ponnaganti Sathyanarayana (Padmashali) his mother Appayamma was sarpanch during 2000. Guthukala Subrahmanyam (Padmashali) TDP cadre. | M150: Kachumarthi Veera Raghava's wife Ramalakshmi was MPP during 2016 Thummalapalli Ramesh Babu (JSP Jaggampet ACI) | P150: Water tanks and pipelines are needed to solve drinking water issues in the village.
A151: =ROW(A150) -> 150 | B151: Jaggampeta | C151: Kirlampudi | D151: RAMAKRISHNAPURAM | F151: Saraswathi Kanta - 9493882666
A152: =ROW(A151) -> 151 | B152: Jaggampeta | C152: Kirlampudi | D152: S.Thimmapuram | F152: Mandeti Veeralakshmi - 9959624492
A153: =ROW(A152) -> 152 | B153: Jaggampeta | C153: Kirlampudi | D153: Simhadripuram | F153: Kalapureddy Papayamma - 9951135685
A154: =ROW(A153) -> 153 | B154: Jaggampeta | C154: Kirlampudi | D154: SOMANARAYANIPETA | F154: Sarise Lakshmi Parvathi - 9490153453
A155: =ROW(A154) -> 154 | B155: Jaggampeta | C155: Kirlampudi | D155: somavaram | F155: Jyothula Seeta Rama Lakshmi - 8686864047
A156: =ROW(A155) -> 155 | B156: Jaggampeta | C156: Kirlampudi | D156: SUNGARAYUNIPALEM | F156: Pattu Chantibabu - 9848652974
A157: =ROW(A156) -> 156 | B157: Jaggampeta | C157: Kirlampudi | D157: Thamarada | F157: Thota Annayya - 8309332929 | G157: YSRCP | H157: Favourable | J157: Thota Ayyana being the senior leader and close associate of Thota Narsimham was elected unanimously from YSRCP as Sarpanch, YSRCP aspirant and anti group of Thota Ayyanna is Adabala Srinivas (MPTC Contestant) was compromised and convinced by Jyothula Chanti Bbau to contest as MPTC later Thota Ayyanna supported JSP MPTC candidate Gokeda Raja. Thota Ayyanna's cross party relations will decide the outcome of the elections, Gokeda Ram Babu (Ex- Nehru Close Aide and Chief Election Agent of Sunil) is currently suffering from Paralysis and his wife may contest as Sarpanch candidate from TDP | K157: General | L157: Anukula Srikanth (TDP- Kapu- Ex- Sarpanch (2014), Encouraged by Jyothua Naveen) Gokeda Raja (JSP -Kapu- MPTC) | M157: K Shiva Ramakrishna - Vice President - YSRCP - Jyothula Chanti Babu Gandham Surya Chakradora - Ward Member - YSRCP - Neutral Geddam. Manikanta - Ward Member - YSRCP - Jyouthula Chanti Babu | N157: YSRCP divided into two factions 1. Thota Ayyanna (Sarpanch) 2. Adabala Srinivas (MPTC Contestant)
A158: =ROW(A157) -> 157 | B158: Jaggampeta | C158: Kirlampudi | D158: Veeravaram | F158: Ambati Bujjamma - 9441807628 | I158: This is the native village of YSRCP MLA candidate Thota Narsimham, His brothers Thota Ravi (Ex-MPP) and Thota Gandhi (ZPTC) who were revoluted against Narsimham before elections and held a press meet in Kirlampudi. Ravi and Gandhi were perceived as close aides of Chanti Babu after his MLA ticket rejection with the initiation of Bhupalapatnam they joined TDP. Still TDP secured 231 majority in the Village even after Ravi and Gandhi's joining, for MP elections Sunil secured huge majority of 1052 with support of Thota families. | J158: Ambati Bujjamma (Mala- Reportedly having relationship with Chanti Babu's Mavayya - Sister's husband village), She took blessings from Thota Narsimham for her nomination and supported by Thota family which helped to win the Sarpanch elections
A159: =ROW(A158) -> 158 | B159: Jaggampeta | C159: Kirlampudi | D159: Velanka | E159: Velanka | F159: Rayudu Swami - 9247855118 | G159: TDP | H159: Favourable | I159: TDP got 972 votes majority over YSRCP, TDP got majority in every booth. The clear majority shows a change in trend as TDP did not perform well in previous elections even in 2014. | J159: Dhomala Gangadher (YCP) lost elections with one vote against Rayudu Swami (TDP). Due to corruption by YCP leaders like Adabala Srinu and Gangadher. TDP got 6 wards and YCP got 6 wards. Gangadher's follower Bolla Venkatrao (SC) was elected in the election before 2020 before Rayudu Swami. | K159: General | L159: Gande Chinna Kasi S/o Gande Chellarao Chinnaraju and Gande Pedha Kasi (land lord) are aspiring for Sarpanch. Gande family have lot of votes in the village and they might decide internally on who should contest. YCP is looking to contest Setti Apparao who runs a sweet shop in Kirlampudi, his extended family contains around 170 votes. He have good relationship with TDP and JSP cadre in the village. Inti Tammarao (Tammaji) is an aspirant from TDP. He did no have the support of current sarpanch Rayudi Swami. | N159: YCP two factions Dhomala Gangadhar (Chantibabu) Setti Somaraju (Narasimha) | O159: Current poles water tanks by sarpanch, NRGC road by MLA
A160: =ROW(A159) -> 159 | C160: Kotananduru | D160: ALLIPUDI | F160: Tharipe Nookalamma - 9010752300
A161: =ROW(A160) -> 160 | C161: Kotananduru | D161: APPALARAJUPETA | F161: Nallamilli Surya Kumari - 9573933445
A162: =ROW(A161) -> 161 | C162: Kotananduru | D162: BHIMAVARAPUKOTA | F162: Jigatala Veerababu - 8096663901
A163: =ROW(A162) -> 162 | C163: Kotananduru | D163: BILLANANDURU | F163: Botsa Manga - 9951353839
A164: =ROW(A163) -> 163 | C164: Kotananduru | D164: BODHAVARAM | F164: Vegi Lakshmi - 9491332202
A165: =ROW(A164) -> 164 | C165: Kotananduru | D165: INDUGAPALLI | F165: Kunche Satyavathi - 9441813892
A166: =ROW(A165) -> 165 | C166: Kotananduru | D166: JAGANNADHAPURAM | F166: Lekkala Upendra - 6281662204
A167: =ROW(A166) -> 166 | C167: Kotananduru | D167: K.A.MALLAVARAM | F167: Vemula Satyaveni - 9441326672
A168: =ROW(A167) -> 167 | C168: Kotananduru | D168: K.E.CHINNAYYAPALEM | F168: Gudlu Sattibabu - 9493138916
A169: =ROW(A168) -> 168 | C169: Kotananduru | D169: K.KOTTAM | F169: Dogga Lakshmi - 9493327269
A170: =ROW(A169) -> 169 | C170: Kotananduru | D170: K.O.AGRAHARAM | F170: Sarika Devudu - 9492668264
A171: =ROW(A170) -> 170 | C171: Kotananduru | D171: KAKARAPALLI | F171: Venkateswara Rao Bantupalli - 9440429349
... A199: =ROW(A198) -> 198 | C199: Peddapuram | D199: VALUTHIMMAPURAM | F199: Bullama Sainam - 9494154536
A200: =ROW(A199) -> 199 | B200: Prathipadu | C200: Prathipadu | D200: BAVURUVAKA | F200: Doddi Satyanarayana - 6304928489
A201: =ROW(A200) -> 200 | B201: Prathipadu | C201: Prathipadu | D201: BURADAKOTA | F201: Chinthala Chinnalamma - 9493461257
A202: =ROW(A201) -> 201 | B202: Prathipadu | C202: Prathipadu | D202: CHINASANKARLAPUDI | F202: Epuri Rama Rao - 9177374670 | G202: YSRCP | H202: Favourable | I202: TDP got 500 votes majority in the assembly elections. | J202: Apuri Rama Rao (Sagara) YCP won against Apuri Sirivas Rao (Sagara) TDP. Miryala Srinu MPTC and Apuri Srinvias Rao used to be two groups in TDP at that time, Srinivas Rao went to YCP before elections. | K202: General | L202: Miryala Srinu (MPTC) TDP Baddeti Srinu (Sagara) TDP Neeti Sangam president Yaka Sathyanarayana (Sagara) (TDP) Apuri Ramarao (Sagara) (YCP) Sarpanch Pilla Kondal Rao (Chinna) OC Kapu YCP Apuri Ramarao (Sagara) (Sarpanch contestant last time) | N202: Apuri Ramarao (present sarpanch) might be interested in joining TDP. | P202: Pilla Kondal Rao allegedly collected bill for a sachivalayam building he did not build and paid back around 6 lakhs from the total bill of around 18 lakhs
A203: =ROW(A202) -> 202 | B203: Prathipadu | C203: Prathipadu | D203: CHINTALURU | F203: Pandrada Ganga - 7032881258
A204: =ROW(A203) -> 203 | B204: Prathipadu | C204: Prathipadu | D204: DHARMAVARAM | F204: Benthukurthi Suseela - 9032206048
A205: =ROW(A204) -> 204 | B205: Prathipadu | C205: Prathipadu | D205: ELURU | F205: Rongala Satyanarayana - 9848851521
A206: =ROW(A205) -> 205 | B206: Prathipadu | C206: Prathipadu | D206: GAJJANAPUDI | F206: Gonagala Appalaraju - 9014143289
A207: =ROW(A206) -> 206 | B207: Prathipadu | C207: Prathipadu | D207: GOKAVARAM | F207: Vanaparthi Rama Lakshmi - 9701654577
A208: =ROW(A207) -> 207 | B208: Prathipadu | C208: Prathipadu | D208: LAMPAKALOVA | F208: Pandi Mani Kumari - 9676356350
A209: =ROW(A208) -> 208 | B209: Prathipadu | C209: Prathipadu | D209: PANDAVULAPALEM | F209: Gummidi Rama Lakshmi - 9948672121
A210: =ROW(A209) -> 209 | B210: Prathipadu | C210: Prathipadu | D210: PEDA SANKARLAPUDI | F210: Surnidi Nagaratnam - 9948498889 | G210: JSP | H210: Battleground | I210: The sarpanch worked for the assembly elections and moved to JSP after elections Surnidi Nagaratnam son Surnidi Suresh. After MLA won here there has been a conflict for power and joined JSP. | J210: In the sarpanch elections Surnidi Nagaratnam won with 70 votes majority, wife of Bullabbai (sarpanch contestant), their son Surnidi Suresh is also active in politics. They won against Dale Chittibabu contested his mother in the elections, he got Annavaram board member after that. Dale Tambarao (Nallababu) won MPTC against TDP candidate Dale Nookaraju, Chittibabu and Tambarao are cousins, Nookaraju is from a seperate family. | K210: General | L210: Dale Chittibabu (YCP) (Sarpanch contestant) Dale Naveern (TDP Raja's cousin) might put up a candidate | M210: Juvvina Thirupathi Rao TDP Kapu
A211: =ROW(A210) -> 210 | B211: Prathipadu | C211: Prathipadu | D211: PEDDIPALEM | F211: Devara Manasa - 9393167777 | G211: YSRCP | H211: Favourable | I211: - TDP has secured majority over 800 votes against YSRCP. - YSRCP had the anti-incumbency as the promised road towards "Uttarakanchi" was not laid. No major infrastructre was developed and the 300 housing Pattas that were given are on the hill top because which no one was ready to move and created anti-incumbency | J211: - Devara Manasa w/o Devara Ramesh from YSRCP has won the election with a majority of 369 votes against Reesu Sathibabu who contested from TDP - Village is Yadav dominated (1500/3500) and Devara Ramesh comes from the Yadav community whereas Reesu Sathibabu comes from the settibalija (700/3500) which gave Ramesh more support | K211: BC (Gen) | L211: - TDP: Deva Rajubabu | Yadav Kundala Apparao | Yadav are the major contestants Deva Rajubabu is actually nephew of K Apparao - YSRCP: - the top leadership is backing no one but trying to bring kapu leaders forward - No major contestants and they are very less confident to win - Devara Ramesh may contest but only to save the reputation of the group - If the reservation is Gen, kapu leader Enugu John may contest with the support from Giribabu | N211: TDP: - Deva Rajubabu and Kundala Apparao's are the only factions that are there in the village but will be working under the leadership of MLA Varupula Satyaprabha YSRCP: - Devara Ramesh | Yadav - Enugu John | Kapu | backed by Giribabu | O211: - The most important road for the village, Uttarakanchi to Peddipalem with a 5 KM stretch was laid by the new govt with an expense of 1.2 Crores. - 4 more CC roads were also laid with a cost of around 80 lakh rupees | P211: - 6 KM long Road from Peddipalem to Pandavulapalem - Need Drains to be constructed - Drinking watre scarcity | R211: - Current Sarpanch Devara Ramesh, YSRCP is too much disppointed with the top leadership of the constituency and even with YS Jagan
A212: =ROW(A211) -> 211 | B212: Prathipadu | C212: Prathipadu | D212: POTHULURU | F212: Bondu Rambabu - 9492037619
A213: =ROW(A212) -> 212 | B213: Prathipadu | C213: Prathipadu | D213: PRATHIPADU | F213: Vijayalakshmi Gudala - 9849752539
A214: =ROW(A213) -> 213 | B214: Prathipadu | C214: Prathipadu | D214: RACHAPALLI | F214: Saripalli Lova Lakshmi - 9505234510
A215: =ROW(A214) -> 214 | B215: Prathipadu | C215: Prathipadu | D215: ROWTHUPALEM | F215: Kongana Bullammayi - 9581990370
A216: =ROW(A215) -> 215 | B216: Prathipadu | C216: Prathipadu | D216: SARABHAVARAM | F216: Amaradi Venkatrao - 9989798634
A217: =ROW(A216) -> 216 | B217: Prathipadu | C217: Prathipadu | D217: T.RAYAVARAM | F217: Thatavarthy Subbarao - 9948116733
A218: =ROW(A217) -> 217 | B218: Prathipadu | C218: Prathipadu | D218: U.JAGANNADHAPURAM | F218: Nadigatla Trimurthulu - 9849189893
A219: =ROW(A218) -> 218 | B219: Prathipadu | C219: Prathipadu | D219: UTTARAKANCHI | F219: Manthina Venkata Ramana - 9000244888
...

Sheet Key Leaders
A1: Assembly | B1: Mandal | C1: Panchayat | D1: Rank | E1: Full Name | F1: Caste | G1: Category | H1: Party | I1: Political Designations | J1: Mobile | K1: Influence | L1: Description

Sheet Back End
A1: Assembly | B1: Mandal | C1: Panchayat | D1: Panchayat / Village / Hamlet | E1: {=A:A&"-"&B:B&"-"&C:C&"-"&D:D} -> Assembly-Mandal-Panchayat-Panchayat / Village / Hamlet | F1: Filtered Mandal | G1: Filtered Village | H1: TDP | I1: TDP Ahead | J1: Strong | K1: Infrastructure | L1: UPTO 50 Votes | M1: Acharyulu | N1: OC
A2: Jaggampeta | B2: Gandepalle | C2: Borrampalem | D2: Borrampalem | E2: Jaggampeta-Gandepalle-Borrampalem-Borrampalem | F2: =IFERROR(__xludf.DUMMYFUNCTION("unique(filter(B:B,A:A=Dashboard!A2))"),"#N/A") -> #N/A | G2: =IFERROR(__xludf.DUMMYFUNCTION("arrayformula(sort(proper(filter(D:D,A:A=Dashboard!A2,B:B=Dashboard!D2)),1,true))"),"#N/A") -> #N/A | H2: YSRCP | I2: TDP Closely Ahead | J2: Medium | K2: Drinking Water | L2: UPTO 100 Votes | M2: Adhivelama | N2: BC
A3: Jaggampeta | B3: Gandepalle | C3: Gandepalle | D3: Gandepalle | E3: Jaggampeta-Gandepalle-Gandepalle-Gandepalle | H3: JSP | I3: Split between YSRCP & TDP | J3: Weak | K3: Government Schemess | L3: UPTO 200 Votes | M3: Agnikula Kshatriya | N3: SC
A4: Jaggampeta | B4: Gandepalle | C4: K. Nayakampalle | D4: K. Nayakampalle | E4: Jaggampeta-Gandepalle-K. Nayakampalle-K. Nayakampalle | H4: BSP | I4: JSP Ahead | K4: Irrigation Facilities | L4: Above 200 Votes | M4: Ayyerula | N4: ST
A5: Jaggampeta | B5: Gandepalle | C5: K.Gopalapuram | D5: K.Gopalapuram | E5: Jaggampeta-Gandepalle-K.Gopalapuram-K.Gopalapuram | H5: CPI / CPM | I5: Split between YSRCP & JSP | K5: Lack of Funds to GPs | L5: Above 600 Votes | M5: Balija | N5: Others BC
A6: Jaggampeta | B6: Gandepalle | C6: Mallepalli | D6: Mallepalli | E6: Jaggampeta-Gandepalle-Mallepalli-Mallepalli | I6: YSRCP Ahead | K6: Prevalent Liquor | M6: Battarajulu | N6: Others SC
A7: Jaggampeta | B7: Gandepalle | C7: Mallepalli | D7: Pathuru | E7: Jaggampeta-Gandepalle-Mallepalli-Pathuru | I7: YSRCP Closely Ahead | K7: Illegal Sand Mining | M7: Bondeelu | N7: Others ST
A8: Jaggampeta | B8: Gandepalle | C8: Murari | D8: Murari | E8: Jaggampeta-Gandepalle-Murari-Murari | I8: JSP Closely Ahead | K8: Sanitization | M8: Brahmin
A9: Jaggampeta | B9: Gandepalle | C9: N.T.Rajapuram | D9: N.T.Rajapuram | E9: Jaggampeta-Gandepalle-N.T.Rajapuram-N.T.Rajapuram | I9: Split between JSP & TDP | K9: Other Issues | M9: Budaga Gangali
A10: Jaggampeta | B10: Gandepalle | C10: Neeladriraopeta | D10: Neeladriraopeta | E10: Jaggampeta-Gandepalle-Neeladriraopeta-Neeladriraopeta | I10: Split between YSRCP, TDP & JSP | M10: Budaga Jungaalu
A11: Jaggampeta | B11: Gandepalle | C11: P. Nayakampalle | D11: P. Nayakampalle | E11: Jaggampeta-Gandepalle-P. Nayakampalle-P. Nayakampalle | I11: NA | M11: Chittikarnalu
A12: Jaggampeta | B12: Gandepalle | C12: P.Surampalem | D12: P.Surampalem | E12: Jaggampeta-Gandepalle-P.Surampalem-P.Surampalem | M12: Mani Dora
A13: Jaggampeta | B13: Gandepalle | C13: P.Surampalem | D13: K.Surampalem | E13: Jaggampeta-Gandepalle-P.Surampalem-K.Surampalem | M13: Christian
A14: Jaggampeta | B14: Gandepalle | C14: Ramayyapalem | D14: Ramayyapalem | E14: Jaggampeta-Gandepalle-Ramayyapalem-Ramayyapalem | M14: Dasari
A15: Jaggampeta | B15: Gandepalle | C15: Singarampalem | D15: Singarampalem | E15: Jaggampeta-Gandepalle-Singarampalem-Singarampalem | M15: Devanga
A16: Jaggampeta | B16: Gandepalle | C16: Subbayamma Peta | D16: Subbayamma Peta | E16: Jaggampeta-Gandepalle-Subbayamma Peta-Subbayamma Peta | M16: Dommarlu
A17: Jaggampeta | B17: Gandepalle | C17: Talluru | D17: Talluru | E17: Jaggampeta-Gandepalle-Talluru-Talluru | M17: Dora
A18: Jaggampeta | B18: Gandepalle | C18: Uppalapadu | D18: Uppalapadu | E18: Jaggampeta-Gandepalle-Uppalapadu-Uppalapadu | M18: Dudekula
A19: Jaggampeta | B19: Gandepalle | C19: Yellamilli | D19: Yellamilli | E19: Jaggampeta-Gandepalle-Yellamilli-Yellamilli | M19: Gangireddula
A20: Jaggampeta | B20: Gandepalle | C20: Yerrampalem | D20: Yerrampalem | E20: Jaggampeta-Gandepalle-Yerrampalem-Yerrampalem | M20: Ganjam
A21: Jaggampeta | B21: Gandepalle | C21: Z.Ragampeta | D21: Z.Ragampeta | E21: Jaggampeta-Gandepalle-Z.Ragampeta-Z.Ragampeta | M21: Gavara
A22: Jaggampeta | B22: Gokavaram | C22: Atchutapuram | D22: Atchutapuram | E22: Jaggampeta-Gokavaram-Atchutapuram-Atchutapuram | M22: Gowda
A23: Jaggampeta | B23: Gokavaram | C23: Gadelapalem | D23: Gadelapalem | E23: Jaggampeta-Gokavaram-Gadelapalem-Gadelapalem | M23: Iyyarakala
... A92: Kakinada Rural | B92: Kakinada (Rural) | C92: S. Atchuthapuram | D92: S. Atchuthapuram | E92: Kakinada Rural-Kakinada (Rural)-S. Atchuthapuram-S. Atchuthapuram | M92: Pamula
A93: Kakinada Rural | B93: Kakinada (Rural) | C93: Sarpavaram | D93: Sarpavaram | E93: Kakinada Rural-Kakinada (Rural)-Sarpavaram-Sarpavaram
A94: Kakinada Rural | B94: Kakinada (Rural) | C94: Suryarao Peta | D94: Suryarao Peta | E94: Kakinada Rural-Kakinada (Rural)-Suryarao Peta-Suryarao Peta
A95: Kakinada Rural | B95: Kakinada (Rural) | C95: Swamynagar | D95: Swamynagar | E95: Kakinada Rural-Kakinada (Rural)-Swamynagar-Swamynagar
A96: Kakinada Rural | B96: Kakinada (Rural) | C96: Thammavaram | D96: Thammavaram | E96: Kakinada Rural-Kakinada (Rural)-Thammavaram-Thammavaram
A97: Kakinada Rural | B97: Kakinada (Rural) | C97: Thimmapuram | D97: Thimmapuram | E97: Kakinada Rural-Kakinada (Rural)-Thimmapuram-Thimmapuram
A98: Kakinada Rural | B98: Kakinada (Rural) | C98: Toorangi | D98: Toorangi | E98: Kakinada Rural-Kakinada (Rural)-Toorangi-Toorangi
A99: Kakinada Rural | B99: Kakinada (Rural) | C99: Vakalapudi | D99: Vakalapudi | E99: Kakinada Rural-Kakinada (Rural)-Vakalapudi-Vakalapudi
A100: Kakinada Rural | B100: Kakinada (Rural) | C100: Valasapakalu | D100: Valasapakalu | E100: Kakinada Rural-Kakinada (Rural)-Valasapakalu-Valasapakalu
A101: Kakinada Rural | B101: Karapa | C101: Aratlakatta | D101: Aratlakatta | E101: Kakinada Rural-Karapa-Aratlakatta-Aratlakatta
A102: Kakinada Rural | B102: Karapa | C102: G. Bhavaram | D102: G. Bhavaram | E102: Kakinada Rural-Karapa-G. Bhavaram-G. Bhavaram
A103: Kakinada Rural | B103: Karapa | C103: Goddatipalem | D103: Goddatipalem | E103: Kakinada Rural-Karapa-Goddatipalem-Goddatipalem
A104: Kakinada Rural | B104: Karapa | C104: Gorripudi | D104: Gorripudi | E104: Kakinada Rural-Karapa-Gorripudi-Gorripudi
... A378: Pithapuram | B378: Pithapuram Town | C378: Pithapuram Town | D378: Pithapuram Town | E378: Pithapuram-Pithapuram Town-Pithapuram Town-Pithapuram Town
A379: Pithapuram | B379: Gollaprolu Town | C379: Gollaprolu Town | D379: Gollaprolu Town | E379: Pithapuram-Gollaprolu Town-Gollaprolu Town-Gollaprolu Town | K379: Jaggampeta-Jaggampeta-Vengayamma Puram
A380: Prathipadu | B380: Yeleswaram Town | C380: Yeleswaram Town | D380: Yeleswaram Town | E380: Prathipadu-Yeleswaram Town-Yeleswaram Town-Yeleswaram Town | K380: Jaggampeta-Kirlampudi-Bhupalapantam
A381: Peddapuram | B381: Peddapuram Town | C381: Peddapuram Town | D381: Peddapuram Town | E381: Peddapuram-Peddapuram Town-Peddapuram Town-Peddapuram Town | K381: Jaggampeta-Kirlampudi-Burugupudi
A382: Peddapuram | B382: Samalkota Town | C382: Samalkota Town | D382: Samalkota Town | E382: Peddapuram-Samalkota Town-Samalkota Town-Samalkota Town | K382: Jaggampeta-Kirlampudi-Geddanapalle
A383: Kakinada Urban | B383: Kakinada City | C383: Kakinada City | D383: Kakinada City | E383: Kakinada Urban-Kakinada City-Kakinada City-Kakinada City | K383: Jaggampeta-Kirlampudi-Goneda
A384: Kakinada Rural | B384: Kakinada City | C384: Kakinada City | D384: Kakinada City | E384: Kakinada Rural-Kakinada City-Kakinada City-Kakinada City | K384: Jaggampeta-Kirlampudi-Jagapathinagaram
A385: Pithapuram | B385: Kothapalle | C385: Subbampeta | D385: Subbampeta | E385: Pithapuram-Kothapalle-Subbampeta-Subbampeta | K385: Jaggampeta-Kirlampudi-Krishnavaram
E386: --- | K386: Jaggampeta-Kirlampudi-Mukkollu
E387: --- | K387: Jaggampeta-Kirlampudi-Palem
E388: --- | K388: Jaggampeta-Kirlampudi-Rajupalem
E389: --- | K389: Jaggampeta-Kirlampudi-Ramachandra Puram
E390: --- | K390: Jaggampeta-Kirlampudi-Ramakrishnapuram
E391: --- | K391: Jaggampeta-Kirlampudi-S.Thimmapuram
E392: --- | K392: Jaggampeta-Kirlampudi-Simhadri Puram
E393: --- | K393: Jaggampeta-Kirlampudi-Somanarayani Peta
E394: --- | K394: Jaggampeta-Kirlampudi-Somavaram
E395: --- | K395: Jaggampeta-Kirlampudi-Sungarayunipalem
E396: --- | K396: Jaggampeta-Kirlampudi-Thamarada
E397: --- | K397: Jaggampeta-Kirlampudi-Veeravaram
... E427: --- | K427: Kakinada Rural-Karapa-Nadakuduru
E428: ---
E429: --- | K429: Kakinada Rural-Karapa-Patharlagadda
E430: --- | K430: Kakinada Rural-Karapa-Peda Kothuru
E431: --- | K431: Kakinada Rural-Karapa-Peddapurappadu
E432: --- | K432: Kakinada Rural-Karapa-Penuguduru
E433: --- | K433: Kakinada Rural-Karapa-Siripuram
E434: --- | K434: Kakinada Rural-Karapa-Uppalanka
E435: --- | K435: Kakinada Rural-Karapa-Vakada
E436: --- | K436: Kakinada Rural-Karapa-Valasapakulu
E437: --- | K437: Kakinada Rural-Karapa-Velangi
E438: --- | K438: Kakinada Rural-Karapa-Vemulavada
E439: --- | K439: Kakinada Rural-Karapa-Vijayarayudu Palem
E440: --- | K440: Kakinada Rural-Karapa-Yandamuru
... E1943: --- | K1943: Pithapuram-Kothapalle-Subbampeta-Subbampeta

Sheet Raw Data - Field Input
A1: Assembly | B1: Mandal Name | C1: GP Name | D1: Village Hamlet | E1: Current Categorisation | F1: Field Categorisation | G1: Seat Call | H1: Top Cohorts in the Village | I1: Reasons for Win/ Loss in 2019 Elections | J1: Elaboration of the Reason | K1: Current Party Positioning | L1: Reasoning for Party Positioning | M1: TDP Assesment | N1: Reasoning | O1: YSRCP Assesment | P1: Reasoning | Q1: JSP Assesment | R1: Reasoning | S1: Perception on the Government | T1: Reasoning | U1: Remarks | V1: Field Remarks | W1: Status | Y1: Created by
A2: Pithapuram | B2: Gollaprolu | C2: =IFERROR(__xludf.DUMMYFUNCTION("filter('Back End'!C:C,'Back End'!A:A=A2,'Back End'!B:B=B2,'Back End'!D:D=D2)"),"#REF!") -> #REF! | D2: KODAVALI | E2: Safe | G2: TDP Ahead | H2: 1. Farmers 2. Fisherman | I2: Caste Composition | J2: 1.SVSN Varma has followed a divide and rule policy in two different castes(kapu and mala) which led to a change of decision in the vote bank. | K2: TDP>YCP>JSP | L2: 1. Due to the leader's reputation in the castes of Mala and Settibalija, TDP had a sizable vote base from the beginning. 2. If TDP and JSP are having an alliance then there is a great chance of a huge vote bank. | M2: Strong | N2: Strong Cadre and Strong Leadership | O2: Medium | P2: Strong Cadre and Strong Leadership | Q2: Strong | R2: Strong Cadre and Strong Leadership | S2: Positive | T2: Positive Image Welfare Schemes | W2: Review
A3: Prathipadu | B3: Prathipadu | C3: =IFERROR(__xludf.DUMMYFUNCTION("filter('Back End'!C:C,'Back End'!A:A=A3,'Back End'!B:B=B3,'Back End'!D:D=D3)"),"#REF!") -> #REF! | D3: Uttarakanchi | E3: Safe | G3: TDP Ahead | H3: 1. Farmers | I3: Caste Composition | J3: 1.This is a Kapu-dominated village and JSP was able to secure more of the Kapu vote bank which split the YCP vote Bank. 2.YCP won over JSP with a very small majority of 11 votes. 3.TDP was able to consolidate the vote bank from Maximum BC Communities ( Senapathulu, Settibalija, and Rajaka) | K3: YCP>TDP>JSP | L3: 1. The JSP & TDP alliance will be the crucial factor in securing the Kapu vote bank along with BC communities. 2)TDP has a strong hold in BC Communities (Yadava). 3) YCP has the majority of the vote bank from SC Community Mala | M3: Strong | N3: Strong Cadre and Strong Leadership | O3: Weak | P3: Weak Leadership & Weak Cadre | Q3: Strong | R3: Strong Cadre and Strong Leadership | S3: Negative | T3: No Development | W3: Complete
A4: Prathipadu | B4: Sankhavaram | C4: =IFERROR(__xludf.DUMMYFUNCTION("filter('Back End'!C:C,'Back End'!A:A=A4,'Back End'!B:B=B4,'Back End'!D:D=D4)"),"#REF!") -> #REF! | D4: Mandapam | E4: Battleground | F4: TDP Closely Ahead | G4: TDP Closely Ahead | H4: 1. Paddy Farmers 2. Daily wage Labourers 3. Cashew farmers 4. Mango Farmers 5. Cotton and Vegetable Farmers | I4: Caste Composition | J4: 1.YCP has the majority of the vote bank from Mala and Kondareddy and a slight edge from the Kapu vote bank due to local Leadership. 2.TDP has consolidated the majority vote bank from the Kapu and BC communities (Yadava). | K4: YCP>TDP>JSP | L4: The corruption of the YSRCP, the lack of public housing, and the poor condition of the roads under YSRCP government are all being vigorously fought against by the TDP. | M4: Strong | N4: Strong Cadre and Strong Leadership | O4: Strong | P4: Strong Cadre and Strong Leadership | Q4: Weak | R4: Weak Leadership & Weak Cadre | S4: Positive | T4: Positive Image Welfare Schemes | W4: Review | Y4: Prashanth
A5: Pithapuram | B5: Pithapuram | C5: =IFERROR(__xludf.DUMMYFUNCTION("filter('Back End'!C:C,'Back End'!A:A=A5,'Back End'!B:B=B5,'Back End'!D:D=D5)"),"#REF!") -> #REF! | D5: Mallam | E5: Battleground | G5: Dead Heat | H5: 1. Farmers | I5: Caste Composition | J5: 1. This is a Kapu-dominated village and JSP was able to split the YCP Vote bank. 2. YSRCP was banking on the SC vote bank (Mala, Madiga) which constitutes 600 votes in the village. | K5: YCP>TDP>JSP | L5: 1)The JSP & TDP alliance will be the crucial factor in securing the Kapu vote bank along with BC communities. 2)TDP has a stronghold in BC Communities (Settibalija, Nayibrahmin, Rajaka). 3) YCP has the majority of the vote bank from SC Community Mala and Madiga. | M5: Strong | N5: Strong Cadre and Strong Leadership | O5: Strong | P5: Strong Cadre and Strong Leadership | Q5: Strong | R5: Strong Cadre and Strong Leadership | S5: Positive | T5: Positive Image Welfare Schemes | W5: Complete
A6: Pithapuram | B6: Pithapuram | C6: =IFERROR(__xludf.DUMMYFUNCTION("filter('Back End'!C:C,'Back End'!A:A=A6,'Back End'!B:B=B6,'Back End'!D:D=D6)"),"#REF!") -> #REF! | D6: Kolanka | E6: Battleground | G6: Dead Heat | H6: 1.Farmers 2. Labours | I6: JSP Split the Votes | J6: 1. This is a Kapu-dominated village and JSP was able to split the YCP's Kapu Vote bank 2. TDP has consolidated the majority vote bank from BC communities (Settibalija, Kummari, Rajaka,). | K6: YCP>TDP>JSP | L6: 1) The JSP & TDP alliance will be the crucial factor in securing the Kapu vote bank along with BC communities(Settibalija, Kummari, Rajaka,). 2) Despite having a vote bank from Mala and Madiga and a little advantage from Kapu, YCP has a slight negative impact because no developments have been made. | M6: Strong | N6: Strong Cadre and Strong Leadership | O6: Strong | P6: Strong Cadre and Strong Leadership | Q6: Weak | R6: Weak Leadership & Weak Cadre | S6: Negative | T6: No Development | W6: Complete
A7: Pithapuram | B7: Pithapuram | C7: =IFERROR(__xludf.DUMMYFUNCTION("filter('Back End'!C:C,'Back End'!A:A=A7,'Back End'!B:B=B7,'Back End'!D:D=D7)"),"#REF!") -> #REF! | D7: Fakruddinpalem | E7: Battleground | G7: Dead Heat | H7: 1.Farmers 2.Agriculture Labours | I7: Caste Composition | J7: 1.This villlage witnesses BC (Settibalija ,Yadava) vs Kapu fight 2.JSP was able to split the YCP Vote bank. 3.YCP was banking on the SC vote bank (Mala, Madiga) | K7: TDP>YCP>JSP | L7: 1) The JSP & TDP alliance will be the crucial factor in securing the Kapu vote bank along with BC communities(Settibalija and Yadavas). | M7: Strong | N7: Strong Cadre Weak Leadership | O7: Medium | P7: Strong Cadre Weak Leadership | Q7: Weak | R7: Weak Leadership & Weak Cadre | S7: Negative | T7: No Development | W7: Incomplete
A8: Pithapuram | B8: Pithapuram | C8: =IFERROR(__xludf.DUMMYFUNCTION("filter('Back End'!C:C,'Back End'!A:A=A8,'Back End'!B:B=B8,'Back End'!D:D=D8)"),"#REF!") -> #REF! | D8: Narasingapuram | E8: Battleground | F8: TDP Ahead | G8: Dead Heat | H8: 1)Farmers (Paddy) 2)labours | I8: Caste Composition | J8: 1. This is the BC (Settibalija) dominant village and this community are split between YCP and TDP. 2. Mala and Madiaga constitute around (1000-Votes ) majorly inclined towards YCP. 3.JSP has negligible presence . | K8: YCP>TDP>JSP | L8: 1. TDP has a strong presence in the Settibalija community and the TDP+JSP alliance may also help to consolidate the majority of the kapu vote bank. 2. Setti Balija community and other minor BC communities are inclined towards TDP due to the local leadership of Rayadu Chinni (Sarpanch contestant). | M8: Strong | N8: Strong Cadre and Strong Leadership | O8: Medium | P8: Strong Leadership but Weak Vote Bank | Q8: Weak | R8: Weak Leadership & Weak Cadre | S8: Positive | T8: Positive Image Welfare Schemes | U8: Bills are pending for Ambedkar statue | W8: Complete
A9: Prathipadu | B9: Prathipadu | C9: =IFERROR(__xludf.DUMMYFUNCTION("filter('Back End'!C:C,'Back End'!A:A=A9,'Back End'!B:B=B9,'Back End'!D:D=D9)"),"#REF!") -> #REF! | D9: PEDDIPALEM | E9: Favourable | G9: TDP Closely Ahead | H9: 1. Farmers 2. Agriculture Labour | I9: Caste Composition | J9: 1. This is a Yadava-dominated village and the community is split between both YSRCP and TDP due to the local leadership. 2. Setti Balija community and other minor BC communities are inclined towards TDP due to the local leadership of Satti Babu (Sarpanch contestant). 3. Madiga and Mala communities constitute (350- Votes) and are majorly inclined towards YSRCP. | K9: TDP>YCP>JSP | L9: 1. There is disgruntlement in Yadava community due to lack of development and issues between Sarpanch (Devara Manasa- Anti-MLA) and MPTC Londa Babu (Yadav) which will impact YSRCP vote bank 2. TDP has solid BC vote bank in the village along with strong leadership | M9: Strong | N9: Strong Cadre and Strong Leadership | O9: Strong | P9: Strong Cadre and Strong Leadership | Q9: Weak | R9: Weak Leadership & Weak Cadre | S9: Mixed | T9: Positive Image Welfare Schemes | U9: 1. Sarpanch is disgruntled with YSRCP government due to his pending bills issues of 12 lakhs (Works include - CC Roads, Drains, Silting works) | W9: Complete
A10: Jaggampeta | B10: Gokavaram | C10: =IFERROR(__xludf.DUMMYFUNCTION("filter('Back End'!C:C,'Back End'!A:A=A10,'Back End'!B:B=B10,'Back End'!D:D=D10)"),"#REF!") -> #REF! | D10: GADELAPALEM | E10: Difficult | G10: TDP Trailing | H10: 1. Agricultue | W10: Incomplete
A11: Pithapuram | B11: Pithapuram | C11: =IFERROR(__xludf.DUMMYFUNCTION("filter('Back End'!C:C,'Back End'!A:A=A11,'Back End'!B:B=B11,'Back End'!D:D=D11)"),"#REF!") -> #REF! | D11: Veldurthi | E11: Battleground | G11: Dead Heat | H11: 1. Paddy farmers | I11: JSP Split the Votes | J11: 1. This is Kapu OC's dominant village which is majorly split between TDP, YCP, and JSP. 2. JSP has a good commence in the Kapu community which was able to split the votes which dented the YCP party. | K11: TDP>JSP>YCP | L11: 1. TDP is banking on the OC Kapu community along with other minor BC communities (Settibalija, Padmashali, Yadavas). 2. YCP is banking on SC Communities Mala and Madiga | M11: Strong | N11: Strong Cadre and Strong Leadership | O11: Medium | P11: Strong Leadership but Weak Vote Bank | Q11: Weak | R11: Weak Leadership & Weak Cadre | S11: Mixed | T11: Positive Image Welfare Schemes | U11: 1. Pending bills on water motors, sanitization (5 lakhs) | W11: Complete
A12: Pithapuram | B12: Pithapuram | C12: =IFERROR(__xludf.DUMMYFUNCTION("filter('Back End'!C:C,'Back End'!A:A=A12,'Back End'!B:B=B12,'Back End'!D:D=D12)"),"#REF!") -> #REF! | D12: Jalluru | E12: Battleground | G12: Dead Heat | H12: 1. Farmers 2. Labour 3. Masons | I12: Caste Composition | J12: 1. This is the BC and OC (Kapu and Settibalija) dominant village. 2. The Kapu community was split between YSRCP, JSP, and TDP due to local leadership. 3. TDP is banking on the Settibalija community in this village 4. YCP is banking on traditional support of SC Communities (Mala and Madiga) | K12: YCP>TDP>JSP | L12: 1. YCP is basically banking on SC Communities (Mala, Madiga), OC Kapu vote bank, along with a slight edge of BC vote bank. 2.JSP +TDP alliance may help these parties secure Kapu vote bank . | M12: Strong | N12: Strong Cadre and Strong Leadership | O12: Strong | P12: Strong Cadre and Strong Leadership | Q12: Weak | R12: Weak Leadership & Weak Cadre | S12: Positive | T12: Positive Image Welfare Schemes | W12: Complete
A13: Prathipadu | B13: Rowthulapudi | C13: =IFERROR(__xludf.DUMMYFUNCTION("filter('Back End'!C:C,'Back End'!A:A=A13,'Back End'!B:B=B13,'Back End'!D:D=D13)"),"#REF!") -> #REF! | D13: Gummaregula | E13: Battleground | F13: TDP Ahead | G13: TDP Closely Ahead | H13: 1.farmers 2.labor | I13: Leader Dominance | J13: 1. This is BC Padmashali's dominant village which is majorly split between TDP and YCP. 2. This is the battleground village where the majority of the communities split between TDP and YCP. 3. OC and SC vote banks are majorly inclined towards the YCP Party while Madiga is inclined towards TDP. | K13: YCP>TDP>JSP | L13: 1. People are disgruntled with the government as there are no developments and leaders are not completely responsive towards the people. 2. People are highly satisfied with the TDP government due to the developments made during their time and this is the major X factor for the shift in the vote bank. 3.JSP has bare minimum presence in this village . | M13: Medium | N13: Strong Leadership but Weak Vote Bank | O13: Strong | P13: Strong Cadre and Strong Leadership | Q13: Weak | R13: Weak Leadership & Weak Cadre | S13: Negative | T13: Negative Image on Local Leadership | W13: Complete | Y13: Jayasri
A14: Pithapuram | B14: Pithapuram | C14: =IFERROR(__xludf.DUMMYFUNCTION("filter('Back End'!C:C,'Back End'!A:A=A14,'Back End'!B:B=B14,'Back End'!D:D=D14)"),"#REF!") -> #REF! | D14: Kumarapuram | E14: Battleground | G14: Dead Heat | H14: 1. Famers 2. Agriculture Labour | I14: Caste Composition | J14: 1.This is OC Community Kapu dominant village which is majorly split between YCP and JSP. 2. YCP is majorly banking on SC Communities (Mala and Madiga) with the slight edge of Kapu Vote Bank. 3. Kapu community is present in a decent number but JSP has minimal hold over the community in the village which split the vote bank of YCP. | K14: YCP>TDP>JSP | L14: 1.YCP is majorly banking on SC Communities (Mala and Madiga) with the slight edge of Kapu Vote Bank and the minimum vote of Settibalija is added beneficial. 2. If TDP and JSP are having an alliance then there is a great chance of an OC Kapu vote bank | M14: Strong | N14: Strong Cadre and Strong Leadership | O14: Strong | P14: Strong Cadre and Strong Leadership | Q14: Weak | R14: Weak Leadership & Weak Cadre | S14: Positive | T14: Positive Image Welfare Schemes | U14: Pending bills of amount 5 lakhs on Rudra Graveyard | W14: Complete
A15: Pithapuram | B15: Gollaprolu | C15: =IFERROR(__xludf.DUMMYFUNCTION("filter('Back End'!C:C,'Back End'!A:A=A15,'Back End'!B:B=B15,'Back End'!D:D=D15)"),"#REF!") -> #REF! | D15: CHEBROLU | E15: Battleground | G15: Dead Heat | H15: 1. Paddy farmers | I15: JSP Split the Votes | J15: 1. The Kapu community is split among all the major parties due to the local leadership and party's image, Minor BCs voted in favour of YSRCP which provided an edge to the party. Mala and Madiga communities consolidated in favour of YSRCP 2. TDP was able to secure majority of the Yadava community vote share due to the local leadership, 3. JSP split the maximum amount of Kapu vote bank which dented prospects of YSRCP in the village. | K15: TDP>JSP>YCP | L15: 1. TDP has stronghold in the Yadava community and JSP alliance will help to secure the majority of the Kapu vote bank 2. YSRCP is banking on section of the Kapu votes along with SC communities 3. Swing communities (Minor BCs) will play major role in deciding the outcome in the village | M15: Strong | N15: Strong Cadre and Strong Leadership | O15: Weak | P15: Weak Leadership & Weak Cadre | Q15: Strong | R15: Strong Cadre and Strong Leadership | S15: Negative | T15: No Development | U15: 1. Sarpanch has pending bills of 14 lakhs (CC Roads, Drains, gravel roads) | W15: Complete
A16: Pithapuram | B16: Gollaprolu | C16: =IFERROR(__xludf.DUMMYFUNCTION("filter('Back End'!C:C,'Back End'!A:A=A16,'Back End'!B:B=B16,'Back End'!D:D=D16)"),"#REF!") -> #REF! | D16: CHINA JAGGAMPETA | E16: Battleground | G16: TDP Closely Ahead | H16: 1. Migration Labour working in Cashew Farms | I16: Anti-Incumbency on TDP | J16: 1. The major BC communities (Uppara & Yadava) spliit between YSRCP and TDP due to the local leadership and previous election promises of YSRCP 2. JSP had minimal impact still holds vote bank in SC communities | K16: TDP>JSP>YCP | L16: 1. High Concentration of BC communities provides an edge to TDP 2. YSRCP still holds command in BC communities due to local leadership 3. JSP has minimal impact | M16: Strong | N16: Strong Cadre and Strong Leadership | O16: Medium | P16: Strong Cadre and Strong Leadership | Q16: Weak | R16: Strong Cadre Weak Leadership | S16: Negative | T16: No Development | U16: 1. Pending Bills for Sarpanch (6 Lakhs for Sachivalayam Construction) | W16: Complete
A17: Prathipadu | B17: Prathipadu | C17: =IFERROR(__xludf.DUMMYFUNCTION("filter('Back End'!C:C,'Back End'!A:A=A17,'Back End'!B:B=B17,'Back End'!D:D=D17)"),"#REF!") -> #REF! | D17: Sankarlapudi | E17: Safe | G17: TDP Ahead | H17: Famers | I17: welfare schemes | J17: Due to welfare schemes last time elections were won by YCP | K17: TDP>YCP>JSP | L17: majority votes towards tdp | M17: Strong | N17: Strong Cadre and Strong Leadership | O17: Medium | P17: Strong Cadre Weak Leadership | Q17: Weak | R17: Weak Leadership & Weak Cadre | S17: Negative | T17: No Development | W17: Incomplete
A18: Pithapuram | B18: Gollaprolu | C18: =IFERROR(__xludf.DUMMYFUNCTION("filter('Back End'!C:C,'Back End'!A:A=A18,'Back End'!B:B=B18,'Back End'!D:D=D18)"),"#REF!") -> #REF! | D18: Durgada | E18: Difficult | G18: TDP Trailing | H18: 1. Farmers (Paddy, Cotton,Mirchi) | I18: JSP Split the Votes | J18: 1. This is the OC and BC (Kapu, Padmashali, and Yadavs) dominant village. 2. The OC Community Kapu caste is basically split between YCP and JSP due to local leadership. | K18: YCP>TDP>JSP | L18: 1. YCP is banking on the majority of OC caste Kapu,SC caste Mala, and Madiga along with the slight edge of BC caste (Padmashali). 2. TDP is generally banking on BC community (Yadvas -1200) votes. | M18: Medium | N18: Strong Cadre Weak Leadership | O18: Strong | P18: Strong Cadre and Strong Leadership | Q18: Weak | R18: Weak Leadership & Weak Cadre | S18: Positive | T18: Positive Image Welfare Schemes | U18: 1. Pending bills on road nearly 35 lakhs. 2. Nearly 50 lakhs is pending on Sachyavalayam bills. 3.10 lakhs is pending on each Graveyard road and CC Road. | W18: Complete
A19: Pithapuram | B19: Pithapuram | C19: =IFERROR(__xludf.DUMMYFUNCTION("filter('Back End'!C:C,'Back End'!A:A=A19,'Back End'!B:B=B19,'Back End'!D:D=D19)"),"#REF!") -> #REF! | D19: P Rayavaram | E19: Battleground | F19: Dead Heat | G19: Dead Heat | H19: 1. Farmers 2. Agricultural Labourers | I19: Leader Dominance | J19: 1. SC vote bank was completely in favour of YCP 2. Kapu vote bank got split between YCP and DP, this dented the TDP polling 3. It was also a case of YS Rajasekhar Reddy sympathy and Jagan Wave | K19: JSP>TDP>YCP | L19: 1. This is a Kapu community-dominant village 2. JSP Incharge Pengala Uday Bhaskar Srinivas is a proactive leader who responds to healthcare and other needs of villagers 3. YCP MLA P Dora Babu has not been actively involved with people after the elections 4. TDP SVSN Varma is also not very active when it comes to public involvement | M19: Medium | N19: weak leadership and strong cadre | O19: Weak | P19: Weak Leadership & Weak Cadre | Q19: Strong | R19: Strong Cadre and Strong Leadership | S19: Negative | T19: No Development | W19: Review | Y19: Prashanth
A20: Prathipadu | B20: Prathipadu | C20: =IFERROR(__xludf.DUMMYFUNCTION("filter('Back End'!C:C,'Back End'!A:A=A20,'Back End'!B:B=B20,'Back End'!D:D=D20)"),"#REF!") -> #REF! | D20: CHINASANKARLAPUDI | E20: Battleground | G20: Dead Heat | H20: 1. Korralu Machine labour | I20: Caste Composition | J20: 1. This is the BC and OC dominant Village(Kapu and Uppara ). 2. BC community Uppara is split between YCP and TDP. 3.YSRCP has an edge over SC communities due to the Pro-SC image | K20: YCP>TDP>JSP | L20: 1. YCP is majorly banking on SC communities (Mala and Madiga ) and also with the majority of upper caste due to local leadership. 2. YCP also has an advantage of getting maximum votes from the Kapu community due to local leadership Epuri Ramarao maintaining good relations. | M20: Medium | N20: Strong Cadre Weak Leadership | O20: Strong | P20: Strong Cadre and Strong Leadership | Q20: Weak | R20: Weak Leadership & Weak Cadre | S20: Positive | T20: Positive Image Welfare Schemes | U20: 20 lakh bill is pending on construction on roads ,drainage system,and bathrooms | W20: Review
A21: Prathipadu | B21: Gokavaram | C21: =IFERROR(__xludf.DUMMYFUNCTION("filter('Back End'!C:C,'Back End'!A:A=A21,'Back End'!B:B=B21,'Back End'!D:D=D21)"),"#REF!") -> #REF! | D21: THANTIKONDA | E21: Favourable | G21: TDP Closely Ahead | W21: Incomplete
A22: Prathipadu | B22: Prathipadu | C22: =IFERROR(__xludf.DUMMYFUNCTION("filter('Back End'!C:C,'Back End'!A:A=A22,'Back End'!B:B=B22,'Back End'!D:D=D22)"),"#REF!") -> #REF! | D22: Yeluru | E22: Favourable | G22: TDP Closely Ahead | H22: 1. Paddy Farmers 2. Vegetable Cultivators | I22: Caste Composition | J22: 1. This is village witness fight between Koppula Velama (TDP) and Kapu (YSRCP) due to the local dynamics 2. YSRCP has edge over SC communities due to the Pro-SC image 3. JSP was not in a position dent the Kapu vote bank due to a lack of local leadership | K22: YCP>TDP>JSP | L22: 1. TDP has complete command over K Velama community and section of Kapu supports the party due to TDP-JSP alliance which provides an edge to the party 2. YSRCP is banking on Kapu + SC vote bank but there will be split in Kapu community which will impact YSRCP prospects | M22: Medium | N22: Strong Cadre Weak Leadership | O22: Strong | P22: Strong Cadre and Strong Leadership | Q22: Weak | R22: weak leadership and strong cadre | S22: Positive | T22: One More Chance to Jagan | U22: Sarpanch has pending bills of 3 lakhs for infra works and disgruntled with YSRCP government | W22: Complete
A23: Prathipadu | B23: Yeleswaram | C23: =IFERROR(__xludf.DUMMYFUNCTION("filter('Back End'!C:C,'Back End'!A:A=A23,'Back End'!B:B=B23,'Back End'!D:D=D23)"),"#REF!") -> #REF! | D23: Siripuram | E23: Battleground | G23: TDP Ahead | H23: 1. Paddy Farmers | I23: Caste Composition | J23: 1. Mala & Madiga community is inclined towards YSRCP, there is a split in Perika community due to local leadership 2. This is a battleground village as majority of the BC communities Rajaka, Setti Balija are split between YSRCP & TDP in the village | K23: YCP>TDP>JSP | L23: 1. YSRCP is sucessful in consolidating SC vote bank and splitting BC vote bank in the village 2. TDP lacks support in SC communities and highly banking on Koppula Velama & Setti Balija communities 3. JSP presence is very less in the village due to low concentration of Kapu community | M23: Strong | N23: Strong Cadre and Strong Leadership | O23: Strong | P23: Strong Cadre Weak Leadership | Q23: Weak | R23: Weak Leadership & Weak Cadre | S23: Mixed | T23: No Development | U23: 1. Pending Bills to Sarpanch of 8 lakhs - Gravel Roads 2. Culverts on Drianges - 30 lakhs | W23: Complete
A24: Pithapuram | B24: Gollaprolu | C24: =IFERROR(__xludf.DUMMYFUNCTION("filter('Back End'!C:C,'Back End'!A:A=A24,'Back End'!B:B=B24,'Back End'!D:D=D24)"),"#REF!") -> #REF! | D24: TATIPARTHI | E24: Battleground | G24: Dead Heat | H24: 1. Farmers 2. Weavers | I24: Anti-Incumbency on TDP | J24: 1. It's a battleground village and both YSRCP & TDP have equal amount of support in communities. 2. Kapu community was split between YSRCP and TDP in the previous election due to MLA's candidature. 3. TDP was banking on the Senapathulu vote bank along with some sections of minor BCs | K24: YCP>TDP>JSP | L24: 1. Its battleground village and JSP alliance will favour TDP in securing Kapu vote bank 2. YSRCP is trying to secure minor BC communities in the village throgh welfare schemes | M24: Strong | N24: Strong Cadre and Strong Leadership | O24: Strong | P24: Strong Cadre and Strong Leadership | Q24: Medium | R24: weak leadership and strong cadre | S24: Positive | T24: Positive Image Welfare Schemes | U24: 1. Sarpanch has pending bills of 30 lakhs ( Miniral Water Plant, Compound Wall of Burial Ground & CC Roads) | W24: Complete
A25: Kakinada Rural | B25: Kakinada (Rural) | C25: =IFERROR(__xludf.DUMMYFUNCTION("filter('Back End'!C:C,'Back End'!A:A=A25,'Back End'!B:B=B25,'Back End'!D:D=D25)"),"#REF!") -> #REF! | D25: KOVVADA | E25: Battleground | G25: Dead Heat | H25: 1. Finance Business 2. Kiran Shop Owners 3. Self Business | I25: Caste Composition | J25: 1. This is a Kapu-dominated village where 50% of the population (2500 votes) belong to the Kapu community. 2. The Kapu community was split between YSRCP and JSP, JSP was able to secure a majority of the vote bank due to the party's image and Pantham Nannaji Candidature. 3. TDP was focused on the BC vote bank majorly Setti Balija, Yadava, and Rajaka communities. 4. Madiga & Mala communities constitute around 1000 votes and are inclined towards YSRCP. | K25: TDP>JSP>YCP | L25: 1. JSP & TDP alliance will be the crucial factor in securing the Kapu vote bank along with BC communities. 2. YSRCP leaders (Kotiapally Uma- Kapu) are disgruntled with local MLA Kurasala Kanna Babu leadership. | M25: Medium | N25: Strong Cadre Weak Leadership | O25: Medium | P25: Strong Cadre Weak Leadership | Q25: Medium | R25: Strong Cadre Weak Leadership | S25: Negative | T25: No Development | U25: Sarpanch Kotipally Uma (Kapu) has issue of pending bills of 60 lakhs and disgruntled with MLA Kanna Babu | V25: కొవ్వాడ గ్రామం లో వైకాపా పార్టీ వల్లే మూడు వర్గాలుగా విడిపోయారు. రెండు రోజులు క్రితం ఇరు వర్గాలు MLA కార్యాలయం వద్ద గోడవకి దిగారు. ఈ విషయం కురాశాల కన్నబాబు కు చేరింది.ఏంపిపి,ఆమె భర్త ,ఉప సర్పంచ్ ఒక వర్గం,సర్పంచ్,మండల రేషన్ డీలర్ మాజీ అద్యక్షుడు ఒక వర్గం,మాజీ ఉప సర్పంచ్ మూడో వర్గం గా వున్నారు. తన వర్గానికి చెందిన కొందరికి పట్టాలు మంజూరు కాలేదు అని ప్రజలతో కలసి మాజీ ఉప సర్పంచ్ MLA దగ్గరికి చేరుకున్నారు. | W25: Complete | Y25: .
A26: Kakinada Rural | B26: Kakinada (Rural) | C26: =IFERROR(__xludf.DUMMYFUNCTION("filter('Back End'!C:C,'Back End'!A:A=A26,'Back End'!B:B=B26,'Back End'!D:D=D26)"),"#REF!") -> #REF! | D26: NEMAM | E26: Battleground | G26: Dead Heat | H26: 1. Fisherman 2. Toddy Tappers 3. Farmers | I26: Caste Composition | J26: 1. The majority of the Setti Balija and Fisherman communities supported TDP which helped to secure the majority in the village. 2. Kapu and Mala communities inclined towards YSRCP along with some sections of Rajaka & Vishwa Brahmin. 3. JSP Impact was minimal and able to split the Kapu votes which dented the YSRCP vote bank. | K26: TDP>YCP>JSP | L26: 1. The Major Caste split between three parties is key reason for party positining 2. JSP and TDP alliance will play a bigger role in the coming elections | M26: Strong | N26: Strong Cadre and Strong Leadership | O26: Strong | P26: Strong Cadre and Strong Leadership | Q26: Medium | R26: weak leadership and strong cadre | S26: Mixed | T26: Positive Image Welfare Schemes | U26: 1. Lack of Basic facilities in Jagan Anna colonies (480 beneficiaries) | W26: Complete
A27: Jaggampeta | B27: Gandepalle | C27: =IFERROR(__xludf.DUMMYFUNCTION("filter('Back End'!C:C,'Back End'!A:A=A27,'Back End'!B:B=B27,'Back End'!D:D=D27)"),"#REF!") -> #REF! | D27: Ramayyapalem | E27: Difficult | G27: TDP Trailing | H27: farmers | I27: Caste Composition | J27: 1. Turupu kapu (1050 votes) constitute the majority of the votes. 2. Because YCP promised to implement all well-intentioned initiatives and all the welfare schemes to the public. 3. The majority of the Turpu kapu vote bank went to the YCP due to Jyothula Chanti Babu's domination as leader. He is from the caste of the tirpu kapu. | K27: YCP>TDP>JSP | L27: 1)Due to more caste composition from turpu kapu . 2)Sucessfull schemes like Amma Vodi, Cheyutha and Rythu Barosa | M27: Weak | N27: Weak Leadership & Weak Cadre | O27: Strong | P27: Strong Cadre and Strong Leadership | Q27: Weak | R27: Weak Leadership & Weak Cadre | S27: Positive | T27: One More Chance to Jagan | W27: Incomplete
A28: Kakinada Rural | B28: Kakinada (Rural) | C28: =IFERROR(__xludf.DUMMYFUNCTION("filter('Back End'!C:C,'Back End'!A:A=A28,'Back End'!B:B=B28,'Back End'!D:D=D28)"),"#REF!") -> #REF! | D28: P.VENKATAPURAM | E28: Difficult | G28: TDP Trailing | H28: Farmers,auto drivers | I28: welfare schemes | J28: 1.This is completely a settibalija-dominant village. 2. Because TDP leader Pilli Ananth Lakshmi belongs to the same settibalija caste as them, TDP received the most votes. | K28: YCP>TDP>JSP | L28: 1)YSRCP has a good image due to good schemes like Ammavodi,vidyadeevan, Asara Pathakam so BC vote bank has a slight shift towards YSRCP. 2)Numerous developments are done during the YSRCP's governance. | M28: Medium | N28: Strong Cadre Weak Leadership | O28: Strong | P28: Strong Cadre and Strong Leadership | Q28: Weak | R28: weak leadership and strong cadre | S28: Positive | T28: Positive Image Welfare Schemes | W28: Review
A29: Jaggampeta | B29: Gandepalle | C29: =IFERROR(__xludf.DUMMYFUNCTION("filter('Back End'!C:C,'Back End'!A:A=A29,'Back End'!B:B=B29,'Back End'!D:D=D29)"),"#REF!") -> #REF! | D29: Subbayamma Peta | E29: Difficult | G29: TDP Trailing | H29: farmers | I29: Caste Composition | J29: majority votes based on turupu kapu | K29: YCP>TDP>JSP | L29: all votes from kapu members for ycp again | M29: Weak | N29: Weak Leadership & Weak Cadre | O29: Strong | P29: Strong Cadre and Strong Leadership | Q29: Weak | R29: Weak Leadership & Weak Cadre | S29: Positive | T29: One More Chance to Jagan | W29: Incomplete
A30: Kakinada Rural | B30: Kakinada (Rural) | C30: =IFERROR(__xludf.DUMMYFUNCTION("filter('Back End'!C:C,'Back End'!A:A=A30,'Back End'!B:B=B30,'Back End'!D:D=D30)"),"#REF!") -> #REF! | D30: GANGANAPALLI | E30: Difficult | G30: TDP Trailing | H30: Job Holders,Farmers | I30: Leader Dominance | J30: 1. In order to help the YCP win prior elections, Geesala Sreenivas Rao nearly spent one crore swaying the votes of Kapu and Settibalija, which represent roughly 2000 and 1000 vote banks, respectively. | K30: YCP>TDP>JSP | L30: There is a positive image on YSRCP. 2) Ycp is supported by the 2000 Kapu vote bank. 3)If the government fails to give the populace house pattas, then YCP risks losing nearly 1000 votes of settibalija. | M30: Medium | N30: Strong Cadre Weak Leadership | O30: Strong | P30: Strong Cadre and Strong Leadership | Q30: Weak | R30: weak leadership and strong cadre | S30: Positive | T30: Positive Image Welfare Schemes | U30: pending bills on Jagan Pala Kendra of 8 lakhs panchayath's bill of 16 lakhs is pending. 2. Constructed SC Community hall ,will have good impact on Community. | W30: Review
A31: Jaggampeta | B31: Gandepalle | C31: =IFERROR(__xludf.DUMMYFUNCTION("filter('Back End'!C:C,'Back End'!A:A=A31,'Back End'!B:B=B31,'Back End'!D:D=D31)"),"#REF!") -> #REF! | D31: P.Surampalem | E31: Difficult | F31: Dead Heat | G31: Dead Heat | H31: 1.Daily Labours | I31: Leader Dominance | J31: 1. YCP has a stronghold and majority vote bank from kapu community which is split between YCP and TDP but majorly inclined to YCP. 2. Due to sympathy towards YCP MLA Jyothula Chantibabu as he lost two times being in TDP people gave one chance to him. 3. It was a case of voting out of respect for YS Rajasekhar Reddy and villagers also wanted to give a chance to the new rule of YS Jagan | K31: YCP>TDP>JSP | L31: 1. People are highly dissatisfied with YCP Party as YCP MLA Jyothula Chanti Babu is not at all responsive towards people but some of them are satisfied with the welfare schemes they are getting. 2. Compared to YCP MLA, TDP MLA Jyothula Nehru is far better and is very responsive towards people and he nearly has a 30% vote bank in the village. 3. JSP has local leaders who are active in this village which may consolidate some of the vote bank. | M31: Medium | N31: Medium leadership medium vote bank | O31: Strong | P31: Strong Cadre and Strong Leadership | Q31: Weak | R31: Weak Leadership & Weak Cadre | S31: Positive | T31: Positive Image Welfare Schemes | W31: Complete | Y31: Jayasri
A32: Jaggampeta | B32: Gandepalle | C32: =IFERROR(__xludf.DUMMYFUNCTION("filter('Back End'!C:C,'Back End'!A:A=A32,'Back End'!B:B=B32,'Back End'!D:D=D32)"),"#REF!") -> #REF! | D32: P. Nayakampalle | E32: Battleground | G32: Dead Heat | H32: 1. Paddy Farmers 2.Private Employees | I32: Caste Composition | J32: 1. This village is dominated by the Kamma community and inclined towards TDP. Settibalija community along with other SC communities Mala & Madiga shifted towards YSRCP in the previous elections. 2. JSP secured around 250 votes due to the shift of the Kapu community in the village. | K32: TDP>YCP>JSP | L32: 1. There will be complete shift of Kamma and Kapu communities in the next elections due to the allaince of TDP-JSP 2. YSRCP has good presence in village due high concentration of Mala and Erukala (50 votes), along with government schemes beneficiaries like Ammavodi, Cheyutha and Asara | M32: Medium | N32: Strong Cadre Weak Leadership | O32: Medium | P32: Strong Cadre Weak Leadership | Q32: Medium | R32: Strong Cadre Weak Leadership | S32: Positive | T32: One More Chance to Jagan | W32: Complete
A33: Pithapuram | B33: Pithapuram | C33: =IFERROR(__xludf.DUMMYFUNCTION("filter('Back End'!C:C,'Back End'!A:A=A33,'Back End'!B:B=B33,'Back End'!D:D=D33)"),"#REF!") -> #REF! | D33: Mangiturthi | E33: Battleground | G33: Dead Heat | H33: Farmers(paddy,Vegetables), | I33: Caste Composition | J33: 1. This OC (Kapu)dominant village followed by BC(Settibalija and Velamas). 2. JSP was able to split a decent amount of votes which is a vote bank of the YSRCP Party. 3. YCP strength is majorly based on the SC community (Mala and Madiga ) along with the section of the Kapu vote bank. | K33: YCP>TDP>JSP | L33: 1. Kapu vote bank is split between all three parties due to local leadership(Kommireddy baburao-TDP, Kasthireddy Akkaya -YCP, Purapa Rajesh -JSP). 2. JSP has a strong presence in the Kapu community due to local leadership (Purapa Rajesh- OC Kapu) and the TDP+JSP alliance will help to consolidate the majority of the vote bank from Kapu as well as the Settibalija ,Velama of BC community. | M33: Strong | N33: Strong Cadre and Strong Leadership | O33: Strong | P33: Strong Cadre and Strong Leadership | Q33: Weak | R33: Weak Leadership & Weak Cadre | S33: Positive | T33: Positive Image Welfare Schemes | U33: 1.pending bills on Gadpa Gadpa Programme | W33: Complete
A34: Kakinada Rural | B34: Karapa | C34: =IFERROR(__xludf.DUMMYFUNCTION("filter('Back End'!C:C,'Back End'!A:A=A34,'Back End'!B:B=B34,'Back End'!D:D=D34)"),"#REF!") -> #REF! | D34: ARATLAKATTA | E34: Battleground | G34: Dead Heat | H34: Famers | I34: Caste Composition | J34: 1. This village is dominated Kapu and Setti Balija communities. In the previous elections Kapu votes were split between YSRCP and JSP due to MLA candidates. 2. TDP was able to secure the majority of the BC vote bank along with Kamma community due to its MLA candidature of Pilli Anantha Laxmi (Setti Balija). | K34: YCP>TDP>JSP | L34: 1. Both YSRCP and TDP are equally strong due to Kapu vs BC equation 2. TDP & JSP alliance will play crucilal role in coming election | M34: Strong | N34: Strong Cadre and Strong Leadership | O34: Strong | P34: Strong Cadre and Strong Leadership | Q34: Medium | R34: weak leadership and strong cadre | S34: Positive | T34: Positive Image Welfare Schemes | W34: Review
A35: Kakinada Rural | B35: Karapa | C35: =IFERROR(__xludf.DUMMYFUNCTION("filter('Back End'!C:C,'Back End'!A:A=A35,'Back End'!B:B=B35,'Back End'!D:D=D35)"),"#REF!") -> #REF! | D35: Uppalanka | E35: Battleground | G35: Dead Heat | H35: 1.Fisherman | I35: Caste Composition | J35: 1. This is fisherman dominant village (Agnikula Kshatriya.) which is split between YCP and TDP due to local leadership( Bommadi Satish, Sangadi Srinu). 2. JSP was able to gain a slight vote share from the BC Vote bank which dented the TDP prospectus. | K35: YCP>TDP>JSP | L35: 1. Despite TDP having good alliance with JSP , YCP has more chance due to the subsidies provided by the local leadership (Bommadi Satish)which is nearly 10,000/- directly into their bank accounts. | M35: Strong | N35: Strong Cadre and Strong Leadership | O35: Strong | P35: Strong Cadre and Strong Leadership | Q35: Weak | R35: Weak Leadership & Weak Cadre | S35: Positive | T35: Positive Image Welfare Schemes | W35: Review
A36: Jaggampeta | B36: Gandepalle | C36: =IFERROR(__xludf.DUMMYFUNCTION("filter('Back End'!C:C,'Back End'!A:A=A36,'Back End'!B:B=B36,'Back End'!D:D=D36)"),"#REF!") -> #REF! | D36: Z.Ragampeta | E36: Battleground | G36: Dead Heat | H36: 1. Toddy Tappers 2. Paddy Farmers | I36: Anti-Incumbency on TDP | J36: 1. TDP was able to consolidate Kamma, Setti Balija vote bank in the previous elections 2. YSRCP was able to secure the majority of the SC vote bank (Mala, Madiga) along with the Erukala community. 3. Kapu vote bank was split between TDP and YSRCP. | K36: YCP>TDP>JSP | L36: 1. This is Kamma dominated village and TDP has stronghold in Kamma & Setti Balija communities 2. YSRCP has strong vote bank in SC communities along with section of OC Kapu community support 3. Kapu community is present in the decent number but JSP has minimal hold over the community in the village | M36: Strong | N36: Strong Cadre and Strong Leadership | O36: Strong | P36: Strong Cadre and Strong Leadership | Q36: Weak | R36: Weak Leadership & Weak Cadre | S36: Mixed | T36: Positive Image Welfare Schemes | U36: 1. There are pending bills of street lights, drainages, Roads and Sachivalayam construction 2. Sarpanch opined that volunteers are taking away the power from elected members | W36: Complete
A37: Peddapuram | B37: Samalkota | C37: =IFERROR(__xludf.DUMMYFUNCTION("filter('Back End'!C:C,'Back End'!A:A=A37,'Back End'!B:B=B37,'Back End'!D:D=D37)"),"#REF!") -> #REF! | D37: Atcham Peta | E37: Battleground | G37: Dead Heat | H37: Farmers(Paddy), Mestri | I37: JSP Split the Votes | J37: 1. This is Kapu's dominant village OC community which is split equally between all three parties TDP, YCP, and JSP due to local leadership. 2. YCP is completely banking on SC communities (Mala and Madiga )along with minimum votes from the Kapu vote bank. 3. TDP is completely banking on BC communities (Settibalija )along with the split votes from the kapu vote bank. | K37: YCP>JSP>TDP | L37: 1. YCP is completely banking on SC communities (Mala and Madiga )along with minimum votes from the kapu vote bank. 2. JSP has a strong presence in the Kapu community due to local leadership (Pabbineni Eswarao - OC Kapu) and also the TDP+JSP alliance will help to consolidate the majority of the vote bank from Kapu as well as Settibalija BC community. | M37: Medium | N37: Strong Cadre Weak Leadership | O37: Strong | P37: Strong Cadre and Strong Leadership | Q37: Strong | R37: Strong Cadre and Strong Leadership | S37: Mixed | T37: Positive Image Welfare Schemes | U37: 1.pending bills on sweaper | W37: Complete
A38: Tuni | B38: Tuni | C38: =IFERROR(__xludf.DUMMYFUNCTION("filter('Back End'!C:C,'Back End'!A:A=A38,'Back End'!B:B=B38,'Back End'!D:D=D38)"),"#REF!") -> #REF! | D38: Rapaka | E38: Battleground | G38: Dead Heat | H38: 1.Farmers(Agricultural) | I38: Caste Composition | J38: 1.This is Kapu's dominant village and this community is split between TDP and YSRCP. 2. YCP is totally banking on SC communities (Mala) and also has the vote bank of Kapu. 3. TDP is totally banking on BC communities (Velma, Yadavas) | K38: YCP>TDP>JSP | L38: 1. YCP is totally banking on SC communities (Mala) and also has the vote bank of Kapu. 2. JSP had minimal impact and still holds the vote bank in kapu communities. 3. The JSP and TDP alliance will play a bigger role in the coming elections | M38: Strong | N38: Strong Cadre and Strong Leadership | O38: Strong | P38: Strong Cadre and Strong Leadership | Q38: Weak | R38: Weak Leadership & Weak Cadre | S38: Positive | T38: Positive Image Welfare Schemes | W38: Complete
A39: Tuni | B39: Tuni | C39: =IFERROR(__xludf.DUMMYFUNCTION("filter('Back End'!C:C,'Back End'!A:A=A39,'Back End'!B:B=B39,'Back End'!D:D=D39)"),"#REF!") -> #REF! | D39: Atikivanipalem | E39: Battleground | G39: TDP Closely Trailing | H39: 1. Paddy Farmers 2. Horticulture | I39: Anti-Incumbency on TDP | J39: 1. The majority of the BC communities Perika & Setti Balija communities voted in favour of YSRCP due to anti-incumbency on the TDP government. 2. TDP was able to secure the Perika vote bank due to the local leadership in the village. | K39: YCP>TDP>JSP | L39: 1. This is battleground village and leadership hails from Setti Balija & Perika communities in both parties 2. JSP-TDP alliance will have very less impact in the village | M39: Medium | N39: Strong Cadre Weak Leadership | O39: Strong | P39: Strong Cadre and Strong Leadership | Q39: Weak | R39: Weak Leadership & Weak Cadre | S39: Mixed | T39: Positive Image Welfare Schemes | U39: 1. Positive Image among the beneficiaries but developmental works are pending in the village 2. Pending bills of 2 lakhs to Sarpanch | W39: Complete
A40: Tuni | B40: Thondangi | C40: =IFERROR(__xludf.DUMMYFUNCTION("filter('Back End'!C:C,'Back End'!A:A=A40,'Back End'!B:B=B40,'Back End'!D:D=D40)"),"#REF!") -> #REF! | D40: A.Kothapalle | E40: Difficult | G40: TDP Trailing | H40: 1. Paddy Farmers 2.Cotton Farmers | I40: Caste Composition | J40: 1. These BC (Perika )and OC (Kapu ) are dominant villages. 2. YSRCP is banking on the dominant caste Perika with a huge majority along with the swing of the kapu vote bank and majorly inclined votes of SC (Mala) vote. 3. TDP is banking on the split share of kapu, and yadava along with the support of other BC minorities. | K40: YCP>TDP>JSP | L40: 1. YSRCP strong presence in Perika (BC) and SC Mala communities. 2. TDP failed to gather votes of the Perika community as well as other minor BC communities' vote bank. | M40: Medium | N40: Strong Cadre Weak Leadership | O40: Strong | P40: Strong Cadre and Strong Leadership | Q40: Weak | R40: Weak Leadership & Weak Cadre | S40: Positive | T40: Positive Image Welfare Schemes | U40: 1. Pending bills on sanitation,light, and bleaching powder which is of 18 lakhs | W40: Complete
A41: Tuni | B41: Kotananduru | C41: =IFERROR(__xludf.DUMMYFUNCTION("filter('Back End'!C:C,'Back End'!A:A=A41,'Back End'!B:B=B41,'Back End'!D:D=D41)"),"#REF!") -> #REF! | D41: B.H.Kota | E41: Battleground | G41: Dead Heat | H41: 1. Paddy farmers 2.Daily labours | I41: Caste Composition | J41: 1. This is completely SC (Mala and Madiga Dominant village) which is mostly inclined towards the YSRCP Party. 2.YCP is banking on Mala and Kapu vote bank due to leaders candidature. | K41: YCP>TDP>JSP | L41: 1. TDP is banking on BC communities Settibalija, Gavara and other minor communities with very less vote bank . 2. YSRCP's strong presence in Mala , Madiga,and kapu communities | M41: Medium | N41: Strong Cadre Weak Leadership | O41: Strong | P41: Strong Cadre and Strong Leadership | Q41: Weak | R41: Weak Leadership & Weak Cadre | S41: Positive | T41: Positive Image Welfare Schemes | W41: Complete
A42: Tuni | B42: Kotananduru | C42: =IFERROR(__xludf.DUMMYFUNCTION("filter('Back End'!C:C,'Back End'!A:A=A42,'Back End'!B:B=B42,'Back End'!D:D=D42)"),"#REF!") -> #REF! | D42: Appalarajupeta | E42: Battleground | G42: Dead Heat | H42: 1. Agriculture labour 2.masons | I42: Caste Composition | J42: 1. This is BC (Koppula Velma) dominant village,the community is split between TDP and YSRCP. 2.. Other SC and BC communities (Rajaka& Nayi Brahmin) voted in favor of YSRCP due to the wave in the previous elections. | K42: YCP>TDP>JSP | L42: 1. Due to the high concentration of the Koppula Velma community YSRCP has a slight edge over the Kapu community due to the local leader's (Nallamali Govindu )candidature. 2.This is a battleground village and leadership hails from Koppula Velma communities in both parties | M42: Medium | N42: Strong Cadre Weak Leadership | O42: Strong | P42: Strong Cadre and Strong Leadership | Q42: Weak | R42: Weak Leadership & Weak Cadre | S42: Positive | T42: Positive Image Welfare Schemes | U42: 1. Pending bills on gravel filling for house site | W42: Complete
A43: Tuni | B43: Kotananduru | C43: =IFERROR(__xludf.DUMMYFUNCTION("filter('Back End'!C:C,'Back End'!A:A=A43,'Back End'!B:B=B43,'Back End'!D:D=D43)"),"#REF!") -> #REF! | D43: Billananduru | E43: Difficult | G43: TDP Trailing | H43: 1.Agriculture labourers 2. Paddy and Cashew nut Farmers | I43: Caste Composition | J43: 1. This is BC (Koppula Velma dominant) village which is completely inclined towards YSRCP. 2. Other SC and BC communities (Rajaka& Nayi Brahmin) voted in favour of YSRCP due to the wave in the previous elections. 3. People were dissatisfied with the TDP Govt so they wanted to experience governance under new govt | K43: YCP>TDP>JSP | L43: 1. Due to the high concentration of the Koppula Velma community, YSRCP has a maximum hand over the Koppula Velma community due to the local leader's (Bostha Sthibabu)candidature. 2.TDP is totally banking on BC community (Yadavas) and other minor communities of BC. 3. Villagers are happy with the schemes of YCP Govt as they are getting money directly to their accounts | M43: Medium | N43: Strong Cadre Weak Leadership | O43: Strong | P43: Strong Cadre and Strong Leadership | Q43: Weak | R43: Weak Leadership & Weak Cadre | S43: Positive | T43: Positive Image Welfare Schemes | U43: 1.pending bills on sweeper salaries and sarpanch salary(30 lakhs) | W43: Complete
A44: Tuni | B44: Thondangi | C44: =IFERROR(__xludf.DUMMYFUNCTION("filter('Back End'!C:C,'Back End'!A:A=A44,'Back End'!B:B=B44,'Back End'!D:D=D44)"),"#REF!") -> #REF! | D44: Gollamusalayyapeta | E44: Battleground | G44: Dead Heat | H44: 1. Fisherman 2.Paddy Farmers 3.Mirchi farmers 4.Cashew Farmers | I44: Caste Composition | J44: 1. This is the BC (Yadava)dominant village, the community is split between majority to TDP and with a minor vote bank towards YCP. 2. YCP is banking on BC (Vadabalija) community along with the slight Swing of other BC and OC Communities (Padmashali and kapu). | K44: TDP>YCP>JSP | L44: 1. TDP is banking on the majority of BC Yadav community along with other minor communities of BC and also due to local leadership(Talapathi Srinivas )candidature. 2. The JSP+TDP alliance may bring a slight edge for TDP to secure a slight margin of higher votes compared to other parties. | M44: Strong | N44: Strong Cadre and Strong Leadership | O44: Medium | P44: Strong Cadre Weak Leadership | Q44: Weak | R44: Weak Leadership & Weak Cadre | S44: Mixed | T44: Positive Image Welfare Schemes | W44: Complete
A45: Tuni | B45: Kotananduru | C45: =IFERROR(__xludf.DUMMYFUNCTION("filter('Back End'!C:C,'Back End'!A:A=A45,'Back End'!B:B=B45,'Back End'!D:D=D45)"),"#REF!") -> #REF! | D45: Indugapalle | E45: Battleground | G45: Dead Heat | H45: 1. Paddy Farmers 2. Cotton Farmers 3.Cashew Farming | I45: Caste Composition | J45: 1. This is the OC (Kapu)dominant village, the community split between all three parties TDP, YCP,JSP. 2 SC communities Mala and Madiga are completely inclined towards YCP. | K45: YCP>TDP>JSP | L45: 1.YCP is banking on Mala ,Madiaga and swing of kapu community with the majority of vote bank. 2.TDP is banking on BC communities Yadavas,Padmashali and minor communities of BC. | M45: Medium | N45: Strong Cadre Weak Leadership | O45: Strong | P45: Strong Cadre and Strong Leadership | Q45: Weak | R45: Weak Leadership & Weak Cadre | S45: Positive | T45: Positive Image Welfare Schemes | U45: 1.Pending bills on Ramraju kattu (1 crore) | W45: Complete
A46: Tuni | B46: Kotananduru | C46: =IFERROR(__xludf.DUMMYFUNCTION("filter('Back End'!C:C,'Back End'!A:A=A46,'Back End'!B:B=B46,'Back End'!D:D=D46)"),"#REF!") -> #REF! | D46: Jagannadhapuram | E46: Difficult | G46: TDP Trailing | H46: 1. Paddy Farmers | I46: Caste Composition | J46: 1. This is BC (Koppula Velma ) and SC (madiga dominant village. 2. Koppula velma BC and SC (Madiga) Communities are majorly split between TDP and YCP. | K46: YCP>TDP>JSP | L46: 1.YCP is completely banking on BC Koppula Velma community along with SC Communities Mala and Madiga. 2.TDP is banking minor vote bank from BC communities (Rajaka and Nayi Brahmin) | M46: Medium | N46: Strong Cadre Weak Leadership | O46: Strong | P46: Strong Cadre and Strong Leadership | Q46: Weak | R46: Weak Leadership & Weak Cadre | S46: Positive | T46: Positive Image Welfare Schemes | W46: Review
A47: Tuni | B47: Tuni | C47: =IFERROR(__xludf.DUMMYFUNCTION("filter('Back End'!C:C,'Back End'!A:A=A47,'Back End'!B:B=B47,'Back End'!D:D=D47)"),"#REF!") -> #REF! | D47: Hamsavaram | E47: Difficult | G47: TDP Trailing | H47: 1. Farmers 2. Labours 3. Masons | I47: Caste Composition | J47: 1.High concentration of Mala & Madiga communities provided an edge to YSRCP. 2. YSRCP was able to split the minor BC communities through manifesto promises 3. TDP was able to secure majority of the Yadava vote bank in the village but minimal support in other communities 3. JSP had minimal presence due to the low Kapu vote bank. 4. Reddy community has decent present in the village and inclined towards YSRCP | K47: YCP>TDP>JSP | L47: 1. High Concentration of SC Vote Bank favours YSRCP 2. Split in BC community hampers TDP Chances 3. Minimal Impact of JSP | M47: Medium | N47: Strong Leadership but Weak Vote Bank | O47: Strong | P47: Strong Cadre and Strong Leadership | Q47: Weak | R47: Weak Leadership & Weak Cadre | S47: Mixed | T47: Positive Image Welfare Schemes | U47: 1. General Public opined that there is no development 2. Harassment by YSRCP leadership if someone questions on development 3. Sarpanch is financially strong and spent a lot of money on his elections | W47: Complete
A48: Tuni | B48: Tuni | C48: =IFERROR(__xludf.DUMMYFUNCTION("filter('Back End'!C:C,'Back End'!A:A=A48,'Back End'!B:B=B48,'Back End'!D:D=D48)"),"#REF!") -> #REF! | D48: H Kothuru | E48: Battleground | G48: Dead Heat | H48: 1)Farmers (Paddy) 2) Labours | I48: Leader Dominance | J48: 1. This is BC's dominant village (Uppara) followed by settibalija and Perika. 2. The Uppara vote bank is split between YCP and TDP. | K48: TDP>YCP>JSP | L48: 1. TDP is banking completely on BC communities ( Uppara , Perika and Settibalija)due to local leadership Kartari Annavaram. 2. YCP is completely banking on SC community Mala and some votes from BC community. 3.JSP has minimal impact in the village | M48: Strong | N48: Strong Cadre and Strong Leadership | O48: Medium | P48: Strong Cadre Weak Leadership | Q48: Weak | R48: Weak Leadership & Weak Cadre | S48: Positive | T48: Positive Image Welfare Schemes | W48: Complete
A49: Tuni | B49: Tuni | C49: =IFERROR(__xludf.DUMMYFUNCTION("filter('Back End'!C:C,'Back End'!A:A=A49,'Back End'!B:B=B49,'Back End'!D:D=D49)"),"#REF!") -> #REF! | D49: Rajupeta | E49: Favourable | G49: TDP Ahead | H49: 1. Cashew Farmers 2. Agriculture Labour 3. Masons | I49: Party Leaders Tacit Understanding with Opposition Leaders | J49: 1. Killada Satya Narayana (Yadava- Ex-Vice Sarpanch) is very influential in TDP and commands a good hold over the community supported YSRCP in the previous elections 2. Kapu community voted in favour of YSRCP due to Dadisetti Raja's MLA candidature. 3. Minor BC communities Nayi Brahmin inclined towards YSRCP and Padmashali inclined towards TDP. | K49: TDP>YCP>JSP | L49: 1. There is split in Yadava vote bank due to local dynamics between YSRCP & TDP. TDP is banking on Yadava committee 2. JSP alliance will play very minor role due to lack of local leadership in the village | M49: Strong | N49: Strong Cadre and Strong Leadership | O49: Medium | P49: Strong Cadre Weak Leadership | Q49: Weak | R49: weak leadership and strong cadre | S49: Mixed | T49: Positive Image Welfare Schemes | U49: 1. Sarpanch has pending bills of 4 lakhs and disappointed with the government 2.YSRCP Sarpanch maintain good relationship with TDP leader Killadi Satya Narayana | W49: Complete
A50: Tuni | B50: Tuni | C50: =IFERROR(__xludf.DUMMYFUNCTION("filter('Back End'!C:C,'Back End'!A:A=A50,'Back End'!B:B=B50,'Back End'!D:D=D50)"),"#REF!") -> #REF! | D50: Chamavaram | E50: Difficult | G50: TDP Trailing | H50: 1. Farmers 2. Government Employees 3. Auto Drivers | I50: Caste Composition | J50: 1. The majority of the Kapu vote bank inclined towards YSRCP due to the MLA's candidature of Dadsisetty Raja but some sections of Kapu supported TDP due to the local leadership of Nagam Lova Dora (MPTC Contestant). 2. YSRCP has solid support from in Mala and Madiga communities. | K50: YCP>TDP>JSP | L50: 1. Due to the high concentration of Kapu community along with SC communities (YSRCP built the graveyard for SC communities) 2. JSP has minimal impact on Kapu community 3. TDP is successful in spliting the Kapu vote bank along with BC consolidation. | M50: Medium | N50: Strong Leadership but Weak Vote Bank | O50: Strong | P50: Strong Cadre and Strong Leadership | Q50: Weak | R50: Weak Leadership & Weak Cadre | S50: Positive | T50: Positive Image Welfare Schemes | U50: 1. Auto Drivers in SC support YCP due to 10,000 rupees 2. Dwacra and Asha workers in favour YSRCP as they secured jobs under this government | W50: Complete
A51: Tuni | B51: Tuni | C51: =IFERROR(__xludf.DUMMYFUNCTION("filter('Back End'!C:C,'Back End'!A:A=A51,'Back End'!B:B=B51,'Back End'!D:D=D51)"),"#REF!") -> #REF! | D51: Agraharam | E51: Battleground | G51: Dead Heat | H51: 1. Agriclture Labour 2. Farmers 3. Fisherman | I51: Caste Composition | J51: 1.This is BC dominant village( Vadabalija) followed by Kapu community and voted in favour of YSRCP in the last elections 2. TDP was able to split the Kapu community due to the local leadership 3.JSP had minimal impact on Kapu vote bank due to lack of local leadership | K51: YCP>TDP>JSP | L51: 1. YSRCP holds strong support from Vada Balija communities and section of Kapu community due to MLA's candidature 2. TDP's local leadership in Kapu community and JSP-TDP alliance will help to secure Kapu vote bank in the next elections | M51: Medium | N51: Strong Leadership but Weak Vote Bank | O51: Strong | P51: Strong Cadre and Strong Leadership | Q51: Weak | R51: Weak Leadership & Weak Cadre | S51: Mixed | T51: No Development | U51: 1.There is no Panchyath building(New Gram Panchyath). 2.YSRCP rebel Sarpanch candidate won with support of TDP leaders with 150 majority of votes. | W51: Complete
A52: Tuni | B52: Tuni | C52: =IFERROR(__xludf.DUMMYFUNCTION("filter('Back End'!C:C,'Back End'!A:A=A52,'Back End'!B:B=B52,'Back End'!D:D=D52)"),"#REF!") -> #REF! | D52: K.O.Mallavaram | E52: Battleground | G52: Dead Heat | H52: 1. Farmers 2. Govt employees 3. Private employees | I52: Issue Based Voting | J52: 1.This is Velama dominated village and this community is split between both YSRCP and TDP due to the local leadership. 2. YCP is leading in Mala and Kapu communities, TDP has strong support in Yadava and Settli Balija communities. | K52: YCP>TDP>JSP | L52: 1. YSRCP has a strong hold on communities like SC (Mala) and Velma Community | M52: Medium | N52: Strong Cadre Weak Leadership | O52: Strong | P52: Strong Cadre and Strong Leadership | Q52: Weak | R52: Weak Leadership & Weak Cadre | S52: Positive | T52: Positive Image Welfare Schemes | W52: Complete
A53: Tuni | B53: Tuni | C53: =IFERROR(__xludf.DUMMYFUNCTION("filter('Back End'!C:C,'Back End'!A:A=A53,'Back End'!B:B=B53,'Back End'!D:D=D53)"),"#REF!") -> #REF! | D53: D.Polavaram | E53: Battleground | G53: Dead Heat | H53: 1. Farmers 2. Labour 3. Masons | I53: Caste Composition | J53: 1.This is Koppula Velma and Padmashali's dominant village and these communities were split between both YSRCP and TDP. 2. TDP is banking on the BC Community (Yadava) and Padamashali communities 3. YCP is banking on communities Gavara and Mala. 4.JSP had minimal impact on Kapu vote bank due to weak leadership in the village | K53: TDP>YCP>JSP | L53: 1. TDP has stronghold in major BC communities (K.Velama, Padmashali & Yadava) 2.YSRCP will be impacted due to the high concentration of BC communities 2. JSP -TDP alliance will have less impact in driving the Kapu vote bank in the village | M53: Strong | N53: Strong Cadre and Strong Leadership | O53: Medium | P53: Strong Cadre Weak Leadership | Q53: Medium | R53: Strong Cadre Weak Leadership | S53: Negative | T53: No Development | W53: Complete
A54: Tuni | B54: Tuni | C54: =IFERROR(__xludf.DUMMYFUNCTION("filter('Back End'!C:C,'Back End'!A:A=A54,'Back End'!B:B=B54,'Back End'!D:D=D54)"),"#REF!") -> #REF! | D54: Dondavaka | E54: Battleground | G54: TDP Closely Trailing | H54: 1.Farmers(Paddy) 2.Agricultural labours | I54: Leader Dominance | J54: 1. This is OC Kapu's dominant village which is split among all three parties JSP, TDP, and JSP. However YSRCP secures majority of the Kapu vote bank in the village due to the MLA's candidature 2. YCP was able secure maximum SC (Mala) vote bank along with Nayi Brahmin vote bank in the village 3. TDP was able to secure Rajaka, Koppula Velama and Yadava community vote bank in the village | K54: YCP>TDP>JSP | L54: 1. JSP has a strong presence in the Kapu community ) and also the TDP+JSP alliance will help to consolidate the majority of the vote bank from Kapu as well as Settibalija BC community. | M54: Strong | N54: Strong Cadre and Strong Leadership | O54: Medium | P54: Strong Cadre Weak Leadership | Q54: Medium | R54: Strong Cadre Weak Leadership | S54: Negative | T54: No Development | U54: 1. In the governce of TDP housing sites were given and are occupied by YSRCP in their governance native village of Dadi Setti Raja | W54: Complete
A55: Tuni | B55: Tuni | C55: =IFERROR(__xludf.DUMMYFUNCTION("filter('Back End'!C:C,'Back End'!A:A=A55,'Back End'!B:B=B55,'Back End'!D:D=D55)"),"#REF!") -> #REF! | D55: Kolimeru | E55: Difficult | G55: TDP Trailing | H55: 1. Farmers 2. Agriculture Labour | I55: Caste Composition | J55: 1.The top castes in the village (Mala & Kapu) are inclined towards YSRCP 2. TDP is banking on Setti Balija and minor BCs in the village but their population very less compared to Mala & Kapu communities 3. JSP has minimal impact due to lack of leadership in the village | K55: JSP>YCP>TDP | L55: 1. This village has issues between Mala and Kapu communities due to local dynamics which might favour opposition parties 2. There are high chances of spliting Kapu vote bank in the village due to JSP alliance which will favour TDP 3. JSP is lacking leadership in Kapu community | M55: Weak | N55: Weak Leadership & Weak Cadre | O55: Strong | P55: Strong Cadre and Strong Leadership | Q55: Medium | R55: Strong Cadre Weak Leadership | S55: Mixed | T55: Positive Image Welfare Schemes | U55: 1. Mala vs Kapu fight be can be capitalised in the village in order gain Kapu vote bank (Kapu guy harassed Mala girl in the village) 2. Sarpanch has pending bills of 20 Lakhs for infra works | W55: Complete
A56: Tuni | B56: Tuni | C56: =IFERROR(__xludf.DUMMYFUNCTION("filter('Back End'!C:C,'Back End'!A:A=A56,'Back End'!B:B=B56,'Back End'!D:D=D56)"),"#REF!") -> #REF! | D56: Tetagunta | E56: Difficult | G56: TDP Trailing | H56: 1. Paddy Farmers 2. Masons 3. Toddy Tappers | I56: Internal Conflicts | J56: 1. This village witnessed fight between Kapu vs Yadava communities and the majority of the BC communities Perika, Rajaka along with SC communities (Mala & Madiga) communities inclined towards YSRCP due to strong leadership in the village. 2. TDP is banking on the Yadava vote bank along with a section of the Setti Balija community. 3. Despite the high concentration of the Kapu vote bank JSP has minimal presence due to lack of local leadership. | K56: YCP>TDP>JSP | L56: 1. YSRCP strong Vote bank in Kapu and SC communities 2. TDP has a Yadava vote bank but lacks support in other BC communities 3. JSP has minimal presence | M56: Medium | N56: weak leadership and strong cadre | O56: Strong | P56: Strong Cadre and Strong Leadership | Q56: Weak | R56: Weak Leadership & Weak Cadre | S56: Mixed | T56: Positive Image Welfare Schemes | U56: 1 YSRCP Sarpanch is dissatisfied with the government due to pending bills and salaries of sanitation workers of GP 2)TDP MLA candidate Yanmala Divya has a guest house in Yerra Koneru. 3. Sarpanch Atti Nagaraju(Perika) is the least influential and worked as a servant in Kshatriya community. | W56: Complete
A57: Prathipadu | B57: Rowthulapudi | C57: =IFERROR(__xludf.DUMMYFUNCTION("filter('Back End'!C:C,'Back End'!A:A=A57,'Back End'!B:B=B57,'Back End'!D:D=D57)"),"#REF!") -> #REF! | D57: Gidajam | E57: Difficult | F57: TDP Trailing | G57: TDP Trailing | H57: 1.Paddy Farming | I57: Caste Composition | J57: 1. This is the OC and SC dominant village with the majority of vote banks from both the castes. 2. OC (Kapu ) and SC (Mala and Madiga) are majorly inclined towards to YCP. | K57: YCP>TDP>JSP | L57: 1. TDP is banking on split votes of Madiaga and Kapu. 2. YCP is banking on kapu,Mala, and other minorities of the BC caste (Settibalija) | M57: Medium | N57: Strong Cadre Weak Leadership | O57: Strong | P57: Strong Cadre Weak Leadership | Q57: Weak | R57: Weak Leadership & Weak Cadre | S57: Mixed | T57: Positive Image Welfare Schemes | V57: Because the YSRCP family holds government employment and the TDP lacks active leaders, the YSRCP won the Sarpanch election while the TDP won the MPTC. If money is distributed, the YSRCP wins. | W57: Complete
A58: Prathipadu | B58: Sankhavaram | C58: =IFERROR(__xludf.DUMMYFUNCTION("filter('Back End'!C:C,'Back End'!A:A=A58,'Back End'!B:B=B58,'Back End'!D:D=D58)"),"#REF!") -> #REF! | D58: Gowrampeta | E58: Difficult | G58: TDP Trailing | H58: Farmers | I58: Impact of Janmabhoomi Commitees | J58: 1. Good image on Jagan 2.Impact of Janmabhoomies Commities | K58: YCP>TDP>JSP | L58: 1.Good Schmes,Selfless Service 2.The Manifesto Given By TDP Was Not Implemented | M58: Weak | N58: Weak Leadership & Weak Cadre | O58: Strong | P58: Strong Cadre and Strong Leadership | Q58: Weak | R58: Weak Leadership & Weak Cadre | S58: Positive | T58: Positive Image Welfare Schemes | W58: Incomplete
A59: Prathipadu | B59: Sankhavaram | C59: =IFERROR(__xludf.DUMMYFUNCTION("filter('Back End'!C:C,'Back End'!A:A=A59,'Back End'!B:B=B59,'Back End'!D:D=D59)"),"#REF!") -> #REF! | D59: Kathipudi | E59: Battleground | G59: Dead Heat | H59: Farmers(paddy), cashew farming | I59: Caste Composition | J59: 1. In This completely Kapu-dominant village, the community is able to split between all three parties due to local leadership (Venna Eswarudu-TDP, Gothu Subramanyam-YCP, Medisetti Suryakiran-JSP). 2. TDP is completely banking on the BC Community (Yadavas). 3. YCP is completely banking on the SC community (Mala and Madiga) along with split votes of Kapu. | K59: YCP>TDP>JSP | L59: 1.YCP is completely banking on the SC community (Mala and Madiga) along with split votes of Kapu along with local leadership (Gothu Subramanyam-YCP). 2.2. JSP has a strong presence in the Kapu community and the TDP+JSP alliance will help to consolidate the majority of the vote bank | M59: Strong | N59: Strong Cadre and Strong Leadership | O59: Strong | P59: Strong Cadre and Strong Leadership | Q59: Weak | R59: Weak Leadership & Weak Cadre | S59: Positive | T59: Positive Image Welfare Schemes | W59: Complete
A60: Jaggampeta | B60: Kirlampudi | C60: =IFERROR(__xludf.DUMMYFUNCTION("filter('Back End'!C:C,'Back End'!A:A=A60,'Back End'!B:B=B60,'Back End'!D:D=D60)"),"#REF!") -> #REF! | D60: Mukkollu | E60: Battleground | F60: TDP Ahead | G60: Dead Heat | H60: 1.Agriculture(paddy) | I60: Caste Composition | J60: 1. This is a completely Kapu-dominant village, the community is split between YCP and TDP Parties due to local leadership. 2. YCP is completely banking on the SC Community (Mala ) along with Kapu Vote Bank. 3. TDP is dependent on Kapu along with the minimum votes bank from the BC community (Sagara). | K60: TDP>YCP>JSP | L60: 1. The TDP+JSP alliance will play a major role in the consolidation of the Kapu community. 2. YSRCP is banking on the Mala and Kapu vote banks in the village 3. TDP MLA Jyothula Nehru is very responsive towards people in development and also helps the public. 4.YCP MLA Jyothula Chanti Babu is not all considering public opinions or helping them hence this village is completely against YCP. | M60: Strong | N60: Strong Cadre and Strong Leadership | O60: Medium | P60: Medium leadership medium vote bank | Q60: Weak | R60: Weak Leadership & Weak Cadre | S60: Negative | T60: No Development | U60: 1.2 lakh bill related to the ground is pending. | W60: Complete | Y60: Jayasri
A61: Prathipadu | B61: Yeleswaram | C61: =IFERROR(__xludf.DUMMYFUNCTION("filter('Back End'!C:C,'Back End'!A:A=A61,'Back End'!B:B=B61,'Back End'!D:D=D61)"),"#REF!") -> #REF! | D61: C. Rayavaram | E61: Battleground | G61: Dead Heat | H61: 1. Farmers 2. Daily Labour | I61: Anti-Incumbency on TDP | J61: 1. The major communities Kapu and Yadava communities voted in favour of YSRCP due to the anti-incumbency on MLA Varma 2. Other BCs (Rajaka) and Mala communities voted in favour of YSRCP due to last election wave. Still TDP managed secure traditional support of Yadava community failed to curtail split in the community | K61: YCP>TDP>JSP | L61: 1. This village has Kapu and Yadava communities as dominant ones and inclined towards YSRCP and TDP respectively. 2. JSP has the support of Kapu youth in the village but lacks leadership | M61: Medium | N61: Strong Cadre Weak Leadership | O61: Strong | P61: Strong Cadre Weak Leadership | Q61: Weak | R61: Weak Leadership & Weak Cadre | S61: Positive | T61: Positive Image Welfare Schemes | U61: 1. Sarpanch has pending bills for Drainage works and disgruntled with YCP government | W61: Complete
A62: Peddapuram | B62: Samalkota | C62: =IFERROR(__xludf.DUMMYFUNCTION("filter('Back End'!C:C,'Back End'!A:A=A62,'Back End'!B:B=B62,'Back End'!D:D=D62)"),"#REF!") -> #REF! | D62: PANASAPADU | E62: Safe | G62: TDP Ahead | H62: Famers, Mason Building workers | I62: Leader Dominance | J62: 1.This is a Kapu and Settibalija-dominated village and TDP was able to secure a majority of the Settibalija vote bank along with minor BC communities (Yadav, Rajaka & Kummari). 2. The Kapu community was split between YSRCP and JSP due to local leadership and MLA's candidature. | K62: TDP>YCP>JSP | L62: 1)TDP has a strong vote bank due to the high concentration of BC communities such as Settibalija, Yadava 2)TDP-JSP alliance will play a major role in the consolidation of the Kapu community 3. YSRCP is banking on the Mala and Kapu vote bank in the village | M62: Strong | N62: Strong Cadre and Strong Leadership | O62: Medium | P62: Strong Cadre Weak Leadership | Q62: Strong | R62: Strong Cadre and Strong Leadership | S62: Negative | T62: No Development | W62: Complete
A63: Kakinada Rural | B63: Karapa | C63: =IFERROR(__xludf.DUMMYFUNCTION("filter('Back End'!C:C,'Back End'!A:A=A63,'Back End'!B:B=B63,'Back End'!D:D=D63)"),"#REF!") -> #REF! | D63: KURADA | E63: Difficult | G63: TDP Trailing | H63: 1.Farmers (Paddy) | I63: Caste Composition | J63: 1. This is the OC (Kapu) and BC (settibalija) dominant village. 2.YCP has a strong hold in the Kapu community, the majority of SC (Mala and Madiga ), along with the swing of minor communities from BC communities(Padmashali, Rajaka, Kummari). 3. TDP is totally banking on BC communities ( Settibalija) but still did not able to grasp full vote bank. | K63: YCP>TDP>JSP | L63: 1. There is a high chance of gaining major votes if TDP +JSP go in alliance. 2. There is a high chance of losing votes from TDP from BC community Settibalija if both local leaderships are from BC and OC communities. | M63: Strong | N63: Strong Cadre and Strong Leadership | O63: Strong | P63: Strong Cadre and Strong Leadership | Q63: Medium | R63: Strong Cadre Weak Leadership | S63: Positive | T63: Positive Image Welfare Schemes | U63: 1. Pending bills on sanitization nearly 80,000/- 2. Electrical bills are still pending. | W63: Complete
A64: Prathipadu | B64: Yeleswaram | C64: Ramanayyapeta | D64: Ramanayyapeta | E64: Difficult | G64: TDP Trailing | H64: Daily Labours, Farmers | I64: Caste Composition | J64: 1. This is a completely SC-dominant village (Mala and Madiga ). 2. TDP Completely banked on the BC Community(Padmashali) along with minor voting from the SC Community. 3. YCP completely banked on the majority of SC Community. | K64: YCP>TDP>JSP | L64: 1. Due to the high concentration of SC belt TDP alone or the alliance with JSP may not help both parties in gaining the vote bank. | M64: Weak | N64: Weak Leadership & Weak Cadre | O64: Strong | P64: Strong Cadre and Strong Leadership | Q64: Weak | R64: Weak Leadership & Weak Cadre | S64: Positive | T64: Positive Image Welfare Schemes | W64: Complete
A65: Peddapuram | B65: Samalkota | C65: =IFERROR(__xludf.DUMMYFUNCTION("filter('Back End'!C:C,'Back End'!A:A=A65,'Back End'!B:B=B65,'Back End'!D:D=D65)"),"#REF!") -> #REF! | D65: Pandravada | E65: Favourable | G65: TDP Closely Ahead | H65: 1.Farmers 2. Construction Labour 3. Masons 4. Drivers 5. Agriculture Labour | I65: Leader Dominance | J65: 1. This is Setti Balija-dominated village and the majority of them are inclined toward TDP. 2. Mala, Madiga & Minor BCs (Rajaka) inclined towards YSRCP due to the local leadership. | K65: TDP>YCP>JSP | L65: 1. High Concentration of Setti Balija Vote Bank favours TDP 2. Less SC communities presence in the village | M65: Strong | N65: Strong Cadre and Strong Leadership | O65: Medium | P65: Strong Leadership but Weak Vote Bank | Q65: Weak | R65: Weak Leadership & Weak Cadre | S65: Negative | T65: No Development | U65: 1. Sarpanch has pending bills of 3-4 lakhs (water motors, street lights & drinking water issues) | W65: Complete
A66: Kakinada Rural | B66: Karapa | C66: =IFERROR(__xludf.DUMMYFUNCTION("filter('Back End'!C:C,'Back End'!A:A=A66,'Back End'!B:B=B66,'Back End'!D:D=D66)"),"#REF!") -> #REF! | D66: NADAKUDURU | E66: Difficult | G66: TDP Trailing | H66: 1. Port Labour 2. Daily Labour 3. Agriculture Labour | I66: Anti-Incumbency on TDP | J66: 1. The majority of the K. Velama community voted in favour of YSRCP due to the previous election wave. 2. The Kapu community is split between YSRCP and JSP due to the respective MLA's candidature. 3. SettiBalija and Minor BC communities are inclined towards TDP. | K66: YCP>TDP>JSP | L66: 1. Majority of top communities Kapu and K.Velama communities inclined towards YSRCP though JSP was able to split up Kapu vote bank 2. TDP is failed to consolidate BC vote bank due to lack of local leadership | M66: Weak | N66: Weak Leadership & Weak Cadre | O66: Strong | P66: Strong Cadre and Strong Leadership | Q66: Medium | R66: weak leadership and strong cadre | S66: Positive | T66: Positive Image Welfare Schemes | W66: Complete
A67: Prathipadu | B67: Yeleswaram | C67: Tirumalayapalem | D67: Tirumalayapalem | E67: Favourable | G67: TDP Closely Ahead | H67: 1. Farmers 2. Agriculture Labour | I67: Leader Dominance | J67: 1. The majority of the Kapu along with BC communities inclined towards TDP due to the local leadership. 2. YSRCP was banking on Kapu, Minor BC communities and a section of Kapu inclined towards YSRCP due to MLA's candidature. | K67: TDP>YCP>JSP | L67: 1. High concentration of Kapu community along BC communities 2. YCP focused Mala and Minor BC communities 3. JSP has minimal impact on Kapu community | M67: Strong | N67: Strong Cadre and Strong Leadership | O67: Strong | P67: Strong Cadre and Strong Leadership | Q67: Weak | R67: Weak Leadership & Weak Cadre | S67: Positive | T67: Positive Image Welfare Schemes | U67: 1. Sarpanch has pending bills of 15 Lakhs for Infra Works (Drainages, Bores) | W67: Complete
A68: Peddapuram | B68: Samalkota | C68: =IFERROR(__xludf.DUMMYFUNCTION("filter('Back End'!C:C,'Back End'!A:A=A68,'Back End'!B:B=B68,'Back End'!D:D=D68)"),"#REF!") -> #REF! | D68: UNDURU | E68: Difficult | G68: TDP Trailing | H68: 1. Farmers | I68: JSP Split the Votes | J68: 1. This is dominated by the Kapu community and JSP split the Kapu vote bank of TDP which impacted the prospects in the village. 2. Mala constituted 1500 votes and unanimously supported YSRCP in the previous elections. 3. TDP failed to consolidate the BC vote bank (Setti Balija) due to a lack of local leadership. | K68: YCP>JSP>TDP | L68: 1. High concerntration of Kapu vote bank and split between YSRCP and JSP 2. Mala and other minor BC communities inclined towards YSRCP | M68: Weak | N68: Weak Leadership & Weak Cadre | O68: Strong | P68: Strong Cadre and Strong Leadership | Q68: Medium | R68: weak leadership and strong cadre | S68: Positive | T68: Positive Image Welfare Schemes | W68: Complete
A69: Jaggampeta | B69: Kirlampudi | C69: =IFERROR(__xludf.DUMMYFUNCTION("filter('Back End'!C:C,'Back End'!A:A=A69,'Back End'!B:B=B69,'Back End'!D:D=D69)"),"#REF!") -> #REF! | D69: Palem | E69: Battleground | G69: Dead Heat | H69: 1. Agriclture Labour 2. Factory Labour | I69: Anti-Incumbency on TDP | J69: 1. There is a split in the Kapu community between YSRCP and TDP in previous elections 2. The majority of the minor BC communities voted in favour of YSRCP due to the Jagan Manifest promises. 3. JSP had minimal impact on the Kapu community. | K69: YCP>TDP>JSP | L69: 1. Kapu community split between YSRCP & TDP 2. YSRCP is sligly ahed in minor BC communities due to welfare schemes 3. JSP alliance will play very minimal role in the village | M69: Medium | N69: Weak Leadership & Weak Cadre | O69: Strong | P69: Strong Cadre and Strong Leadership | Q69: Medium | R69: Weak Leadership & Weak Cadre | S69: Mixed | T69: Positive Image Welfare Schemes | U69: Sarpanch has pending bills of 80,000 and disgruntled with YSRCP government | W69: Complete | Y69: Jayasri
A70: Jaggampeta | B70: Kirlampudi | C70: =IFERROR(__xludf.DUMMYFUNCTION("filter('Back End'!C:C,'Back End'!A:A=A70,'Back End'!B:B=B70,'Back End'!D:D=D70)"),"#REF!") -> #REF! | D70: Rajupalem | E70: Battleground | G70: Dead Heat | H70: 1.Paddy Agriculture | I70: Caste Composition | J70: 1.This OC (Kapu) and BC (Perika) dominant village which is split between TDP and YCP. 2.YSRCP is banking totally on sc (Mala and Madiga) with slight edge of OC (Kapu )vote bank along with the swing of BC (perika) community. | K70: YCP>TDP>JSP | L70: 1. YSRCP has a strong vote bank in the village in Kapu,Perika and Mala communities along with strong Local leadership(Ganeshula Rambabu) and are satisfied with welfare schemes and developments. | M70: Medium | N70: Weak Leadership & Weak Cadre | O70: Strong | P70: Strong Cadre and Strong Leadership | Q70: Weak | R70: Weak Leadership & Weak Cadre | S70: Positive | T70: Positive Image Welfare Schemes | W70: Complete
A71: Kakinada Rural | B71: Karapa | C71: =IFERROR(__xludf.DUMMYFUNCTION("filter('Back End'!C:C,'Back End'!A:A=A71,'Back End'!B:B=B71,'Back End'!D:D=D71)"),"#REF!") -> #REF! | D71: Penuguduru | E71: Battleground | G71: Dead Heat | H71: Farmers(Paddy) | I71: welfare schemes | J71: 1.This is OC Kapu dominant village,the community is split between the two parties of TDP and YCP. 2.JSP has a very good presence in the Kapu community and can split a good share of votes intended for the YSRCP party. 3. YSRCP is totally banking on SC communities( Mala ) along with a swing of kapu vote share and other minor BC communities. | K71: YCP>TDP>JSP | L71: 1.YSRCP is totally banking on SC communities( Mala ) along with a swing of kapu vote share and other minor BC communities and local leadership may also play a crucial role. 2. JSP has a very good presence in the Kapu community, the TDP+JSP alliance is an added advantage along with a majority vote share from the BC community(Settibalija). | M71: Strong | N71: Strong Cadre and Strong Leadership | O71: Strong | P71: Strong Cadre and Strong Leadership | Q71: Medium | R71: Strong Cadre Weak Leadership | S71: Positive | T71: Positive Image Welfare Schemes | W71: Complete
A72: Prathipadu | B72: Yeleswaram | C72: =IFERROR(__xludf.DUMMYFUNCTION("filter('Back End'!C:C,'Back End'!A:A=A72,'Back End'!B:B=B72,'Back End'!D:D=D72)"),"#REF!") -> #REF! | D72: Yerravaram | E72: Battleground | G72: Dead Heat | H72: 1. Farmers (Sugar Cane, Paddy, Banana) 2. Agriculture Labour | I72: Anti-Incumbency on TDP | J72: 1. Though the major communities Kapu & Perika communities split between YSRCP and TDP, YSRCP took the slight lead in these communities. 2. YSRCP was successful in consolidating Mala and other minor BC communities due to a wave in the previous elections. 3. JSP secured a minimal amount of Kapu vote share in the village. | K72: YCP>TDP>JSP | L72: 1. Both YSRCP and TDP has strong vote bank and leadership in the village 2. JSP impact restricted to Kapu community | M72: Strong | N72: Strong Cadre and Strong Leadership | O72: Strong | P72: Strong Cadre and Strong Leadership | Q72: Weak | R72: weak leadership and strong cadre | S72: Positive | T72: Positive Image Welfare Schemes | U72: 1. GP has pending general funds of 5 lakhs and pending 10 lakhs under 15th finance commission | W72: Complete
A73: Peddapuram | B73: Samalkota | C73: =IFERROR(__xludf.DUMMYFUNCTION("filter('Back End'!C:C,'Back End'!A:A=A73,'Back End'!B:B=B73,'Back End'!D:D=D73)"),"#REF!") -> #REF! | D73: VENKATAKRISHNARAYAPURAM | E73: Difficult | G73: TDP Trailing | H73: Farmers | I73: welfare schemes | J73: 1.YCP Won Because Of His Father Influence(Y S Rajashekhar Reddy) And Padayathra Programme Inpressed To Peoples | K73: YCP>TDP>JSP | L73: welfare schemes | M73: Medium | N73: Strong Cadre Weak Leadership | O73: Strong | P73: Strong Cadre and Strong Leadership | Q73: Weak | R73: Weak Leadership & Weak Cadre | S73: Positive | T73: Positive Image Welfare Schemes | W73: Incomplete
A74: Peddapuram | B74: Samalkota | C74: =IFERROR(__xludf.DUMMYFUNCTION("filter('Back End'!C:C,'Back End'!A:A=A74,'Back End'!B:B=B74,'Back End'!D:D=D74)"),"#REF!") -> #REF! | D74: VETLAPALEM | E74: Difficult | G74: TDP Trailing | H74: Farmers | I74: Impact of Janmabhoomi Commitees | J74: """1.Good image on Jagan 2.Impact OF Janmabhoomies Commities" | K74: YCP>TDP>JSP | L74: welfare schemes | M74: Medium | N74: Strong Cadre Weak Leadership | O74: Strong | P74: Strong Cadre and Strong Leadership | Q74: Weak | R74: Weak Leadership & Weak Cadre | S74: Positive | T74: Positive Image Welfare Schemes | W74: Incomplete
A75: Jaggampeta | B75: Kirlampudi | C75: =IFERROR(__xludf.DUMMYFUNCTION("filter('Back End'!C:C,'Back End'!A:A=A75,'Back End'!B:B=B75,'Back End'!D:D=D75)"),"#REF!") -> #REF! | D75: Simhadri Puram | E75: Difficult | F75: TDP Closely Trailing | G75: TDP Closely Trailing | H75: 1.Farmers(,vegetables,cotton) 2.Palm oil company | I75: Leader Dominance | J75: 1. This is Kapu OC dominant village which is split between YSRCP and TDP. 2. YSRCP majorly banked on SC ( Mala and Madiga) along with the support of Kapu Vote Bank due to MLAS candidature. | K75: YCP>TDP>JSP | L75: 1. YCP MLA Jyothula Chanti Babu is positive in public as he is very responsive to them and helped them in many developments and people are also highly satisfied with the schemes. 2.TDP has a little way due to some disgruntled leaders in YCP party and this may become an X Factor | M75: Medium | N75: Strong Cadre and Strong Leadership | O75: Weak | P75: Weak Leadership & Weak Cadre | Q75: Weak | R75: Weak Leadership & Weak Cadre | S75: Negative | T75: No Development | U75: 1.pending bills on Sachyvalayam and Panchayath (total 14 lakhs) 2. local leader kalpureddy papayam (Kapu ,YSRCP) is disgruntled with the party | W75: Complete | Y75: Jayasri
A76: Jaggampeta | B76: Gokavaram | C76: =IFERROR(__xludf.DUMMYFUNCTION("filter('Back End'!C:C,'Back End'!A:A=A76,'Back End'!B:B=B76,'Back End'!D:D=D76)"),"#REF!") -> #REF! | D76: Gummalladuddi | E76: Battleground | G76: Dead Heat | H76: 1. Agriculture (paddy) 2.Drivers 3.Construction worker and daily labour | I76: Caste Composition | J76: 1. This village is BC dominated village, currently TDP is slightly ahead than YSRCP. The BCs are currently inclined towards TDP 2. YSRCP is slightly on backfoot due to disatisfaction among its leadership | K76: TDP>YCP>JSP | L76: With BC communities and Kapu in support of JSP alliance TDP is ahead in this village | M76: Strong | N76: Strong Cadre and Strong Leadership | O76: Medium | P76: Strong Leadership but Weak Vote Bank | Q76: Weak | R76: Weak Leadership & Weak Cadre | S76: Negative | T76: No Development | U76: 1. Street Lights, Water Motors Repaire Bills are Pending 2. 15th Finance commssion pending amount 5 lakhs is pending | W76: Complete
A77: Jaggampeta | B77: Gokavaram | C77: =IFERROR(__xludf.DUMMYFUNCTION("filter('Back End'!C:C,'Back End'!A:A=A77,'Back End'!B:B=B77,'Back End'!D:D=D77)"),"#REF!") -> #REF! | D77: Kothapalle | E77: Difficult | G77: TDP Trailing | H77: 1. Agriculture (Paddy) 2.Weavers 3.Pot makers | I77: Caste Composition | J77: 1.This is completely OC (kapu) and SC (Mala) dominant village which are completely inclined towards YSRCP . | K77: YCP>TDP>JSP | L77: 1. TDP is banking on the BC community (Settibalija)and other minor communities. 2. The TDP +JSP alliance many not have much effect as YSRCP is totally supported by Kapu and SC communities and also due to local MLAS candidature. | M77: Weak | N77: Weak Leadership & Weak Cadre | O77: Strong | P77: Strong Cadre and Strong Leadership | Q77: Weak | R77: Weak Leadership & Weak Cadre | S77: Positive | T77: Positive Image Welfare Schemes | W77: Complete
A78: Jaggampeta | B78: Gokavaram | C78: =IFERROR(__xludf.DUMMYFUNCTION("filter('Back End'!C:C,'Back End'!A:A=A78,'Back End'!B:B=B78,'Back End'!D:D=D78)"),"#REF!") -> #REF! | D78: GOKAVARAM | E78: Battleground | G78: Dead Heat | H78: 1.Farmers(Paddy,Sweet corn) 2.Lorry driver | I78: JSP Split the Votes | J78: 1. This is the OC (Kapu) and BC (Thurpu Kapu) dominant village which are split between TDP, YCP, and JSP. 2. YCP is totally banking on the SC (Mala )community along with split votes of Kapu and other minority votes BC caste. 3. JSP was able to split a decent amount of Kapu vote share which dented the prospects of both TDP & YSRCP in the village. | K78: YCP>TDP>JSP | L78: 1.OC (kapu) and Thurpu kapu (BC)communities are slightly disgruntled with the leadership due to the lack of development in the village. 2.JSP has a strong presence in the Kapu community and the TDP+JSP alliance will help to consolidate the majority of the vote bank | M78: Strong | N78: Strong Cadre and Strong Leadership | O78: Strong | P78: Strong Cadre and Strong Leadership | Q78: Weak | R78: Weak Leadership & Weak Cadre | S78: Negative | T78: No Development | U78: 1. Pending bills of 2 lakhs for drainage. 2. Pending bills on slabs for the market | W78: Complete
A79: Kakinada Rural | B79: Karapa | C79: =IFERROR(__xludf.DUMMYFUNCTION("filter('Back End'!C:C,'Back End'!A:A=A79,'Back End'!B:B=B79,'Back End'!D:D=D79)"),"#REF!") -> #REF! | D79: VAKADA | E79: Difficult | G79: TDP Trailing | H79: Farmers | I79: Caste Composition | J79: 1.YCP got majority votes from the kapu caste and Kana babu is a strong Leader 2.TDP lost due to local Leaders did not do the campaign Properly. | K79: YCP>TDP>JSP | L79: YCP has high Majority to come because He developed so much and gave so many helpful Schemes | M79: Medium | N79: Strong Cadre Weak Leadership | O79: Strong | P79: Strong Cadre and Strong Leadership | Q79: Weak | R79: Weak Leadership & Weak Cadre | S79: Positive | T79: Positive Image Welfare Schemes | W79: Review
A80: Kakinada Rural | B80: Karapa | C80: =IFERROR(__xludf.DUMMYFUNCTION("filter('Back End'!C:C,'Back End'!A:A=A80,'Back End'!B:B=B80,'Back End'!D:D=D80)"),"#REF!") -> #REF! | D80: Vemulavada | E80: Battleground | G80: Dead Heat | H80: 1.Agriculture(Paddy) | I80: Caste Composition | J80: 1.This is Kapu dominant village , the community is majorly split between YSRCP and JSP. 2. Ysrcp is banking on SC communities (Mala ) along with other minor communities of BC and majority of kapu community. 3.Jsp has good hold in Kapu community which able to secure vote share from kapu tended to YSRCP . | K80: YCP>TDP>JSP | L80: 1.TDP has a strong presence in the Kapu community and the TDP+JSP alliance will help to consolidate the majority of the vote bank | M80: Medium | N80: Strong Cadre Weak Leadership | O80: Strong | P80: Strong Cadre and Strong Leadership | Q80: Weak | R80: weak leadership and strong cadre | S80: Positive | T80: Positive Image Welfare Schemes | U80: 1.pending bills on graveyard,CC Roads and drainage | W80: Complete
A81: Jaggampeta | B81: Gokavaram | C81: =IFERROR(__xludf.DUMMYFUNCTION("filter('Back End'!C:C,'Back End'!A:A=A81,'Back End'!B:B=B81,'Back End'!D:D=D81)"),"#REF!") -> #REF! | D81: MALLAVARAM | E81: Difficult | G81: TDP Closely Trailing | H81: 1. Agricultural Farming 2.Potato starch | I81: Caste Composition | J81: 1. This is Thurpu Kapu's dominant village which is majorly inclined towards YCP and rest to TDP. 2. YCP banked on the majority of Thurpu kapu along with SC, ST, and OC (Mala, Kapu, and Konda Dora). 3.JSP has no bare minimum presence in this village. | K81: YCP>TDP>JSP | L81: 1. YCP has a positive image due to the success of welfare schemes. 2. There is more chance for YCP to win this election because of welfare schemes like Cheyutha and Vidya Deevana. The majority of the vote composition is towards YCP 2. YCP has a strong vote bank in the Kapu Community due to the key local YCP leader hailing from the Thurpu Kapu community | M81: Medium | N81: Medium Leadership but low vote bank | O81: Strong | P81: Strong Cadre and Strong Leadership | Q81: Weak | R81: Weak Leadership & Weak Cadre | S81: Positive | T81: Positive Image Welfare Schemes | U81: 1.Pending bills of 8lakhs on Sachyavalayam buildings and RBK buildings | W81: Review | Y81: Jayasri
